Workbook

Sheet MR-AR
B1: Coresphere100 Technologies Pvt. Ltd.
B2: Monthly Recurring Revenue
B3: From Apr 25 to Oct 25
B5: Particulars | C5: For the month ended | D5: For the month ended | E5: For the month ended | F5: For the month ended | G5: For the month ended | H5: For the month ended | I5: For the month ended
C6: 45748 | D6: 45778 | E6: 45809 | F6: 45839 | G6: 45870 | H6: 45901 | I6: 45931
B7: Total monthly revenue from B2B subscribers excluding GST (A) | C7: =SUM(C9:C47) -> 1741620.9 | D7: =SUM(D9:D47) -> 2163257.6 | E7: =SUM(E9:E47) -> 2564306.8 | F7: =SUM(F9:F47) -> 3134923.8 | G7: =SUM(G9:G47) -> 3859051.3 | H7: =SUM(H9:H47) -> 4595146.1 | I7: =SUM(I9:I47) -> 5204678.9
B9: Annual Subscription
B10: Annual- Half Yearly Payment | C10: =SUMIF(Pivot!$A$2:$A$42,'MR-AR'!B10,Pivot!$B$2:$B$42)/118% -> 51835.311 | D10: =SUMIF(Pivot!$A$2:$A$42,'MR-AR'!B10,Pivot!$C$2:$C$42)/118% -> 294835.31 | E10: =SUMIF(Pivot!$A$2:$A$42,'MR-AR'!B10,Pivot!$D$2:$D$42)/118% -> 294835.31 | F10: =SUMIF(Pivot!$A$2:$A$42,'MR-AR'!B10,Pivot!$E$2:$E$42)/118% -> 316751.98 | G10: =SUMIF(Pivot!$A$2:$A$42,'MR-AR'!B10,Pivot!$F$2:$F$42)/118% -> 981618.64 | H10: =SUMIF(Pivot!$A$2:$A$42,'MR-AR'!B10,Pivot!$G$2:$G$42)/118% -> 1024702 | I10: =SUMIF(Pivot!$A$2:$A$42,'MR-AR'!B10,Pivot!$H$2:$H$42)/118% -> 1214135.3
B11: Annual subscription, Quarterly upfront | C11: =SUMIF(Pivot!$A$2:$A$42,'MR-AR'!B11,Pivot!$B$2:$B$42)/118% -> 48276.836 | D11: =SUMIF(Pivot!$A$2:$A$42,'MR-AR'!B11,Pivot!$C$2:$C$42)/118% -> 48276.836 | E11: =SUMIF(Pivot!$A$2:$A$42,'MR-AR'!B11,Pivot!$D$2:$D$42)/118% -> 96276.836 | F11: =SUMIF(Pivot!$A$2:$A$42,'MR-AR'!B11,Pivot!$E$2:$E$42)/118% -> 180776.84 | G11: =SUMIF(Pivot!$A$2:$A$42,'MR-AR'!B11,Pivot!$F$2:$F$42)/118% -> 355799.44 | H11: =SUMIF(Pivot!$A$2:$A$42,'MR-AR'!B11,Pivot!$G$2:$G$42)/118% -> 446418.08 | I11: =SUMIF(Pivot!$A$2:$A$42,'MR-AR'!B11,Pivot!$H$2:$H$42)/118% -> 511638.42
B12: Annual Upfront | C12: =SUMIF(Pivot!$A$2:$A$42,'MR-AR'!B12,Pivot!$B$2:$B$42)/118% -> 653322.31 | D12: =SUMIF(Pivot!$A$2:$A$42,'MR-AR'!B12,Pivot!$C$2:$C$42)/118% -> 768915.25 | E12: =SUMIF(Pivot!$A$2:$A$42,'MR-AR'!B12,Pivot!$D$2:$D$42)/118% -> 1006485 | F12: =SUMIF(Pivot!$A$2:$A$42,'MR-AR'!B12,Pivot!$E$2:$E$42)/118% -> 1447016.8 | G12: =SUMIF(Pivot!$A$2:$A$42,'MR-AR'!B12,Pivot!$F$2:$F$42)/118% -> 1673643.1 | H12: =SUMIF(Pivot!$A$2:$A$42,'MR-AR'!B12,Pivot!$G$2:$G$42)/118% -> 1970881.1 | I12: =SUMIF(Pivot!$A$2:$A$42,'MR-AR'!B12,Pivot!$H$2:$H$42)/118% -> 2048228.6
B13: Annual-Monthly | C13: =SUMIF(Pivot!$A$2:$A$42,'MR-AR'!B13,Pivot!$B$2:$B$42)/118% -> 69033.051 | D13: =SUMIF(Pivot!$A$2:$A$42,'MR-AR'!B13,Pivot!$C$2:$C$42)/118% -> 78199.718 | E13: =SUMIF(Pivot!$A$2:$A$42,'MR-AR'!B13,Pivot!$D$2:$D$42)/118% -> 91674.294 | F13: =SUMIF(Pivot!$A$2:$A$42,'MR-AR'!B13,Pivot!$E$2:$E$42)/118% -> 157840.4 | G13: =SUMIF(Pivot!$A$2:$A$42,'MR-AR'!B13,Pivot!$F$2:$F$42)/118% -> 157840.4 | H13: =SUMIF(Pivot!$A$2:$A$42,'MR-AR'!B13,Pivot!$G$2:$G$42)/118% -> 222484.46 | I13: =SUMIF(Pivot!$A$2:$A$42,'MR-AR'!B13,Pivot!$H$2:$H$42)/118% -> 322755.65
B14: 2 Year- Upfront | C14: =SUMIF(Pivot!$A$2:$A$42,'MR-AR'!B14,Pivot!$B$2:$B$42)/118% -> 0 | D14: =SUMIF(Pivot!$A$2:$A$42,'MR-AR'!B14,Pivot!$C$2:$C$42)/118% -> 0 | E14: =SUMIF(Pivot!$A$2:$A$42,'MR-AR'!B14,Pivot!$D$2:$D$42)/118% -> 0 | F14: =SUMIF(Pivot!$A$2:$A$42,'MR-AR'!B14,Pivot!$E$2:$E$42)/118% -> 4021.7542 | G14: =SUMIF(Pivot!$A$2:$A$42,'MR-AR'!B14,Pivot!$F$2:$F$42)/118% -> 4021.7542 | H14: =SUMIF(Pivot!$A$2:$A$42,'MR-AR'!B14,Pivot!$G$2:$G$42)/118% -> 4021.7542 | I14: =SUMIF(Pivot!$A$2:$A$42,'MR-AR'!B14,Pivot!$H$2:$H$42)/118% -> 4021.7542
D15: =SUMIF(Pivot!$A$2:$A$42,'MR-AR'!B15,Pivot!$C$2:$C$42)/118% -> 0 | E15: =SUMIF(Pivot!$A$2:$A$42,'MR-AR'!B15,Pivot!$D$2:$D$42)/118% -> 0 | F15: =SUMIF(Pivot!$A$2:$A$42,'MR-AR'!B15,Pivot!$E$2:$E$42)/118% -> 0 | G15: =SUMIF(Pivot!$A$2:$A$42,'MR-AR'!B15,Pivot!$F$2:$F$42)/118% -> 0 | H15: =SUMIF(Pivot!$A$2:$A$42,'MR-AR'!B15,Pivot!$G$2:$G$42)/118% -> 0 | I15: =SUMIF(Pivot!$A$2:$A$42,'MR-AR'!B15,Pivot!$H$2:$H$42)/118% -> 0
B16: Other Than Annual Subscriptions | D16: =SUMIF(Pivot!$A$2:$A$42,'MR-AR'!B16,Pivot!$C$2:$C$42)/118% -> 0 | E16: =SUMIF(Pivot!$A$2:$A$42,'MR-AR'!B16,Pivot!$D$2:$D$42)/118% -> 0 | F16: =SUMIF(Pivot!$A$2:$A$42,'MR-AR'!B16,Pivot!$E$2:$E$42)/118% -> 0 | G16: =SUMIF(Pivot!$A$2:$A$42,'MR-AR'!B16,Pivot!$F$2:$F$42)/118% -> 0 | H16: =SUMIF(Pivot!$A$2:$A$42,'MR-AR'!B16,Pivot!$G$2:$G$42)/118% -> 0 | I16: =SUMIF(Pivot!$A$2:$A$42,'MR-AR'!B16,Pivot!$H$2:$H$42)/118% -> 0
B17: 10 -Days -Upfront | C17: =SUMIF(Pivot!$A$2:$A$42,'MR-AR'!B17,Pivot!$B$2:$B$42)/118% -> 0 | D17: =SUMIF(Pivot!$A$2:$A$42,'MR-AR'!B17,Pivot!$C$2:$C$42)/118% -> 0 | E17: =SUMIF(Pivot!$A$2:$A$42,'MR-AR'!B17,Pivot!$D$2:$D$42)/118% -> 0 | F17: =SUMIF(Pivot!$A$2:$A$42,'MR-AR'!B17,Pivot!$E$2:$E$42)/118% -> 8000 | G17: =SUMIF(Pivot!$A$2:$A$42,'MR-AR'!B17,Pivot!$F$2:$F$42)/118% -> 0 | H17: =SUMIF(Pivot!$A$2:$A$42,'MR-AR'!B17,Pivot!$G$2:$G$42)/118% -> 0 | I17: =SUMIF(Pivot!$A$2:$A$42,'MR-AR'!B17,Pivot!$H$2:$H$42)/118% -> 0
B18: 12 -Days -Upfront | C18: =SUMIF(Pivot!$A$2:$A$42,'MR-AR'!B18,Pivot!$B$2:$B$42)/118% -> 0 | D18: =SUMIF(Pivot!$A$2:$A$42,'MR-AR'!B18,Pivot!$C$2:$C$42)/118% -> 0 | E18: =SUMIF(Pivot!$A$2:$A$42,'MR-AR'!B18,Pivot!$D$2:$D$42)/118% -> 0 | F18: =SUMIF(Pivot!$A$2:$A$42,'MR-AR'!B18,Pivot!$E$2:$E$42)/118% -> 0 | G18: =SUMIF(Pivot!$A$2:$A$42,'MR-AR'!B18,Pivot!$F$2:$F$42)/118% -> 3483.8983 | H18: =SUMIF(Pivot!$A$2:$A$42,'MR-AR'!B18,Pivot!$G$2:$G$42)/118% -> 0 | I18: =SUMIF(Pivot!$A$2:$A$42,'MR-AR'!B18,Pivot!$H$2:$H$42)/118% -> 0
B19: 15 -Days -Upfront | C19: =SUMIF(Pivot!$A$2:$A$42,'MR-AR'!B19,Pivot!$B$2:$B$42)/118% -> 0 | D19: =SUMIF(Pivot!$A$2:$A$42,'MR-AR'!B19,Pivot!$C$2:$C$42)/118% -> 0 | E19: =SUMIF(Pivot!$A$2:$A$42,'MR-AR'!B19,Pivot!$D$2:$D$42)/118% -> 0 | F19: =SUMIF(Pivot!$A$2:$A$42,'MR-AR'!B19,Pivot!$E$2:$E$42)/118% -> 0 | G19: =SUMIF(Pivot!$A$2:$A$42,'MR-AR'!B19,Pivot!$F$2:$F$42)/118% -> 0 | H19: =SUMIF(Pivot!$A$2:$A$42,'MR-AR'!B19,Pivot!$G$2:$G$42)/118% -> 4000 | I19: =SUMIF(Pivot!$A$2:$A$42,'MR-AR'!B19,Pivot!$H$2:$H$42)/118% -> 0
B20: 13 month-Upfront | C20: =SUMIF(Pivot!$A$2:$A$42,'MR-AR'!B20,Pivot!$B$2:$B$42)/118% -> 0 | D20: =SUMIF(Pivot!$A$2:$A$42,'MR-AR'!B20,Pivot!$C$2:$C$42)/118% -> 0 | E20: =SUMIF(Pivot!$A$2:$A$42,'MR-AR'!B20,Pivot!$D$2:$D$42)/118% -> 0 | F20: =SUMIF(Pivot!$A$2:$A$42,'MR-AR'!B20,Pivot!$E$2:$E$42)/118% -> 0 | G20: =SUMIF(Pivot!$A$2:$A$42,'MR-AR'!B20,Pivot!$F$2:$F$42)/118% -> 0 | H20: =SUMIF(Pivot!$A$2:$A$42,'MR-AR'!B20,Pivot!$G$2:$G$42)/118% -> 0 | I20: =SUMIF(Pivot!$A$2:$A$42,'MR-AR'!B20,Pivot!$H$2:$H$42)/118% -> 0
B21: 19 -Days -Upfront | C21: =SUMIF(Pivot!$A$2:$A$42,'MR-AR'!B21,Pivot!$B$2:$B$42)/118% -> 0 | D21: =SUMIF(Pivot!$A$2:$A$42,'MR-AR'!B21,Pivot!$C$2:$C$42)/118% -> 0 | E21: =SUMIF(Pivot!$A$2:$A$42,'MR-AR'!B21,Pivot!$D$2:$D$42)/118% -> 0 | F21: =SUMIF(Pivot!$A$2:$A$42,'MR-AR'!B21,Pivot!$E$2:$E$42)/118% -> 34592.52 | G21: =SUMIF(Pivot!$A$2:$A$42,'MR-AR'!B21,Pivot!$F$2:$F$42)/118% -> 11032.203 | H21: =SUMIF(Pivot!$A$2:$A$42,'MR-AR'!B21,Pivot!$G$2:$G$42)/118% -> 0 | I21: =SUMIF(Pivot!$A$2:$A$42,'MR-AR'!B21,Pivot!$H$2:$H$42)/118% -> 0
B22: 38 -Days -Upfront | C22: =SUMIF(Pivot!$A$2:$A$42,'MR-AR'!B22,Pivot!$B$2:$B$42)/118% -> 0 | D22: =SUMIF(Pivot!$A$2:$A$42,'MR-AR'!B22,Pivot!$C$2:$C$42)/118% -> 0 | E22: =SUMIF(Pivot!$A$2:$A$42,'MR-AR'!B22,Pivot!$D$2:$D$42)/118% -> 4934.2105 | F22: =SUMIF(Pivot!$A$2:$A$42,'MR-AR'!B22,Pivot!$E$2:$E$42)/118% -> 0 | G22: =SUMIF(Pivot!$A$2:$A$42,'MR-AR'!B22,Pivot!$F$2:$F$42)/118% -> 0 | H22: =SUMIF(Pivot!$A$2:$A$42,'MR-AR'!B22,Pivot!$G$2:$G$42)/118% -> 0 | I22: =SUMIF(Pivot!$A$2:$A$42,'MR-AR'!B22,Pivot!$H$2:$H$42)/118% -> 0
B23: 1 month-Upfront | C23: =SUMIF(Pivot!$A$2:$A$42,'MR-AR'!B23,Pivot!$B$2:$B$42)/118% -> 185711.86 | D23: =SUMIF(Pivot!$A$2:$A$42,'MR-AR'!B23,Pivot!$C$2:$C$42)/118% -> 231211.87 | E23: =SUMIF(Pivot!$A$2:$A$42,'MR-AR'!B23,Pivot!$D$2:$D$42)/118% -> 310949.15 | F23: =SUMIF(Pivot!$A$2:$A$42,'MR-AR'!B23,Pivot!$E$2:$E$42)/118% -> 445211.86 | G23: =SUMIF(Pivot!$A$2:$A$42,'MR-AR'!B23,Pivot!$F$2:$F$42)/118% -> 57474.576 | H23: =SUMIF(Pivot!$A$2:$A$42,'MR-AR'!B23,Pivot!$G$2:$G$42)/118% -> 159146.16 | I23: =SUMIF(Pivot!$A$2:$A$42,'MR-AR'!B23,Pivot!$H$2:$H$42)/118% -> 203241.14
B24: 2 months subscription, Monthly | C24: =SUMIF(Pivot!$A$2:$A$42,'MR-AR'!B24,Pivot!$B$2:$B$42)/118% -> 40000 | D24: =SUMIF(Pivot!$A$2:$A$42,'MR-AR'!B24,Pivot!$C$2:$C$42)/118% -> 30000 | E24: =SUMIF(Pivot!$A$2:$A$42,'MR-AR'!B24,Pivot!$D$2:$D$42)/118% -> 9000 | F24: =SUMIF(Pivot!$A$2:$A$42,'MR-AR'!B24,Pivot!$E$2:$E$42)/118% -> 9000 | G24: =SUMIF(Pivot!$A$2:$A$42,'MR-AR'!B24,Pivot!$F$2:$F$42)/118% -> 42916 | H24: =SUMIF(Pivot!$A$2:$A$42,'MR-AR'!B24,Pivot!$G$2:$G$42)/118% -> 42916 | I24: =SUMIF(Pivot!$A$2:$A$42,'MR-AR'!B24,Pivot!$H$2:$H$42)/118% -> 0
B25: 2 months- Upfront | C25: =SUMIF(Pivot!$A$2:$A$42,'MR-AR'!B25,Pivot!$B$2:$B$42)/118% -> 89000 | D25: =SUMIF(Pivot!$A$2:$A$42,'MR-AR'!B25,Pivot!$C$2:$C$42)/118% -> 125500 | E25: =SUMIF(Pivot!$A$2:$A$42,'MR-AR'!B25,Pivot!$D$2:$D$42)/118% -> 71500 | F25: =SUMIF(Pivot!$A$2:$A$42,'MR-AR'!B25,Pivot!$E$2:$E$42)/118% -> 10000 | G25: =SUMIF(Pivot!$A$2:$A$42,'MR-AR'!B25,Pivot!$F$2:$F$42)/118% -> 10000 | H25: =SUMIF(Pivot!$A$2:$A$42,'MR-AR'!B25,Pivot!$G$2:$G$42)/118% -> 0 | I25: =SUMIF(Pivot!$A$2:$A$42,'MR-AR'!B25,Pivot!$H$2:$H$42)/118% -> 0
B26: 2 month & 13 Days-Upfront | C26: =SUMIF(Pivot!$A$2:$A$42,'MR-AR'!B26,Pivot!$B$2:$B$42)/118% -> 0 | D26: =SUMIF(Pivot!$A$2:$A$42,'MR-AR'!B26,Pivot!$C$2:$C$42)/118% -> 0 | E26: =SUMIF(Pivot!$A$2:$A$42,'MR-AR'!B26,Pivot!$D$2:$D$42)/118% -> 0 | F26: =SUMIF(Pivot!$A$2:$A$42,'MR-AR'!B26,Pivot!$E$2:$E$42)/118% -> 0 | G26: =SUMIF(Pivot!$A$2:$A$42,'MR-AR'!B26,Pivot!$F$2:$F$42)/118% -> 0 | H26: =SUMIF(Pivot!$A$2:$A$42,'MR-AR'!B26,Pivot!$G$2:$G$42)/118% -> 0 | I26: =SUMIF(Pivot!$A$2:$A$42,'MR-AR'!B26,Pivot!$H$2:$H$42)/118% -> 7632.8957
B27: 3 months subscription, Monthly | C27: =SUMIF(Pivot!$A$2:$A$42,'MR-AR'!B27,Pivot!$B$2:$B$42)/118% -> 150000 | D27: =SUMIF(Pivot!$A$2:$A$42,'MR-AR'!B27,Pivot!$C$2:$C$42)/118% -> 150000 | E27: =SUMIF(Pivot!$A$2:$A$42,'MR-AR'!B27,Pivot!$D$2:$D$42)/118% -> 150000 | F27: =SUMIF(Pivot!$A$2:$A$42,'MR-AR'!B27,Pivot!$E$2:$E$42)/118% -> 0 | G27: =SUMIF(Pivot!$A$2:$A$42,'MR-AR'!B27,Pivot!$F$2:$F$42)/118% -> 0 | H27: =SUMIF(Pivot!$A$2:$A$42,'MR-AR'!B27,Pivot!$G$2:$G$42)/118% -> 0 | I27: =SUMIF(Pivot!$A$2:$A$42,'MR-AR'!B27,Pivot!$H$2:$H$42)/118% -> 0
B28: 3 months subscription, upfront | C28: =SUMIF(Pivot!$A$2:$A$42,'MR-AR'!B28,Pivot!$B$2:$B$42)/118% -> 175445.48 | D28: =SUMIF(Pivot!$A$2:$A$42,'MR-AR'!B28,Pivot!$C$2:$C$42)/118% -> 137522.6 | E28: =SUMIF(Pivot!$A$2:$A$42,'MR-AR'!B28,Pivot!$D$2:$D$42)/118% -> 118022.6 | F28: =SUMIF(Pivot!$A$2:$A$42,'MR-AR'!B28,Pivot!$E$2:$E$42)/118% -> 40022.599 | G28: =SUMIF(Pivot!$A$2:$A$42,'MR-AR'!B28,Pivot!$F$2:$F$42)/118% -> 38666.667 | H28: =SUMIF(Pivot!$A$2:$A$42,'MR-AR'!B28,Pivot!$G$2:$G$42)/118% -> 20666.667 | I28: =SUMIF(Pivot!$A$2:$A$42,'MR-AR'!B28,Pivot!$H$2:$H$42)/118% -> 20666.667
... B46: 1year & 6 months - Half Yearly Payment | C46: =SUMIF(Pivot!$A$2:$A$42,'MR-AR'!B46,Pivot!$B$2:$B$42)/118% -> 0 | D46: =SUMIF(Pivot!$A$2:$A$42,'MR-AR'!B46,Pivot!$C$2:$C$42)/118% -> 0 | E46: =SUMIF(Pivot!$A$2:$A$42,'MR-AR'!B46,Pivot!$D$2:$D$42)/118% -> 0 | F46: =SUMIF(Pivot!$A$2:$A$42,'MR-AR'!B46,Pivot!$E$2:$E$42)/118% -> 0 | G46: =SUMIF(Pivot!$A$2:$A$42,'MR-AR'!B46,Pivot!$F$2:$F$42)/118% -> 0 | H46: =SUMIF(Pivot!$A$2:$A$42,'MR-AR'!B46,Pivot!$G$2:$G$42)/118% -> 0 | I46: =SUMIF(Pivot!$A$2:$A$42,'MR-AR'!B46,Pivot!$H$2:$H$42)/118% -> 0
B48: Total monthly revenue from B2C subscribers (B) | C48: =Invoices!M13 -> 42252 | D48: =Invoices!M14 -> 24128 | E48: =Invoices!M15 -> 24554.28 | F48: =Invoices!M16 -> 19474 | G48: =Invoices!M17 -> 18627 | H48: =Invoices!M18 -> 14394.92 | I48: =Invoices!M20 -> 13549.16
B50: Total monthly revenue from B2B and B2C C=A+B | C50: =C7+C48 -> 1783872.9 | D50: =D7+D48 -> 2187385.6 | E50: =E7+E48 -> 2588861.1 | F50: =F7+F48 -> 3154397.8 | G50: =G7+G48 -> 3877678.3 | H50: =H7+H48 -> 4609541 | I50: =I7+I48 -> 5218228.1
B52: Monthly Recurring revenue (excluding one time and others)-B2B | C52: =C50-C48 -> 1741620.9 | D52: =D50-D48 -> 2163257.6 | E52: =E50-E48 -> 2564306.8 | F52: =F50-F48 -> 3134923.8 | G52: =G50-G48 -> 3859051.3 | H52: =H50-H48 -> 4595146.1 | I52: =I50-I48 -> 5204678.9
B54: No. of active subscribers-B2B | C54: ='Customer churnout'!G6 -> 117 | D54: ='Customer churnout'!G9 -> 143 | E54: ='Customer churnout'!H9 -> 158 | F54: ='Customer churnout'!I9 -> 195 | G54: ='Customer churnout'!J9 -> 219 | H54: ='Customer churnout'!K9 -> 245 | I54: ='Customer churnout'!L9 -> 288
B56: Monthly recurring revenue per subscriber | C56: =C52/C54 -> 14885.649 | D56: =D52/D54 -> 15127.676 | E56: =E52/E54 -> 16229.79 | F56: =F52/F54 -> 16076.533 | G56: =G52/G54 -> 17621.239 | H56: =H52/H54 -> 18755.698 | I56: =I52/I54 -> 18071.802
B58: Total Annual Recurring revenue (excluding one time and others)-B2B | C58: =C52*12 -> 20899451 | D58: =D52*12 -> 25959092 | E58: =E52*12 -> 30771682 | F58: =F52*12 -> 37619086 | G58: =G52*12 -> 46308616 | H58: =H52*12 -> 55141753 | I58: =I52*12 -> 62456147

Sheet MR Accrual
B1: Coresphere100 Technologies Pvt. Ltd.
B2: Monthly revenue (Accrual)
F3: Amount in INR
B4: Particulars | C4: For the month ended | D4: For the month ended | E4: For the month ended | F4: For the month ended | G4: For the month ended | H4: For the month ended | I4: For the month ended | J4: For the month ended
C5: 45748 | D5: 45748 | E5: 45778 | F5: 45809 | G5: 45839 | H5: 45870 | I5: 45901 | J5: 45931 | K5: Total
B6: Monthly Revenue from B2B subscribers (A) | D6: =SUM(D9:D45) -> 1491256.2 | E6: =SUM(E9:E45) -> 2038366.3 | F6: =SUM(F9:F45) -> 2336604.3 | G6: =SUM(G9:G45) -> 2883930.9 | H6: =SUM(H9:H45) -> 3628578.2 | I6: =SUM(I9:I45) -> 4447689.3 | J6: =SUM(J9:J45) -> 5065908.8 | K6: =SUM(K9:K45) -> 21892334
B8: Annual Subscription
B9: Annual- Half Yearly Payment | D9: =SUMIF(Pivot!$A$45:$A$84,B9,Pivot!$B$45:$B$84)/118% -> 45591.266 | E9: =SUMIF(Pivot!$A$45:$A$84,B9,Pivot!$C$45:$C$84)/118% -> 68463.254 | F9: =SUMIF(Pivot!$A$45:$A$84,B9,Pivot!$D$45:$D$84)/118% -> 290463.33 | G9: =SUMIF(Pivot!$A$45:$A$84,B9,Pivot!$E$45:$E$84)/118% -> 316997.5 | H9: =SUMIF(Pivot!$A$45:$A$84,B9,Pivot!$F$45:$F$84)/118% -> 673159.02 | I9: =SUMIF(Pivot!$A$45:$A$84,B9,Pivot!$G$45:$G$84)/118% -> 1000802.2 | J9: =SUMIF(Pivot!$A$45:$H$84,B9,Pivot!$H$45:$H$84)/118% -> 1177971.3 | K9: =SUM(D9:J9) -> 3573447.9
B10: Annual subscription, Quarterly upfront | D10: =SUMIF(Pivot!$A$45:$A$84,B10,Pivot!$B$45:$B$84)/118% -> 47587.42 | E10: =SUMIF(Pivot!$A$45:$A$84,B10,Pivot!$C$45:$C$84)/118% -> 49173.667 | F10: =SUMIF(Pivot!$A$45:$A$84,B10,Pivot!$D$45:$D$84)/118% -> 63038.25 | G10: =SUMIF(Pivot!$A$45:$A$84,B10,Pivot!$E$45:$E$84)/118% -> 172929.77 | H10: =SUMIF(Pivot!$A$45:$A$84,B10,Pivot!$F$45:$F$84)/118% -> 344434.76 | I10: =SUMIF(Pivot!$A$45:$A$84,B10,Pivot!$G$45:$G$84)/118% -> 420350.41 | J10: =SUMIF(Pivot!$A$45:$H$84,B10,Pivot!$H$45:$H$84)/118% -> 501192.13 | K10: =SUM(D10:J10) -> 1598706.4
B11: Annual Upfront | D11: =SUMIF(Pivot!$A$45:$A$84,B11,Pivot!$B$45:$B$84)/118% -> 565804 | E11: =SUMIF(Pivot!$A$45:$A$84,B11,Pivot!$C$45:$C$84)/118% -> 719682.25 | F11: =SUMIF(Pivot!$A$45:$A$84,B11,Pivot!$D$45:$D$84)/118% -> 932783.84 | G11: =SUMIF(Pivot!$A$45:$A$84,B11,Pivot!$E$45:$E$84)/118% -> 1242097.4 | H11: =SUMIF(Pivot!$A$45:$A$84,B11,Pivot!$F$45:$F$84)/118% -> 1589492.6 | I11: =SUMIF(Pivot!$A$45:$A$84,B11,Pivot!$G$45:$G$84)/118% -> 1866858.4 | J11: =SUMIF(Pivot!$A$45:$H$84,B11,Pivot!$H$45:$H$84)/118% -> 2048295.9 | K11: =SUM(D11:J11) -> 8965014.4
B12: Annual-Monthly | D12: =SUMIF(Pivot!$A$45:$A$84,B12,Pivot!$B$45:$B$84)/118% -> 47801.532 | E12: =SUMIF(Pivot!$A$45:$A$84,B12,Pivot!$C$45:$C$84)/118% -> 208651.43 | F12: =SUMIF(Pivot!$A$45:$A$84,B12,Pivot!$D$45:$D$84)/118% -> 85456.512 | G12: =SUMIF(Pivot!$A$45:$A$84,B12,Pivot!$E$45:$E$84)/118% -> 123035.95 | H12: =SUMIF(Pivot!$A$45:$A$84,B12,Pivot!$F$45:$F$84)/118% -> 161676.67 | I12: =SUMIF(Pivot!$A$45:$A$84,B12,Pivot!$G$45:$G$84)/118% -> 192829.62 | J12: =SUMIF(Pivot!$A$45:$H$84,B12,Pivot!$H$45:$H$84)/118% -> 281866.93 | K12: =SUM(D12:J12) -> 1101318.6
B13: 2 Year- Upfront | D13: =SUMIF(Pivot!$A$45:$A$84,B13,Pivot!$B$45:$B$84)/118% -> 0 | E13: =SUMIF(Pivot!$A$45:$A$84,B13,Pivot!$C$45:$C$84)/118% -> 0 | F13: =SUMIF(Pivot!$A$45:$A$84,B13,Pivot!$D$45:$D$84)/118% -> 0 | G13: =SUMIF(Pivot!$A$45:$A$84,B13,Pivot!$E$45:$E$84)/118% -> 1189.9985 | H13: =SUMIF(Pivot!$A$45:$A$84,B13,Pivot!$F$45:$F$84)/118% -> 4098.8838 | I13: =SUMIF(Pivot!$A$45:$A$84,B13,Pivot!$G$45:$G$84)/118% -> 3966.6617 | J13: =SUMIF(Pivot!$A$45:$H$84,B13,Pivot!$H$45:$H$84)/118% -> 4098.8838 | K13: =SUM(D13:J13) -> 13354.428
D14: =SUMIF(Pivot!$A$45:$A$84,B14,Pivot!$B$45:$B$84)/118% -> 0 | E14: =SUMIF(Pivot!$A$45:$A$84,B14,Pivot!$C$45:$C$84)/118% -> 0 | F14: =SUMIF(Pivot!$A$45:$A$84,B14,Pivot!$D$45:$D$84)/118% -> 0 | G14: =SUMIF(Pivot!$A$45:$A$84,B14,Pivot!$E$45:$E$84)/118% -> 0 | H14: =SUMIF(Pivot!$A$45:$A$84,B14,Pivot!$F$45:$F$84)/118% -> 0 | I14: =SUMIF(Pivot!$A$45:$A$84,B14,Pivot!$G$45:$G$84)/118% -> 0 | J14: =SUMIF(Pivot!$A$45:$H$84,B14,Pivot!$H$45:$H$84)/118% -> 0 | K14: =SUM(D14:J14) -> 0
B15: Other Than Annual Subscriptions | D15: =SUMIF(Pivot!$A$45:$A$84,B15,Pivot!$B$45:$B$84)/118% -> 0 | E15: =SUMIF(Pivot!$A$45:$A$84,B15,Pivot!$C$45:$C$84)/118% -> 0 | F15: =SUMIF(Pivot!$A$45:$A$84,B15,Pivot!$D$45:$D$84)/118% -> 0 | G15: =SUMIF(Pivot!$A$45:$A$84,B15,Pivot!$E$45:$E$84)/118% -> 0 | H15: =SUMIF(Pivot!$A$45:$A$84,B15,Pivot!$F$45:$F$84)/118% -> 0 | I15: =SUMIF(Pivot!$A$45:$A$84,B15,Pivot!$G$45:$G$84)/118% -> 0 | J15: =SUMIF(Pivot!$A$45:$H$84,B15,Pivot!$H$45:$H$84)/118% -> 0 | K15: =SUM(D15:J15) -> 0
B16: 10 -Days -Upfront | D16: =SUMIF(Pivot!$A$45:$A$84,B16,Pivot!$B$45:$B$84)/118% -> 0 | E16: =SUMIF(Pivot!$A$45:$A$84,B16,Pivot!$C$45:$C$84)/118% -> 0 | F16: =SUMIF(Pivot!$A$45:$A$84,B16,Pivot!$D$45:$D$84)/118% -> 0 | G16: =SUMIF(Pivot!$A$45:$A$84,B16,Pivot!$E$45:$E$84)/118% -> 8000 | H16: =SUMIF(Pivot!$A$45:$A$84,B16,Pivot!$F$45:$F$84)/118% -> 0 | I16: =SUMIF(Pivot!$A$45:$A$84,B16,Pivot!$G$45:$G$84)/118% -> 0 | J16: =SUMIF(Pivot!$A$45:$H$84,B16,Pivot!$H$45:$H$84)/118% -> 0 | K16: =SUM(D16:J16) -> 8000
B17: 12 -Days -Upfront | D17: =SUMIF(Pivot!$A$45:$A$84,B17,Pivot!$B$45:$B$84)/118% -> 0 | E17: =SUMIF(Pivot!$A$45:$A$84,B17,Pivot!$C$45:$C$84)/118% -> 0 | F17: =SUMIF(Pivot!$A$45:$A$84,B17,Pivot!$D$45:$D$84)/118% -> 0 | G17: =SUMIF(Pivot!$A$45:$A$84,B17,Pivot!$E$45:$E$84)/118% -> 0 | H17: =SUMIF(Pivot!$A$45:$A$84,B17,Pivot!$F$45:$F$84)/118% -> 3483.8983 | I17: =SUMIF(Pivot!$A$45:$A$84,B17,Pivot!$G$45:$G$84)/118% -> 0 | J17: =SUMIF(Pivot!$A$45:$H$84,B17,Pivot!$H$45:$H$84)/118% -> 0 | K17: =SUM(D17:J17) -> 3483.8983
B18: 15 -Days -Upfront | D18: =SUMIF(Pivot!$A$45:$A$84,B18,Pivot!$B$45:$B$84)/118% -> 0 | E18: =SUMIF(Pivot!$A$45:$A$84,B18,Pivot!$C$45:$C$84)/118% -> 0 | F18: =SUMIF(Pivot!$A$45:$A$84,B18,Pivot!$D$45:$D$84)/118% -> 0 | G18: =SUMIF(Pivot!$A$45:$A$84,B18,Pivot!$E$45:$E$84)/118% -> 0 | H18: =SUMIF(Pivot!$A$45:$A$84,B18,Pivot!$F$45:$F$84)/118% -> 0 | I18: =SUMIF(Pivot!$A$45:$A$84,B18,Pivot!$G$45:$G$84)/118% -> 4000 | J18: =SUMIF(Pivot!$A$45:$H$84,B18,Pivot!$H$45:$H$84)/118% -> 0 | K18: =SUM(D18:J18) -> 4000
B19: 13 month-Upfront | D19: =SUMIF(Pivot!$A$45:$A$84,B19,Pivot!$B$45:$B$84)/118% -> 0 | E19: =SUMIF(Pivot!$A$45:$A$84,B19,Pivot!$C$45:$C$84)/118% -> 0 | F19: =SUMIF(Pivot!$A$45:$A$84,B19,Pivot!$D$45:$D$84)/118% -> 0 | G19: =SUMIF(Pivot!$A$45:$A$84,B19,Pivot!$E$45:$E$84)/118% -> 0 | H19: =SUMIF(Pivot!$A$45:$A$84,B19,Pivot!$F$45:$F$84)/118% -> 0 | I19: =SUMIF(Pivot!$A$45:$A$84,B19,Pivot!$G$45:$G$84)/118% -> 0 | J19: =SUMIF(Pivot!$A$45:$H$84,B19,Pivot!$H$45:$H$84)/118% -> 0 | K19: =SUM(D19:J19) -> 0
B20: 19 -Days -Upfront | D20: =SUMIF(Pivot!$A$45:$A$84,B20,Pivot!$B$45:$B$84)/118% -> 0 | E20: =SUMIF(Pivot!$A$45:$A$84,B20,Pivot!$C$45:$C$84)/118% -> 0 | F20: =SUMIF(Pivot!$A$45:$A$84,B20,Pivot!$D$45:$D$84)/118% -> 0 | G20: =SUMIF(Pivot!$A$45:$A$84,B20,Pivot!$E$45:$E$84)/118% -> 7687.2267 | H20: =SUMIF(Pivot!$A$45:$A$84,B20,Pivot!$F$45:$F$84)/118% -> 37937.497 | I20: =SUMIF(Pivot!$A$45:$A$84,B20,Pivot!$G$45:$G$84)/118% -> 0 | J20: =SUMIF(Pivot!$A$45:$H$84,B20,Pivot!$H$45:$H$84)/118% -> 0 | K20: =SUM(D20:J20) -> 45624.723
B21: 38 -Days -Upfront | D21: =SUMIF(Pivot!$A$45:$A$84,B21,Pivot!$B$45:$B$84)/118% -> 0 | E21: =SUMIF(Pivot!$A$45:$A$84,B21,Pivot!$C$45:$C$84)/118% -> 0 | F21: =SUMIF(Pivot!$A$45:$A$84,B21,Pivot!$D$45:$D$84)/118% -> 3947.3684 | G21: =SUMIF(Pivot!$A$45:$A$84,B21,Pivot!$E$45:$E$84)/118% -> 2302.6316 | H21: =SUMIF(Pivot!$A$45:$A$84,B21,Pivot!$F$45:$F$84)/118% -> 0 | I21: =SUMIF(Pivot!$A$45:$A$84,B21,Pivot!$G$45:$G$84)/118% -> 0 | J21: =SUMIF(Pivot!$A$45:$H$84,B21,Pivot!$H$45:$H$84)/118% -> 0 | K21: =SUM(D21:J21) -> 6250
B22: 1 month-Upfront | D22: =SUMIF(Pivot!$A$45:$A$84,B22,Pivot!$B$45:$B$84)/118% -> 211039.61 | E22: =SUMIF(Pivot!$A$45:$A$84,B22,Pivot!$C$45:$C$84)/118% -> 251536.22 | F22: =SUMIF(Pivot!$A$45:$A$84,B22,Pivot!$D$45:$D$84)/118% -> 300929.68 | G22: =SUMIF(Pivot!$A$45:$A$84,B22,Pivot!$E$45:$E$84)/118% -> 378916.63 | H22: =SUMIF(Pivot!$A$45:$A$84,B22,Pivot!$F$45:$F$84)/118% -> 189317.77 | I22: =SUMIF(Pivot!$A$45:$A$84,B22,Pivot!$G$45:$G$84)/118% -> 109793.59 | J22: =SUMIF(Pivot!$A$45:$H$84,B22,Pivot!$H$45:$H$84)/118% -> 178266.07 | K22: =SUM(D22:J22) -> 1619799.6
B23: 2 months subscription, Monthly | D23: =SUMIF(Pivot!$A$45:$A$84,B23,Pivot!$B$45:$B$84)/118% -> 39185.616 | E23: =SUMIF(Pivot!$A$45:$A$84,B23,Pivot!$C$45:$C$84)/118% -> 33395.029 | F23: =SUMIF(Pivot!$A$45:$A$84,B23,Pivot!$D$45:$D$84)/118% -> 8852.459 | G23: =SUMIF(Pivot!$A$45:$A$84,B23,Pivot!$E$45:$E$84)/118% -> 9147.541 | H23: =SUMIF(Pivot!$A$45:$A$84,B23,Pivot!$F$45:$F$84)/118% -> 95681.574 | I23: =SUMIF(Pivot!$A$45:$A$84,B23,Pivot!$G$45:$G$84)/118% -> 168849.84 | J23: =SUMIF(Pivot!$A$45:$H$84,B23,Pivot!$H$45:$H$84)/118% -> 78796.59 | K23: =SUM(D23:J23) -> 433908.65
B24: 2 months- Upfront | D24: =SUMIF(Pivot!$A$45:$A$84,B24,Pivot!$B$45:$B$84)/118% -> 64638.815 | E24: =SUMIF(Pivot!$A$45:$A$84,B24,Pivot!$C$45:$C$84)/118% -> 113771.81 | F24: =SUMIF(Pivot!$A$45:$A$84,B24,Pivot!$D$45:$D$84)/118% -> 91831.306 | G24: =SUMIF(Pivot!$A$45:$A$84,B24,Pivot!$E$45:$E$84)/118% -> 42532.258 | H24: =SUMIF(Pivot!$A$45:$A$84,B24,Pivot!$F$45:$F$84)/118% -> 10000 | I24: =SUMIF(Pivot!$A$45:$A$84,B24,Pivot!$G$45:$G$84)/118% -> 6774.1935 | J24: =SUMIF(Pivot!$A$45:$H$84,B24,Pivot!$H$45:$H$84)/118% -> 0 | K24: =SUM(D24:J24) -> 329548.39
B25: 2 month & 13 Days-Upfront | D25: =SUMIF(Pivot!$A$45:$A$84,B25,Pivot!$B$45:$B$84)/118% -> 0 | E25: =SUMIF(Pivot!$A$45:$A$84,B25,Pivot!$C$45:$C$84)/118% -> 0 | F25: =SUMIF(Pivot!$A$45:$A$84,B25,Pivot!$D$45:$D$84)/118% -> 0 | G25: =SUMIF(Pivot!$A$45:$A$84,B25,Pivot!$E$45:$E$84)/118% -> 0 | H25: =SUMIF(Pivot!$A$45:$A$84,B25,Pivot!$F$45:$F$84)/118% -> 0 | I25: =SUMIF(Pivot!$A$45:$A$84,B25,Pivot!$G$45:$G$84)/118% -> 0 | J25: =SUMIF(Pivot!$A$45:$H$84,B25,Pivot!$H$45:$H$84)/118% -> 4350.7505 | K25: =SUM(D25:J25) -> 4350.7505
B26: 3 months subscription, Monthly | D26: =SUMIF(Pivot!$A$45:$A$84,B26,Pivot!$B$45:$B$84)/118% -> 99487.8 | E26: =SUMIF(Pivot!$A$45:$A$84,B26,Pivot!$C$45:$C$84)/118% -> 153296.7 | F26: =SUMIF(Pivot!$A$45:$A$84,B26,Pivot!$D$45:$D$84)/118% -> 148351.65 | G26: =SUMIF(Pivot!$A$45:$A$84,B26,Pivot!$E$45:$E$84)/118% -> 69230.769 | H26: =SUMIF(Pivot!$A$45:$A$84,B26,Pivot!$F$45:$F$84)/118% -> 0 | I26: =SUMIF(Pivot!$A$45:$A$84,B26,Pivot!$G$45:$G$84)/118% -> 0 | J26: =SUMIF(Pivot!$A$45:$H$84,B26,Pivot!$H$45:$H$84)/118% -> 0 | K26: =SUM(D26:J26) -> 470366.92
... B45: 1year & 6 months - Half Yearly Payment | D45: =SUMIF(Pivot!$A$45:$A$84,B45,Pivot!$B$45:$B$84)/118% -> 0 | E45: =SUMIF(Pivot!$A$45:$A$84,B45,Pivot!$C$45:$C$84)/118% -> 0 | F45: =SUMIF(Pivot!$A$45:$A$84,B45,Pivot!$D$45:$D$84)/118% -> 0 | G45: =SUMIF(Pivot!$A$45:$A$84,B45,Pivot!$E$45:$E$84)/118% -> 0 | H45: =SUMIF(Pivot!$A$45:$A$84,B45,Pivot!$F$45:$F$84)/118% -> 0 | I45: =SUMIF(Pivot!$A$45:$A$84,B45,Pivot!$G$45:$G$84)/118% -> 0 | J45: =SUMIF(Pivot!$A$45:$H$84,B45,Pivot!$H$45:$H$84)/118% -> 0 | K45: =SUM(D45:J45) -> 0
B47: Monthly Revenue from B2C subscribers (B) | D47: ='MR-AR'!C48 -> 42252 | E47: ='MR-AR'!D48 -> 24128 | F47: ='MR-AR'!E48 -> 24554.28 | G47: =Invoices!M16 -> 19474 | H47: =Invoices!M17 -> 18627 | I47: =Invoices!M18 -> 14394.92 | J47: =Invoices!M20 -> 13549.16 | K47: =SUM(D47:J47) -> 156979.36
B49: Monthly Revenue from B2B and B2C C=A+B | D49: =D6+D47 -> 1533508.2 | E49: =E6+E47 -> 2062494.3 | F49: =F6+F47 -> 2361158.6 | G49: =G6+G47 -> 2903404.9 | H49: =H6+H47 -> 3647205.2 | I49: =I6+I47 -> 4462084.2 | J49: =J6+J47 -> 5079457.9 | K49: =SUM(D49:J49) -> 22049313

Sheet Customer churnout
B1: Coresphere100 Technologies Pvt. Ltd.
B2: Month Wise Customer Churn Out
B4: Particulars | C4: For the month ended | D4: For the month ended | E4: For the month ended | F4: For the month ended | G4: For the month ended | H4: For the month ended | I4: For the month ended | J4: For the month ended | K4: For the month ended | L4: For the month ended
C5: 45658 | D5: 45689 | E5: 45717 | F5: 45748 | G5: 45778 | H5: 45809 | I5: 45839 | J5: 45870 | K5: 45901 | L5: 45931 | M5: Remarks
B6: No. of active subscriber at beginning of month | C6: 16 | D6: =C9 -> 27 | E6: =D9 -> 35 | F6: =E9 -> 57 | G6: =F9 -> 117 | H6: =G9 -> 143 | I6: =H9 -> 158 | J6: =I9 -> 195 | K6: =J9 -> 219 | L6: =K9 -> 245 | M6: Refer active subscriber and Deletion tab
B7: Add: New additions | C7: 15 | D7: 13 | E7: 24 | F7: 61 | G7: 37 | H7: 32 | I7: 48 | J7: 38 | K7: 39 | L7: 49
B8: Less: Deletions | C8: 4 | D8: 5 | E8: 2 | F8: 1 | G8: 11 | H8: 17 | I8: 11 | J8: 14 | K8: 13 | L8: 6
B9: No. of active subscribers at end of month | C9: =C6+C7-C8 -> 27 | D9: =D6+D7-D8 -> 35 | E9: =E6+E7-E8 -> 57 | F9: =F6+F7-F8 -> 117 | G9: =G6+G7-G8 -> 143 | H9: =H6+H7-H8 -> 158 | I9: =I6+I7-I8 -> 195 | J9: =J6+J7-J8 -> 219 | ... L9: =L6+L7-L8 -> 288

Sheet Pivot
A2: Month Wise
B3: Data
A4: Payment Cycle | B4: Sum of Invoiced amount for April | C4: Sum of Invoiced amount for MAY | D4: Sum of June in months | E4: Sum of July in months | F4: Sum of Aug Sales in months | G4: Sum of Sept Sales in months | H4: Sum of Oct Sales in months
A5: 1 month-Upfront | B5: 219140 | C5: 272830.01 | D5: 366920 | E5: 525350 | F5: 67820 | G5: 187792.47 | H5: 239824.54
A6: 2 months- Upfront | B6: 105020 | C6: 148090 | D6: 84370 | E6: 11800 | F6: 11800
A7: 3 months subscription, Monthly | B7: 177000 | C7: 177000 | D7: 177000 | F7: 0
A8: 3 months subscription, upfront | B8: 207025.67 | C8: 162276.67 | D8: 139266.67 | E8: 47226.667 | F8: 45626.667 | G8: 24386.667 | H8: 24386.667
A9: Annual subscription, Quarterly upfront | B9: 56966.667 | C9: 56966.667 | D9: 113606.67 | E9: 213316.67 | F9: 419843.33 | G9: 526773.33 | H9: 603733.33
A10: Annual Upfront | B10: 770920.33 | C10: 907320 | D10: 1187652.3 | E10: 1707479.8 | F10: 1974898.9 | G10: 2325639.7 | H10: 2416909.7
A11: Annual-Monthly | B11: 81459 | C11: 92275.667 | D11: 108175.67 | E11: 186251.67 | F11: 186251.67 | G11: 262531.67 | H11: 380851.67
A12: Three Installments of 50k | B12: 13250 | C12: 13250 | D12: 13250 | E12: 13250 | F12: 13250 | G12: 13250 | H12: 13250
A13: 2 months subscription, Monthly | B13: 47200 | C13: 35400 | D13: 10620 | E13: 10620 | F13: 50640.88 | G13: 50640.88
A14: 5 months subscription, Monthly | F14: 0
A15: 4 months subscription, Monthly | B15: 11800 | C15: 11800 | D15: 11800 | E15: 11800 | F15: 0
A16: 6 month-Upfront | B16: 243183 | C16: 266547 | D16: 398510.33 | E16: 455368.3 | F16: 551788.67 | G16: 581205.33 | H16: 575378.67
A17: Annual- Half Yearly Payment | B17: 61165.667 | C17: 347905.67 | D17: 347905.67 | E17: 373767.33 | F17: 1158310 | G17: 1209148.3 | H17: 1432679.7
A18: (empty)
A19: 10 -Days -Upfront | E19: 9440 | F19: 0
A20: 2 Year- Upfront | E20: 4745.67 | F20: 4745.67 | G20: 4745.67 | H20: 4745.67
A21: 38 -Days -Upfront | D21: 5822.3684 | F21: 0
A22: 12 -Days -Upfront | F22: 4111
A23: 11 months subscription, Monthly | D23: 0 | E23: 7080 | F23: 7080 | G23: 7080 | H23: 7080
A24: 5 month-Upfront | G24: 4130 | H24: 4130
A25: 19 -Days -Upfront | E25: 40819.174 | F25: 13018
A26: 1 year & 1 months-Monthly | B26: 11800 | C26: 11800 | D26: 11800 | E26: 11800 | F26: 11800 | G26: 11800 | H26: 11800
A27: 18 month-Half Yearly Payment | B27: 6883.3333 | C27: 6883.3333 | D27: 6883.3333 | E27: 6883.3333 | F27: 6883.3333 | G27: 6883.3333 | H27: 6883.3333
A28: 9 months subscription, Monthly | E28: 19912.5 | F28: 19912.5 | G28: 17700 | H28: 17700
A29: 15 -Days -Upfront | G29: 4720
A30: 13 month-Upfront | G30: 0 | H30: 0
A31: 8 months & 23 days - Half Yearly Payment | G31: 183844.96 | H31: 183844.96
A32: 6 months subscription, Quarterly upfront | B32: 36399 | C32: 36399 | D32: 36399 | E32: 36399
A33: 6 months subscription, Monthly | B33: 5900 | C33: 5900 | D33: 5900 | E33: 5900 | F33: 5900 | H33: 180195.44
A34: 13 month-Monthly
A35: 10 months | H35: 3894
A36: 3 months- Upfront
A37: 9 months subscription, Upfront | H37: 20075.226
A38: 2 month & 13 Days-Upfront | H38: 9006.8169
A39: 9 months & 23 days subscription, Upfront | H39: 5151.3983
A40: Total Result | B40: 2055112.7 | C40: 2552644 | D40: 3025882 | E40: 3699210.1 | F40: 4553680.6 | G40: 5422272.4 | H40: 6141521.1
A45: Date wise
B46: Data
A47: Payment Cycle | B47: Sum of April Sales (Days Wise) | C47: Sum of May Sales (Days Wise) | D47: Sum of June in days | E47: Sum of July in days | F47: Sum of Aug Sales in days | G47: Sum of Sept Sales in days | H47: Sum of Oct Sales in days
A48: 1 month-Upfront | B48: 249026.74 | C48: 296812.74 | D48: 355097.03 | E48: 447121.63 | F48: 223394.97 | G48: 129556.44 | H48: 210353.97
A49: 2 months- Upfront | B49: 76273.802 | C49: 134250.74 | D49: 108360.94 | E49: 50188.065 | F49: 11800 | G49: 7993.5484
A50: 3 months subscription, Monthly | B50: 117395.6 | C50: 180890.11 | D50: 175054.95 | E50: 81692.308 | F50: 0
A51: 3 months subscription, upfront | B51: 157439.09 | C51: 199473.31 | D51: 154037.76 | E51: 95909.334 | F51: 48052.307 | G51: 41864.348 | H51: 24651.739
A52: Annual subscription, Quarterly upfront | B52: 56153.155 | C52: 58024.927 | D52: 74385.135 | E52: 204057.12 | F52: 406433.01 | G52: 496013.49 | H52: 591406.71
A53: Annual Upfront | B53: 667648.72 | C53: 849225.06 | D53: 1100684.9 | E53: 1465674.9 | F53: 1875601.2 | G53: 2202892.9 | H53: 2416989.2
A54: Annual-Monthly | B54: 56405.807 | C54: 246208.69 | D54: 100838.68 | E54: 145182.42 | F54: 190778.47 | G54: 227538.95 | H54: 332602.98
A55: Three Installments of 50k | B55: 13032.787 | C55: 13467.213 | D55: 13032.787 | E55: 13467.213 | F55: 13467.213 | G55: 13032.787 | H55: 13467.213
A56: 2 months subscription, Monthly | B56: 46239.027 | C56: 39406.134 | D56: 10445.902 | E56: 10794.098 | F56: 112904.26 | G56: 199242.81 | H56: 92979.976
A57: 5 months subscription, Monthly | F57: 0
A58: 4 months subscription, Monthly | B58: 8124.5902 | C58: 11993.443 | D58: 11606.557 | E58: 11993.443 | F58: 3481.9672
A59: 6 month-Upfront | B59: 221999.12 | C59: 257382.13 | D59: 270097.62 | E59: 429896.93 | F59: 496786.03 | G59: 553996.77 | H59: 547780.63
A60: Annual- Half Yearly Payment | B60: 53797.694 | C60: 80786.64 | D60: 342746.74 | E60: 374057.05 | F60: 794327.65 | G60: 1180946.6 | H60: 1390006.1
A61: (empty)
A62: 10 -Days -Upfront | E62: 9440 | F62: 0
A63: 2 Year- Upfront | E63: 1404.1982 | F63: 4836.6828 | G63: 4680.6608 | H63: 4836.6828
A64: 38 -Days -Upfront | D64: 4657.8947 | E64: 2717.1053 | F64: 0
A65: 12 -Days -Upfront | F65: 4111
A66: 11 months subscription, Monthly | D66: 0 | E66: 7206.806 | F66: 7206.806 | G66: 6974.3284 | H66: 7206.806
A67: 5 month-Upfront | F67: 0 | G67: 4049.0196 | H67: 4183.9869
A68: 19 -Days -Upfront | E68: 9070.9275 | F68: 44766.246
A69: 1 year & 1 months-Monthly | B69: 11591.94 | C69: 11978.338 | D69: 11591.94 | E69: 11978.338 | F69: 11978.338 | G69: 11591.94 | H69: 11978.338
A70: 18 month-Half Yearly Payment | B70: 6782.8467 | C70: 7008.9416 | D70: 6782.8467 | E70: 7008.9416 | F70: 7008.9416 | G70: 6782.8467 | H70: 7008.9416
A71: 9 months subscription, Monthly | E71: 5813.8686 | F71: 18022.993 | G71: 17441.606 | H71: 18022.993
A72: 15 -Days -Upfront | G72: 4720
A73: 13 month-Upfront | G73: 0 | H73: 0
A74: 8 months & 23 days - Half Yearly Payment | G74: 137030.4 | H74: 176997.6
A75: 6 months subscription, Quarterly upfront | B75: 11999.67 | C75: 12399.659 | D75: 11999.67 | E75: 12399.659 | F75: 799.97802
A76: 6 months subscription, Monthly | B76: 5771.7391 | C76: 5964.1304 | D76: 5771.7391 | E76: 5964.1304 | F76: 5964.1304 | G76: 1923.913 | H76: 100988.65
A77: 13 month-Monthly
A78: 10 months | H78: 634.20195
A79: 3 months- Upfront
A80: 9 months subscription, Upfront | H80: 15738.417
A81: 2 month & 13 Days-Upfront | H81: 5133.8856
A82: 9 months & 23 days subscription, Upfront | H82: 4803.3309
A83: Total Result | B83: 1759682.3 | C83: 2405272.2 | D83: 2757193.1 | E83: 3403038.5 | F83: 4281722.2 | G83: 5248273.4 | H83: 5977772.3
B86: =B85/118% -> 0 | C86: =C85/118% -> 0 | D86: =D85/118% -> 0 | E86: =E85/118% -> 0 | F86: =F85/118% -> 0 | G86: =G85/118% -> 0 | H86: =H85/118% -> 0

Sheet FY 25-26-Accrual
A1: Coresphere100 Technologies Pvt. Ltd. | F1: Contracts expiring within | G1: 30 | H1: 45777 | I1: 45748 | N1: 45778 | O1: 45808 | R1: 45809 | W1: 45870
A2: Invoices Details | I2: =SUBTOTAL(9,I4:I1944) -> 64954444 | J2: =SUBTOTAL(9,J4:J1944) -> 2055112.7 | K2: =SUBTOTAL(9,K4:K1944) -> 2552644 | N2: =SUBTOTAL(9,N4:N1944) -> 1759682.3 | P2: =SUBTOTAL(9,P4:P1944) -> 2405272.2 | Q2: =SUBTOTAL(9,Q4:Q1944) -> 3025882 | R2: 45838 | S2: =SUBTOTAL(9,S4:S1944) -> 2757193.1 | T2: =SUBTOTAL(9,T4:T1944) -> 3675610.1 | U2: 45869 | V2: =SUBTOTAL(9,V4:V1944) -> 3382483.7 | W2: 45900 | X2: =SUBTOTAL(9,X4:X1944) -> 4553680.6 | Y2: =SUBTOTAL(9,Y4:Y1944) -> 4278677.1 | Z2: 45930 | AA2: =SUBTOTAL(9,AA4:AA1944) -> 5422252.7 | AB2: =SUBTOTAL(9,AB4:AB1944) -> 5248254 | AC2: 45961 | AD2: =SUBTOTAL(9,AD4:AD1944) -> 0 | AE2: =SUBTOTAL(9,AE4:AE1944) -> 0
A3: Contract | B3: Months | C3: Customer Name | D3: Invoice | E3: Nature of service | F3: Start Date | G3: End Date | H3: Payment Cycle | I3: Contract Amount | J3: Invoiced amount for April | K3: Invoiced amount for MAY | L3: Contract period | M3: Days in April | N3: April Sales (Days Wise) | O3: Days in May | P3: May Sales (Days Wise) | Q3: June in months | R3: Days in June | S3: June in days | T3: July in months | U3: Days in July | V3: July in days | W3: Days in Aug | X3: Aug Sales in months | Y3: Aug Sales in days | Z3: Days in Sept | AA3: Sept Sales in months | AB3: Sept Sales in days | AC3: Days in Oct | AD3: Oct Sales in months | AE3: Oct Sales in days
A4: 0 | B4: 45748 | C4: Touchstone Partners | D4: INV-25-26-000001 | E4: subscription based service | F4: 45748 | G4: 45838 | H4: 3 months subscription, upfront | I4: =60000+10800 -> 70800 | J4: 23600 | K4: =I4/3 -> 23600 | L4: =G4-F4+1 -> 91 | M4: =$H$1-F4+1 -> 30 | N4: =I4/L4*M4 -> 23340.659 | O4: =IF(F4<$O$1,31,$O$1-F4) -> 31 | P4: =O4*I4/L4 -> 24118.681 | Q4: =I4/3 -> 23600 | R4: =IF(F4<$R$2,30,$R$2-F4) -> 30 | S4: =R4*I4/L4 -> 23340.659 | U4: =IF(F5<$U$2,31,$U$2-F5) -> 31 | W4: 0 | X4: 0 | Y4: 0
A5: Closed- May 25 | B5: 45748 | C5: Bimal Rajasekhar | D5: INV-25-26-000002 | E5: subscription based service | F5: 45748 | G5: 45808 | H5: 2 months- Upfront | I5: 35400 | J5: 17700 | K5: =I5/2 -> 17700 | L5: =G5-F5+1 -> 61 | M5: =$H$1-F5+1 -> 30 | N5: =I5/L5*M5 -> 17409.836 | O5: =IF(F5<$O$1,31,$O$1-F5) -> 31 | P5: =O5*I5/L5 -> 17990.164 | R5: =IF(F5<$R$2,30,$R$2-F5) -> 30 | U5: =IF(F6<$U$2,31,$U$2-F6) -> 31 | W5: 0 | X5: 0 | Y5: 0
A6: 0 | B6: 45748 | C6: Veritas Legal Advocates and Solicitors | D6: INV-25-26-000003 | E6: subscription based service | F6: 45749 | G6: 45932 | H6: 6 month-Upfront | I6: =993600+178848 -> 1172448 | J6: 195408 | K6: =I6/6 -> 195408 | L6: =G6-F6+1 -> 184 | M6: =$H$1-F6+1 -> 29 | N6: =I6/L6*M6 -> 184788 | O6: =IF(F6<$O$1,31,$O$1-F6) -> 31 | P6: =O6*I6/L6 -> 197532 | Q6: =I6/6 -> 195408 | R6: =IF(F6<$R$2,30,$R$2-F6) -> 30 | S6: =R6*I6/L6 -> 191160 | T6: =I6/6 -> 195408 | U6: =IF(F7<$U$2,31,$U$2-F7) -> 31 | V6: =I6*U6/L6 -> 197532 | W6: =IF(F6<$W$2,31,$W$2-F6) -> 31 | X6: =I6/6 -> 195408 | Y6: =I6*W6/L6 -> 197532 | Z6: =IF(F6<$Z$2,30,$Z$2-I6) -> 30 | AA6: =I6/6 -> 195408 | AB6: =Z6*I6/L6 -> 191160
A7: 0 | B7: Apr & May 25 | C7: LEGALOGIC CONSULTING LLP | D7: INV-25-26-000004,104 | E7: subscription based service | F7: 45748 | G7: 45808 | H7: 2 months subscription, Monthly | I7: =35400*2 -> 70800 | J7: 35400 | K7: 35400 | L7: =G7-F7+1 -> 61 | M7: =$H$1-F7+1 -> 30 | N7: =I7/L7*M7 -> 34819.672 | O7: =IF(F7<$O$1,31,$O$1-F7) -> 31 | P7: =O7*I7/L7 -> 35980.328 | R7: =IF(F7<$R$2,30,$R$2-F7) -> 30 | U7: =IF(F8<$U$2,31,$U$2-F8) -> 31 | W7: 0 | X7: 0 | Y7: 0
A8: 0 | B8: 45748 | C8: VACUITAS COUNSELLOR LLP | D8: INV-25-26-000005 | E8: subscription based service | F8: 45750 | G8: 46114 | H8: Annual Upfront | I8: 116820 | J8: 9735 | K8: =I8/12 -> 9735 | L8: =G8-F8+1 -> 365 | M8: =$H$1-F8+1 -> 28 | N8: =I8/L8*M8 -> 8961.5342 | O8: =IF(F8<$O$1,31,$O$1-F8) -> 31 | P8: =O8*I8/L8 -> 9921.6986 | Q8: =I8/12 -> 9735 | R8: =IF(F8<$R$2,30,$R$2-F8) -> 30 | S8: =R8*I8/L8 -> 9601.6438 | T8: =I8/12 -> 9735 | U8: =IF(F9<$U$2,31,$U$2-F9) -> 31 | V8: =I8*U8/L8 -> 9921.6986 | W8: =IF(F8<$W$2,31,$W$2-F8) -> 31 | X8: =I8/12 -> 9735 | Y8: =I8*W8/L8 -> 9921.6986 | Z8: =IF(F8<$Z$2,30,$Z$2-I8) -> 30 | AA8: =I8/12 -> 9735 | AB8: =I8*Z8/L8 -> 9601.6438
A9: Closed-Apr 25 | B9: 45748 | C9: Tvashta Law | D9: INV-25-26-000006 | E9: One time work | F9: 45748 | G9: 45777 | H9: 1 month-Upfront | I9: 2360 | J9: 2360 | L9: =G9-F9+1 -> 30 | M9: 30 | N9: =I9/L9*M9 -> 2360 | O9: 0 | P9: =O9*I9/L9 -> 0 | R9: =IF(F9<$R$2,30,$R$2-F9) -> 30 | U9: =IF(F10<$U$2,31,$U$2-F10) -> 31 | W9: 0 | X9: 0 | Y9: 0
A10: 0 | B10: 45748 | C10: U. S. GANDHI & CO. | D10: INV-25-26-000007 | E10: subscription based service | F10: 45754 | G10: 45814 | H10: 2 months- Upfront | I10: 9440 | J10: =I10/2 -> 4720 | K10: =I10/2 -> 4720 | L10: =G10-F10+1 -> 61 | M10: =$H$1-F10+1 -> 24 | N10: =I10/L10*M10 -> 3714.0984 | O10: =IF(F10<$O$1,31,$O$1-F10) -> 31 | P10: =O10*I10/L10 -> 4797.377 | R10: =G10-$R$1+1 -> 6 | S10: =R10*I10/L10 -> 928.52459 | U10: =IF(F11<$U$2,31,$U$2-F11) -> 31 | W10: 0 | X10: 0 | Y10: 0
A11: Credit Note Issue | B11: 45748 | C11: Advocate Rohit Jaiswal | D11: INV-25-26-000009,00107,00177 | E11: subscription based service | F11: 45762 | G11: 45791 | H11: 1 month-Upfront | I11: =5900*1 -> 5900 | J11: 5900 | K11: 0 | L11: =G11-F11+1 -> 30 | M11: =$H$1-F11+1 -> 16 | N11: =I11/L11*M11 -> 3146.6667 | O11: =G11-N1+1 -> 14 | P11: =O11*I11/L11 -> 2753.3333 | S11: =R11*I11/L11 -> 0 | V11: =I11*U11/L11 -> 0 | W11: 0 | X11: 0 | Y11: 0
A12: 0 | B12: 45748 | C12: Dileep Poolakkot | D12: INV-25-26-000010 | E12: subscription based service | F12: 45755 | G12: 46119 | H12: Annual Upfront | I12: =60000*118% -> 70800 | J12: 5900 | K12: =I12/12 -> 5900 | L12: =G12-F12+1 -> 365 | M12: =$H$1-F12+1 -> 23 | N12: =I12/L12*M12 -> 4461.3699 | O12: =IF(F12<$O$1,31,$O$1-F12) -> 31 | P12: =O12*I12/L12 -> 6013.1507 | Q12: =I12/12 -> 5900 | R12: =IF(F12<$R$2,30,$R$2-F12) -> 30 | S12: =R12*I12/L12 -> 5819.1781 | T12: =I12/12 -> 5900 | U12: =IF(F13<$U$2,31,$U$2-F13) -> 31 | V12: =I12*U12/L12 -> 6013.1507 | W12: =IF(F12<$W$2,31,$W$2-F12) -> 31 | X12: =I12/12 -> 5900 | Y12: =I12*W12/L12 -> 6013.1507 | Z12: =IF(F12<$Z$2,30,$Z$2-I12) -> 30 | AA12: =I12/12 -> 5900 | AB12: =I12*Z12/L12 -> 5819.1781
A13: 0 | B13: 45748 | C13: Utkarsh Joshi | D13: INV-25-26-000011 | E13: subscription based service | F13: 45755 | G13: 45815 | H13: 2 months- Upfront | I13: 7080 | J13: 3540 | K13: =I13/2 -> 3540 | L13: =G13-F13+1 -> 61 | M13: =$H$1-F13+1 -> 23 | N13: =I13/L13*M13 -> 2669.5082 | O13: =IF(F13<$O$1,31,$O$1-F13) -> 31 | P13: =O13*I13/L13 -> 3598.0328 | R13: 7 | S13: =R13*I13/L13 -> 812.45902 | U13: =IF(F14<$U$2,31,$U$2-F14) -> 31 | W13: 0 | X13: 0 | Y13: 0
A14: 0 | B14: 45748 | C14: Karan Butalia | D14: INV-25-26-000012 | E14: subscription based service | F14: 45755 | G14: 45815 | H14: 2 months- Upfront | I14: 4720 | J14: 2360 | K14: 2360 | L14: =G14-F14+1 -> 61 | M14: =$H$1-F14+1 -> 23 | N14: =I14/L14*M14 -> 1779.6721 | O14: =IF(F14<$O$1,31,$O$1-F14) -> 31 | P14: =O14*I14/L14 -> 2398.6885 | R14: 7 | S14: =R14*I14/L14 -> 541.63934 | U14: =IF(F15<$U$2,31,$U$2-F15) -> 31 | W14: 0 | X14: 0 | Y14: 0
A15: 0 | B15: Jan & Apr & July & Oct 25 | C15: Agama Law Associates | D15: INV- 46, INV-25-26-000013, 277, 483 | E15: subscription based service | F15: 45658 | G15: 46022 | H15: Annual subscription, Quarterly upfront | I15: =80000*4 -> 320000 | J15: 26666.667 | K15: =I15/12 -> 26666.667 | L15: =G15-F15+1 -> 365 | M15: =IF(F17<$H$1,30,$H$1-F17) -> 30 | N15: =I15/L15*M15 -> 26301.37 | O15: =IF(F15<$O$1,31,$O$1-F15) -> 31 | P15: =O15*I15/L15 -> 27178.082 | Q15: =I15/12 -> 26666.667 | R15: =IF(F15<$R$2,30,$R$2-F15) -> 30 | S15: =R15*I15/L15 -> 26301.37 | T15: =I15/12 -> 26666.667 | U15: =IF(F16<$U$2,31,$U$2-F16) -> 31 | V15: =I15*U15/L15 -> 27178.082 | W15: =IF(F15<$W$2,31,$W$2-F15) -> 31 | X15: =I15/12 -> 26666.667 | Y15: =I15*W15/L15 -> 27178.082 | Z15: =IF(F15<$Z$2,30,$Z$2-I15) -> 30 | AA15: =I15/12 -> 26666.667 | AB15: =I15*Z15/L15 -> 26301.37
A16: Closed- May 25 | B16: 45748 | C16: RAJANI ASSOCIATES | D16: INV-25-26-000014 | E16: subscription based service | F16: 45757 | G16: 45786 | H16: 1 month-Upfront | I16: 24780 | J16: 24780 | L16: =G16-F16+1 -> 30 | M16: =$H$1-F16+1 -> 21 | N16: =I16/L16*M16 -> 17346 | O16: =L16-M16 -> 9 | P16: =O16*I16/L16 -> 7434 | R16: =IF(F16<$R$2,30,$R$2-F16) -> 30 | U16: =IF(F17<$U$2,31,$U$2-F17) -> 31 | W16: 0 | X16: 0 | Y16: 0
A17: 0 | B17: 45748 | C17: Venkatesh Dhond | D17: INV-25-26-000015 | E17: subscription based service | F17: 45716 | G17: 45896 | H17: 6 month-Upfront | I17: 100890 | J17: 16815 | K17: =I17/6 -> 16815 | L17: =G17-F17+1 -> 181 | M17: =IF(F17<H1,30,H1-F17) -> 30 | N17: =I17/L17*M17 -> 16722.099 | O17: =IF(F17<$O$1,31,$O$1-F17) -> 31 | P17: =O17*I17/L17 -> 17279.503 | Q17: =I17/6 -> 16815 | R17: =IF(F17<$R$2,30,$R$2-F17) -> 30 | S17: =R17*I17/L17 -> 16722.099 | T17: =I17/6 -> 16815 | U17: =IF(F18<$U$2,31,$U$2-F18) -> 31 | V17: =I17*U17/L17 -> 17279.503 | W17: =G17-$W$1+1 -> 27 | X17: 0 | Y17: =I17*W17/L17 -> 15049.89
A18: 0 | B18: Mar to June 25 | C18: Harshit Malik | D18: INV-000111, INV-25-26-000016, 0109 | E18: subscription based service | F18: 45725 | G18: 45786 | H18: 2 months subscription, Monthly | I18: =11800*4-11800*2 -> 23600 | J18: 11800 | L18: =G18-F18+1 -> 62 | M18: =IF(F18<H3,30,H3-F18) -> 30 | N18: =I18/L18*M18 -> 11419.355 | O18: 9 | P18: =O18*I18/L18 -> 3425.8065 | R18: =30 -> 30 | U18: =IF(F19<$U$2,31,$U$2-F19) -> 31 | W18: 0 | X18: 0 | Y18: 0
A19: 0 | B19: 45748 | C19: PSN Legal Advocates and Legal Consultants | D19: INV-25-26-000017 | E19: subscription based service | F19: 45757 | G19: 46121 | H19: Annual Upfront | I19: 177015 | J19: 14751.25 | K19: =I19/12 -> 14751.25 | L19: =G19-F19+1 -> 365 | M19: =$H$1-F19+1 -> 21 | N19: =I19/L19*M19 -> 10184.425 | O19: =IF(F19<$O$1,31,$O$1-F19) -> 31 | P19: =O19*I19/L19 -> 15034.151 | Q19: =I19/12 -> 14751.25 | R19: =IF(F19<$R$2,30,$R$2-F19) -> 30 | S19: =R19*I19/L19 -> 14549.178 | T19: =I19/12 -> 14751.25 | U19: =IF(F20<$U$2,31,$U$2-F20) -> 31 | V19: =I19*U19/L19 -> 15034.151 | W19: =IF(F19<$W$2,31,$W$2-F19) -> 31 | X19: =I19/12 -> 14751.25 | Y19: =I19*W19/L19 -> 15034.151 | Z19: =IF(F19<$Z$2,30,$Z$2-I19) -> 30 | AA19: =I19/12 -> 14751.25 | AB19: =I19*Z19/L19 -> 14549.178
A20: 0 | B20: Apr to July 25 | C20: Swapna Sheshadri | D20: INV-25-26-000019, 113, 0184, 259 | E20: subscription based service | F20: 45757 | G20: 45878 | H20: 4 months subscription, Monthly | I20: =11800*4 -> 47200 | J20: 11800 | K20: 11800 | L20: =G20-F20+1 -> 122 | M20: =$H$1-F20+1 -> 21 | N20: =I20/L20*M20 -> 8124.5902 | O20: =IF(F20<$O$1,31,$O$1-F20) -> 31 | P20: =O20*I20/L20 -> 11993.443 | Q20: =I20/4 -> 11800 | R20: =IF(F20<$R$2,30,$R$2-F20) -> 30 | S20: =R20*I20/L20 -> 11606.557 | T20: =I20/4 -> 11800 | U20: =IF(F21<$U$2,31,$U$2-F21) -> 31 | V20: =I20*U20/L20 -> 11993.443 | W20: =G20-$W$1+1 -> 9 | Y20: =W20*I20/L20 -> 3481.9672
A21: 0 | B21: 45748 | C21: Vutts & Associates LLP | D21: INV-25-26-000020 | E21: subscription based service | F21: 45758 | G21: 45848 | H21: 3 months subscription, upfront | I21: 35400 | J21: 11800 | K21: =I21/3 -> 11800 | L21: =G21-F21+1 -> 91 | M21: =$H$1-F21+1 -> 20 | N21: =I21/L21*M21 -> 7780.2198 | O21: =IF(F21<$O$1,31,$O$1-F21) -> 31 | P21: =O21*I21/L21 -> 12059.341 | Q21: =I21/3 -> 11800 | R21: =IF(F21<$R$2,30,$R$2-F21) -> 30 | S21: =R21*I21/L21 -> 11670.33 | U21: =G21-$R$2 -> 10 | V21: =U21*I21/L21 -> 3890.1099 | W21: 0 | X21: 0 | Y21: 0
A22: 0 | B22: Feb Apr to Oct 25 | C22: Darius J. Khambata | D22: INV-000085, INV-25-26-000021,INV-25-26-000022, 148,178, 248, 337, 416, 500 | E22: subscription based service | F22: 45695 | G22: 46059 | H22: Annual-Monthly | I22: =20000*12 -> 240000 | J22: 20000 | K22: =I22/12 -> 20000 | L22: =G22-F22+1 -> 365 | M22: =IF(F22<H7,30,H7-F22) -> 30 | N22: =I22/L22*M22 -> 19726.027 | O22: =IF(F22<$O$1,31,$O$1-F22) -> 31 | P22: =O22*I22/L22 -> 20383.562 | Q22: =I22/12 -> 20000 | R22: =IF(F22<$R$2,30,$R$2-F22) -> 30 | S22: =R22*I22/L22 -> 19726.027 | T22: =I22/12 -> 20000 | U22: =IF(F23<$U$2,31,$U$2-F23) -> 31 | V22: =I22*U22/L22 -> 20383.562 | W22: =IF(F22<$W$2,31,$W$2-F22) -> 31 | X22: =I22/12 -> 20000 | Y22: =I22*W22/L22 -> 20383.562 | Z22: =IF(F22<$Z$2,30,$Z$2-I22) -> 30 | AA22: =I22/12 -> 20000 | AB22: =I22*Z22/L22 -> 19726.027
A23: 0 | B23: 45748 | C23: Miglani Varma & Co. | D23: INV-25-26-000023 | E23: subscription based service | F23: 45758 | G23: 45848 | H23: 3 months subscription, upfront | I23: 17700 | J23: 5900 | K23: =I23/3 -> 5900 | L23: =G23-F23+1 -> 91 | M23: =$H$1-F23+1 -> 20 | N23: =I23/L23*M23 -> 3890.1099 | O23: =IF(F23<$O$1,31,$O$1-F23) -> 31 | P23: =O23*I23/L23 -> 6029.6703 | Q23: =I23/3 -> 5900 | R23: =IF(F23<$R$2,30,$R$2-F23) -> 30 | S23: =R23*I23/L23 -> 5835.1648 | U23: =G23-$R$2 -> 10 | V23: =U23*I23/L23 -> 1945.0549 | W23: 0 | X23: 0 | Y23: 0
A24: Closed- May 25 | B24: 45748 | C24: Venkatesh Mohanraj | D24: INV-25-26-000024 | E24: subscription based service | F24: 45759 | G24: 45788 | H24: 1 month-Upfront | I24: 5900 | J24: 5900 | L24: =G24-F24+1 -> 30 | M24: =$H$1-F24+1 -> 19 | N24: =I24/L24*M24 -> 3736.6667 | O24: =L24-M24 -> 11 | P24: =O24*I24/L24 -> 2163.3333 | R24: =IF(F24<$R$2,30,$R$2-F24) -> 30 | U24: =IF(F25<$U$2,31,$U$2-F25) -> 31 | W24: 0 | X24: 0 | Y24: 0
A25: Closed- May 25 | B25: 45748 | C25: Jade Lex Partners | D25: INV-25-26-000025 | E25: subscription based service | F25: 45759 | G25: 45788 | H25: 1 month-Upfront | I25: 7080 | J25: 7080 | L25: =G25-F25+1 -> 30 | M25: =$H$1-F25+1 -> 19 | N25: =I25/L25*M25 -> 4484 | O25: =L25-M25 -> 11 | P25: =O25*I25/L25 -> 2596 | R25: =IF(F25<$R$2,30,$R$2-F25) -> 30 | U25: =IF(F26<$U$2,31,$U$2-F26) -> 31 | W25: 0 | X25: 0 | Y25: 0
A26: Closed- May 25 | B26: 45748 | C26: Alankrit Bajpai | D26: INV-25-26-000026 | E26: subscription based service | F26: 45759 | G26: 45788 | H26: 1 month-Upfront | I26: 5900 | J26: 5900 | L26: =G26-F26+1 -> 30 | M26: =$H$1-F26+1 -> 19 | N26: =I26/L26*M26 -> 3736.6667 | O26: =L26-M26 -> 11 | P26: =O26*I26/L26 -> 2163.3333 | R26: =IF(F26<$R$2,30,$R$2-F26) -> 30 | U26: =IF(F27<$U$2,31,$U$2-F27) -> 31 | W26: 0 | X26: 0 | Y26: 0
A27: Closed- May 25 | B27: 45748 | C27: Badar Durrez | D27: INV-25-26-000028 | E27: subscription based service | F27: 45760 | G27: 45789 | H27: 1 month-Upfront | I27: 5900 | J27: 5900 | L27: =G27-F27+1 -> 30 | M27: =$H$1-F27+1 -> 18 | N27: =I27/L27*M27 -> 3540 | O27: =L27-M27 -> 12 | P27: =O27*I27/L27 -> 2360 | R27: =IF(F27<$R$2,30,$R$2-F27) -> 30 | U27: =IF(F28<$U$2,31,$U$2-F28) -> 31 | W27: 0 | X27: 0 | Y27: 0
A28: 0 | B28: 45748 | C28: Rashmikant and Partners | D28: INV-25-26-000029 | E28: subscription based service | F28: 45761 | G28: 46125 | H28: Annual Upfront | I28: 259600 | J28: 21633.333 | K28: =I28/12 -> 21633.333 | L28: =G28-F28+1 -> 365 | M28: =$H$1-F28+1 -> 17 | N28: =I28/L28*M28 -> 12090.959 | O28: =IF(F28<$O$1,31,$O$1-F28) -> 31 | P28: =O28*I28/L28 -> 22048.219 | Q28: =I28/12 -> 21633.333 | R28: =IF(F28<$R$2,30,$R$2-F28) -> 30 | S28: =R28*I28/L28 -> 21336.986 | T28: =I28/12 -> 21633.333 | U28: =IF(F29<$U$2,31,$U$2-F29) -> 31 | V28: =I28*U28/L28 -> 22048.219 | W28: =IF(F28<$W$2,31,$W$2-F28) -> 31 | X28: =I28/12 -> 21633.333 | Y28: =I28*W28/L28 -> 22048.219 | Z28: =IF(F28<$Z$2,30,$Z$2-I28) -> 30 | AA28: =I28/12 -> 21633.333 | AB28: =I28*Z28/L28 -> 21336.986
A29: 0 | B29: Apr to June 25 | C29: TLH, Advocates & Solicitors | D29: INV-25-26-000030, 124, 198,271 | E29: subscription based service | F29: 45762 | G29: 45852 | H29: 3 months subscription, Monthly | I29: =177000*3 -> 531000 | J29: 177000 | K29: =I29/3 -> 177000 | L29: =G29-F29+1 -> 91 | M29: 16 | N29: =I29/L29*M29 -> 93362.637 | O29: =IF(F29<$O$1,31,$O$1-F29) -> 31 | P29: =O29*I29/L29 -> 180890.11 | Q29: =I29/3 -> 177000 | R29: =IF(F29<$R$2,30,$R$2-F29) -> 30 | S29: =R29*I29/L29 -> 175054.95 | U29: 14 | V29: =I29*U29/L29 -> 81692.308 | W29: 0 | X29: 0 | Y29: 0
A30: 0 | B30: 45748 | C30: Shreeyash Lalit | D30: INV-25-26-000032 | E30: subscription based service | F30: 45762 | G30: 45944 | H30: 6 month-Upfront | I30: 42480 | J30: 7080 | K30: =I30/6 -> 7080 | L30: =G30-F30+1 -> 183 | M30: =$H$1-F30+1 -> 16 | N30: =I30/L30*M30 -> 3714.0984 | O30: =IF(F30<$O$1,31,$O$1-F30) -> 31 | P30: =O30*I30/L30 -> 7196.0656 | Q30: =I30/6 -> 7080 | R30: =IF(F30<$R$2,30,$R$2-F30) -> 30 | S30: =R30*I30/L30 -> 6963.9344 | T30: =I30/6 -> 7080 | U30: =IF(F31<$U$2,31,$U$2-F31) -> 31 | V30: =I30*U30/L30 -> 7196.0656 | W30: =IF(F30<$W$2,31,$W$2-F30) -> 31 | X30: =I30/6 -> 7080 | Y30: =I30*W30/L30 -> 7196.0656 | Z30: =IF(F30<$Z$2,30,$Z$2-I30) -> 30 | AA30: =I30/6 -> 7080 | AB30: =Z30*I30/L30 -> 6963.9344
A31: 0 | B31: 45748 | C31: Dewani Associates | D31: INV-25-26-000033 | E31: subscription based service | F31: 45762 | G31: 45823 | H31: 2 months- Upfront | I31: 23600 | J31: 11800 | K31: =I31/2 -> 11800 | L31: =G31-F31+1 -> 62 | M31: =$H$1-F31+1 -> 16 | N31: =I31/L31*M31 -> 6090.3226 | O31: =IF(F31<$O$1,31,$O$1-F31) -> 31 | P31: =O31*I31/L31 -> 11800 | R31: 15 | S31: =R31*I31/L31 -> 5709.6774 | U31: =IF(F32<$U$2,31,$U$2-F32) -> 31 | W31: 0 | X31: 0 | Y31: 0
A32: 0 | B32: Apr to Oct 25 | C32: R. Vishnu Kumar, Advocate | D32: INV-25-26-000034, 125, 199, 272, 358, 528 | E32: subscription based service | F32: 45762 | G32: 46126 | H32: Annual-Monthly | I32: =20000*12 -> 240000 | J32: 20000 | K32: 20000 | L32: =G32-F32+1 -> 365 | M32: =$H$1-F32+1 -> 16 | N32: =I32/L32*M32 -> 10520.548 | O32: =IF(F32<$O$1,31,$O$1-F32) -> 31 | P32: =O32*I32/L32 -> 20383.562 | Q32: =I32/12 -> 20000 | R32: =IF(F32<$R$2,30,$R$2-F32) -> 30 | S32: =R32*I32/L32 -> 19726.027 | T32: =I32/12 -> 20000 | U32: =IF(F33<$U$2,31,$U$2-F33) -> 31 | V32: =I32*U32/L32 -> 20383.562 | W32: =IF(F32<$W$2,31,$W$2-F32) -> 31 | X32: =I32/12 -> 20000 | Y32: =I32*W32/L32 -> 20383.562 | Z32: =IF(F32<$Z$2,30,$Z$2-I32) -> 30 | AA32: =I32/12 -> 20000 | AB32: =I32*Z32/L32 -> 19726.027
A33: 0 | B33: Mar & Apr 25 | C33: Yash Momaya | D33: INV-25-26-000035, 0127, 0200 | E33: subscription based service | F33: 45763 | G33: 45792 | H33: 1 month-Upfront | I33: =11800*3-11800*2 -> 11800 | J33: 11800 | L33: =G33-F33+1 -> 30 | M33: =$H$1-F33+1 -> 15 | N33: =I33/L33*M33 -> 5900 | O33: =G33-N1+1 -> 15 | P33: =O33*I33/L33 -> 5900 | Q33: 0 | R33: =IF(F33<$R$2,30,$R$2-F33) -> 30 | S33: 0 | T33: 0 | U33: =IF(F34<$U$2,31,$U$2-F34) -> 31 | V33: 0 | W33: 0 | X33: 0 | Y33: 0
A34: Closed- May 25 | B34: 45748 | C34: Chetan Dedhia | D34: INV-25-26-000036 | E34: subscription based service | F34: 45763 | G34: 45792 | H34: 1 month-Upfront | I34: 17700 | J34: 17700 | L34: =G34-F34+1 -> 30 | M34: =$H$1-F34+1 -> 15 | N34: =I34/L34*M34 -> 8850 | O34: =L34-M34 -> 15 | P34: =O34*I34/L34 -> 8850 | R34: =IF(F34<$R$2,30,$R$2-F34) -> 30 | U34: =IF(F35<$U$2,31,$U$2-F35) -> 31 | W34: 0 | X34: 0 | Y34: 0
A35: 0 | B35: 45748 | C35: NC Legal | D35: INV-25-26-000037 | E35: subscription based service | F35: 45778 | G35: 46142 | H35: Annual Upfront | I35: 80240 | K35: =I35/12 -> 6686.6667 | L35: =G35-F35+1 -> 365 | M35: =$H$1-F35+1 -> 0 | N35: =I35/L35*M35 -> 0 | O35: =$O$1-F35+1 -> 31 | P35: =O35*I35/L35 -> 6814.9041 | Q35: =I35/12 -> 6686.6667 | R35: =IF(F35<$R$2,30,$R$2-F35) -> 30 | S35: =R35*I35/L35 -> 6595.0685 | T35: =I35/12 -> 6686.6667 | U35: =IF(F36<$U$2,31,$U$2-F36) -> 31 | V35: =I35*U35/L35 -> 6814.9041 | W35: =IF(F35<$W$2,31,$W$2-F35) -> 31 | X35: =I35/12 -> 6686.6667 | Y35: =I35*W35/L35 -> 6814.9041 | Z35: =IF(F35<$Z$2,30,$Z$2-I35) -> 30 | AA35: =I35/12 -> 6686.6667 | AB35: =I35*Z35/L35 -> 6595.0685
A36: Closed- May 25 | B36: 45748 | C36: Aakash Sharma | D36: INV-25-26-000038 | E36: subscription based service | F36: 45765 | G36: 45795 | H36: 1 month-Upfront | I36: 5900 | J36: 5900 | L36: =G36-F36+1 -> 31 | M36: =$H$1-F36+1 -> 13 | N36: =I36/L36*M36 -> 2474.1935 | O36: =L36-M36 -> 18 | P36: =O36*I36/L36 -> 3425.8065 | R36: =IF(F36<$R$2,30,$R$2-F36) -> 30 | U36: =IF(F37<$U$2,31,$U$2-F37) -> 31 | W36: 0 | X36: 0 | Y36: 0
A37: Closed- May 25 | B37: 45748 | C37: Saga Legal | D37: INV-25-26-000039 | E37: subscription based service | F37: 45761 | G37: 45791 | H37: 1 month-Upfront | I37: 23600 | J37: 23600 | L37: =G37-F37+1 -> 31 | M37: =$H$1-F37+1 -> 17 | N37: =I37/L37*M37 -> 12941.935 | O37: =L37-M37 -> 14 | P37: =O37*I37/L37 -> 10658.065 | R37: =IF(F37<$R$2,30,$R$2-F37) -> 30 | U37: =IF(F38<$U$2,31,$U$2-F38) -> 31 | W37: 0 | X37: 0 | Y37: 0
A38: 0 | B38: 45748 | C38: RPV LEGAL | D38: INV-25-26-000040 | E38: subscription based service | F38: 45769 | G38: 46133 | H38: Annual Upfront | I38: 175000 | J38: 14583.333 | K38: =I38/12 -> 14583.333 | L38: =G38-F38+1 -> 365 | M38: =$H$1-F38+1 -> 9 | N38: =I38/L38*M38 -> 4315.0685 | O38: =IF(F38<$O$1,31,$O$1-F38) -> 31 | P38: =O38*I38/L38 -> 14863.014 | Q38: =I38/12 -> 14583.333 | R38: =IF(F38<$R$2,30,$R$2-F38) -> 30 | S38: =R38*I38/L38 -> 14383.562 | T38: =I38/12 -> 14583.333 | U38: =IF(F39<$U$2,31,$U$2-F39) -> 31 | V38: =I38*U38/L38 -> 14863.014 | W38: =IF(F38<$W$2,31,$W$2-F38) -> 31 | X38: =I38/12 -> 14583.333 | Y38: =I38*W38/L38 -> 14863.014 | Z38: =IF(F38<$Z$2,30,$Z$2-I38) -> 30 | AA38: =I38/12 -> 14583.333 | AB38: =I38*Z38/L38 -> 14383.562
A39: 0 | B39: 45748 | C39: AP & Partners, Advocates | D39: INV-25-26-000041 | E39: subscription based service | F39: 45771 | G39: 45860 | H39: 3 months subscription, upfront | I39: 28320 | J39: 9440 | K39: =I39/3 -> 9440 | L39: =G39-F39+1 -> 90 | M39: =$H$1-F39+1 -> 7 | N39: =I39/L39*M39 -> 2202.6667 | O39: =IF(F39<$O$1,31,$O$1-F39) -> 31 | P39: =O39*I39/L39 -> 9754.6667 | Q39: =I39/3 -> 9440 | R39: =IF(F39<$R$2,30,$R$2-F39) -> 30 | S39: =R39*I39/L39 -> 9440 | U39: =G39-$R$2 -> 22 | V39: =U39*I39/L39 -> 6922.6667 | W39: 0 | X39: 0 | Y39: 0
A40: Credit Note Issue | B40: Apr to June 25 | C40: Pranay Chitale | D40: INV-25-26-000042, 137, 213 | E40: subscription based service | F40: 45770 | G40: 45799 | H40: 1 month-Upfront | I40: =17700 -> 17700 | J40: 17700 | L40: =G40-F40+1 -> 30 | M40: =$H$1-F40+1 -> 8 | N40: =I40/L40*M40 -> 4720 | O40: =G40-N1+1 -> 22 | P40: =O40*I40/L40 -> 12980 | W40: 0 | X40: 0 | Y40: 0
A41: Closed- May 25 | B41: 45748 | C41: Spark Legal | D41: INV-25-26-000043 | E41: subscription based service | F41: 45771 | G41: 45800 | H41: 1 month-Upfront | I41: 11800 | J41: 11800 | L41: =G41-F41+1 -> 30 | M41: =$H$1-F41+1 -> 7 | N41: =I41/L41*M41 -> 2753.3333 | O41: =L41-M41 -> 23 | P41: =O41*I41/L41 -> 9046.6667 | R41: =IF(F41<$R$2,30,$R$2-F41) -> 30 | U41: =IF(F42<$U$2,31,$U$2-F42) -> 31 | W41: 0 | X41: 0 | Y41: 0
A42: 0 | B42: 45748 | C42: Bathiya Legal | D42: INV-25-26-000044 | E42: subscription based service | F42: 45771 | G42: 45862 | H42: 3 months subscription, upfront | I42: =35400 -> 35400 | J42: 11800 | K42: =I42/3 -> 11800 | L42: =G42-F42+1 -> 92 | M42: =$H$1-F42+1 -> 7 | N42: =I42/L42*M42 -> 2693.4783 | O42: =IF(F42<$O$1,31,$O$1-F42) -> 31 | P42: =O42*I42/L42 -> 11928.261 | Q42: =I42/3 -> 11800 | R42: =IF(F42<$R$2,30,$R$2-F42) -> 30 | S42: =R42*I42/L42 -> 11543.478 | U42: =G42-$R$2 -> 24 | V42: =U42*I42/L42 -> 9234.7826 | W42: 0 | X42: 0 | Y42: 0
A43: 0 | B43: 45748 | C43: Justice (Retd.) Kurian Joseph | D43: INV-25-26-000045 | E43: subscription based service | F43: 45774 | G43: 46138 | H43: Annual Upfront | I43: 177000 | J43: 14750 | K43: =I43/12 -> 14750 | L43: =G43-F43+1 -> 365 | M43: =$H$1-F43+1 -> 4 | N43: =I43/L43*M43 -> 1939.726 | O43: =IF(F43<$O$1,31,$O$1-F43) -> 31 | P43: =O43*I43/L43 -> 15032.877 | Q43: =I43/12 -> 14750 | R43: =IF(F43<$R$2,30,$R$2-F43) -> 30 | S43: =R43*I43/L43 -> 14547.945 | T43: =I43/12 -> 14750 | U43: =IF(F44<$U$2,31,$U$2-F44) -> 31 | V43: =I43*U43/L43 -> 15032.877 | W43: =IF(F43<$W$2,31,$W$2-F43) -> 31 | X43: =I43/12 -> 14750 | Y43: =I43*W43/L43 -> 15032.877 | Z43: =IF(F43<$Z$2,30,$Z$2-I43) -> 30 | AA43: =I43/12 -> 14750 | AB43: =I43*Z43/L43 -> 14547.945
A44: 0 | B44: 45748 | C44: SINHA & COMPANY | D44: INV-25-26-000046 | E44: subscription based service | F44: 45772 | G44: 46136 | H44: Annual Upfront | I44: 203904 | J44: 16992 | K44: =I44/12 -> 16992 | L44: =G44-F44+1 -> 365 | M44: =$H$1-F44+1 -> 6 | N44: =I44/L44*M44 -> 3351.8466 | O44: =IF(F44<$O$1,31,$O$1-F44) -> 31 | P44: =O44*I44/L44 -> 17317.874 | Q44: =I44/12 -> 16992 | R44: =IF(F44<$R$2,30,$R$2-F44) -> 30 | S44: =R44*I44/L44 -> 16759.233 | T44: =I44/12 -> 16992 | U44: =IF(F45<$U$2,31,$U$2-F45) -> 31 | V44: =I44*U44/L44 -> 17317.874 | W44: =IF(F44<$W$2,31,$W$2-F44) -> 31 | X44: =I44/12 -> 16992 | Y44: =I44*W44/L44 -> 17317.874 | Z44: =IF(F44<$Z$2,30,$Z$2-I44) -> 30 | AA44: =I44/12 -> 16992 | AB44: =I44*Z44/L44 -> 16759.233
A45: 0 | B45: 45748 | C45: Darshit Jain | D45: INV-25-26-000047 | E45: subscription based service | F45: 45772 | G45: 46136 | H45: Annual Upfront | I45: 25488 | J45: 2124 | K45: =I45/12 -> 2124 | L45: =G45-F45+1 -> 365 | M45: =$H$1-F45+1 -> 6 | N45: =I45/L45*M45 -> 418.98082 | O45: =IF(F45<$O$1,31,$O$1-F45) -> 31 | P45: =O45*I45/L45 -> 2164.7342 | Q45: =I45/12 -> 2124 | R45: =IF(F45<$R$2,30,$R$2-F45) -> 30 | S45: =R45*I45/L45 -> 2094.9041 | T45: =I45/12 -> 2124 | U45: =IF(F46<$U$2,31,$U$2-F46) -> 31 | V45: =I45*U45/L45 -> 2164.7342 | W45: =IF(F45<$W$2,31,$W$2-F45) -> 31 | X45: =I45/12 -> 2124 | Y45: =I45*W45/L45 -> 2164.7342 | Z45: =IF(F45<$Z$2,30,$Z$2-I45) -> 30 | AA45: =I45/12 -> 2124 | AB45: =I45*Z45/L45 -> 2094.9041
A46: 0 | B46: 45748 | C46: Sagar Ghogre | D46: INV-25-26-000048 | E46: subscription based service | F46: 45772 | G46: 46136 | H46: Annual Upfront | I46: 25488 | J46: 2124 | K46: =I46/12 -> 2124 | L46: =G46-F46+1 -> 365 | M46: =$H$1-F46+1 -> 6 | N46: =I46/L46*M46 -> 418.98082 | O46: =IF(F46<$O$1,31,$O$1-F46) -> 31 | P46: =O46*I46/L46 -> 2164.7342 | Q46: =I46/12 -> 2124 | R46: =IF(F46<$R$2,30,$R$2-F46) -> 30 | S46: =R46*I46/L46 -> 2094.9041 | T46: =I46/12 -> 2124 | U46: =IF(F47<$U$2,31,$U$2-F47) -> 31 | V46: =I46*U46/L46 -> 2164.7342 | W46: =IF(F46<$W$2,31,$W$2-F46) -> 31 | X46: =I46/12 -> 2124 | Y46: =I46*W46/L46 -> 2164.7342 | Z46: =IF(F46<$Z$2,30,$Z$2-I46) -> 30 | AA46: =I46/12 -> 2124 | AB46: =I46*Z46/L46 -> 2094.9041
A47: 0 | B47: 45748 | C47: Chetan shah | D47: INV-25-26-000049 | E47: subscription based service | F47: 45772 | G47: 46136 | H47: Annual Upfront | I47: 25488 | J47: 2124 | K47: =I47/12 -> 2124 | L47: =G47-F47+1 -> 365 | M47: =$H$1-F47+1 -> 6 | N47: =I47/L47*M47 -> 418.98082 | O47: =IF(F47<$O$1,31,$O$1-F47) -> 31 | P47: =O47*I47/L47 -> 2164.7342 | Q47: =I47/12 -> 2124 | R47: =IF(F47<$R$2,30,$R$2-F47) -> 30 | S47: =R47*I47/L47 -> 2094.9041 | T47: =I47/12 -> 2124 | U47: =IF(F48<$U$2,31,$U$2-F48) -> 31 | V47: =I47*U47/L47 -> 2164.7342 | W47: =IF(F47<$W$2,31,$W$2-F47) -> 31 | X47: =I47/12 -> 2124 | Y47: =I47*W47/L47 -> 2164.7342 | Z47: =IF(F47<$Z$2,30,$Z$2-I47) -> 30 | AA47: =I47/12 -> 2124 | AB47: =I47*Z47/L47 -> 2094.9041
A48: 0 | B48: 45748 | C48: Sneha Phene | D48: INV-25-26-000050 | E48: subscription based service | F48: 45772 | G48: 46136 | H48: Annual Upfront | I48: 25488 | J48: 2124 | K48: =I48/12 -> 2124 | L48: =G48-F48+1 -> 365 | M48: =$H$1-F48+1 -> 6 | N48: =I48/L48*M48 -> 418.98082 | O48: =IF(F48<$O$1,31,$O$1-F48) -> 31 | P48: =O48*I48/L48 -> 2164.7342 | Q48: =I48/12 -> 2124 | R48: =IF(F48<$R$2,30,$R$2-F48) -> 30 | S48: =R48*I48/L48 -> 2094.9041 | T48: =I48/12 -> 2124 | U48: =IF(F49<$U$2,31,$U$2-F49) -> 31 | V48: =I48*U48/L48 -> 2164.7342 | W48: =IF(F48<$W$2,31,$W$2-F48) -> 31 | X48: =I48/12 -> 2124 | Y48: =I48*W48/L48 -> 2164.7342 | Z48: =IF(F48<$Z$2,30,$Z$2-I48) -> 30 | AA48: =I48/12 -> 2124 | AB48: =I48*Z48/L48 -> 2094.9041
A49: 0 | B49: 45748 | C49: Gunjan Mangla | D49: INV-25-26-000051 | E49: subscription based service | F49: 45772 | G49: 46136 | H49: Annual Upfront | I49: 25488 | J49: 2124 | K49: =I49/12 -> 2124 | L49: =G49-F49+1 -> 365 | M49: =$H$1-F49+1 -> 6 | N49: =I49/L49*M49 -> 418.98082 | O49: =IF(F49<$O$1,31,$O$1-F49) -> 31 | P49: =O49*I49/L49 -> 2164.7342 | Q49: =I49/12 -> 2124 | R49: =IF(F49<$R$2,30,$R$2-F49) -> 30 | S49: =R49*I49/L49 -> 2094.9041 | T49: =I49/12 -> 2124 | U49: =IF(F50<$U$2,31,$U$2-F50) -> 31 | V49: =I49*U49/L49 -> 2164.7342 | W49: =IF(F49<$W$2,31,$W$2-F49) -> 31 | X49: =I49/12 -> 2124 | Y49: =I49*W49/L49 -> 2164.7342 | Z49: =IF(F49<$Z$2,30,$Z$2-I49) -> 30 | AA49: =I49/12 -> 2124 | AB49: =I49*Z49/L49 -> 2094.9041
A50: 0 | B50: 45748 | C50: Zulfiqar Jariwala | D50: INV-25-26-000052 | E50: subscription based service | F50: 45772 | G50: 46136 | H50: Annual Upfront | I50: 25488 | J50: 2124 | K50: =I50/12 -> 2124 | L50: =G50-F50+1 -> 365 | M50: =$H$1-F50+1 -> 6 | N50: =I50/L50*M50 -> 418.98082 | O50: =IF(F50<$O$1,31,$O$1-F50) -> 31 | P50: =O50*I50/L50 -> 2164.7342 | Q50: =I50/12 -> 2124 | R50: =IF(F50<$R$2,30,$R$2-F50) -> 30 | S50: =R50*I50/L50 -> 2094.9041 | T50: =I50/12 -> 2124 | U50: =IF(F51<$U$2,31,$U$2-F51) -> 31 | V50: =I50*U50/L50 -> 2164.7342 | W50: =IF(F50<$W$2,31,$W$2-F50) -> 31 | X50: =I50/12 -> 2124 | Y50: =I50*W50/L50 -> 2164.7342 | Z50: =IF(F50<$Z$2,30,$Z$2-I50) -> 30 | AA50: =I50/12 -> 2124 | AB50: =I50*Z50/L50 -> 2094.9041
A51: 0 | B51: 45748 | C51: Manjari Shah | D51: INV-25-26-000053 | E51: subscription based service | F51: 45772 | G51: 46136 | H51: Annual Upfront | I51: 25488 | J51: 2124 | K51: =I51/12 -> 2124 | L51: =G51-F51+1 -> 365 | M51: =$H$1-F51+1 -> 6 | N51: =I51/L51*M51 -> 418.98082 | O51: =IF(F51<$O$1,31,$O$1-F51) -> 31 | P51: =O51*I51/L51 -> 2164.7342 | Q51: =I51/12 -> 2124 | R51: =IF(F51<$R$2,30,$R$2-F51) -> 30 | S51: =R51*I51/L51 -> 2094.9041 | T51: =I51/12 -> 2124 | U51: =IF(F52<$U$2,31,$U$2-F52) -> 31 | V51: =I51*U51/L51 -> 2164.7342 | W51: =IF(F51<$W$2,31,$W$2-F51) -> 31 | X51: =I51/12 -> 2124 | Y51: =I51*W51/L51 -> 2164.7342 | Z51: =IF(F51<$Z$2,30,$Z$2-I51) -> 30 | AA51: =I51/12 -> 2124 | AB51: =I51*Z51/L51 -> 2094.9041
A52: 0 | B52: 45748 | C52: Sagar Sheth | D52: INV-25-26-000054 | E52: subscription based service | F52: 45772 | G52: 46136 | H52: Annual Upfront | I52: 25488 | J52: 2124 | K52: =I52/12 -> 2124 | L52: =G52-F52+1 -> 365 | M52: =$H$1-F52+1 -> 6 | N52: =I52/L52*M52 -> 418.98082 | O52: =IF(F52<$O$1,31,$O$1-F52) -> 31 | P52: =O52*I52/L52 -> 2164.7342 | Q52: =I52/12 -> 2124 | R52: =IF(F52<$R$2,30,$R$2-F52) -> 30 | S52: =R52*I52/L52 -> 2094.9041 | T52: =I52/12 -> 2124 | U52: =IF(F53<$U$2,31,$U$2-F53) -> 31 | V52: =I52*U52/L52 -> 2164.7342 | W52: =IF(F52<$W$2,31,$W$2-F52) -> 31 | X52: =I52/12 -> 2124 | Y52: =I52*W52/L52 -> 2164.7342 | Z52: =IF(F52<$Z$2,30,$Z$2-I52) -> 30 | AA52: =I52/12 -> 2124 | AB52: =I52*Z52/L52 -> 2094.9041
A53: 0 | B53: 45748 | C53: Mahek Bookwala | D53: INV-25-26-000055 | E53: subscription based service | F53: 45772 | G53: 46136 | H53: Annual Upfront | I53: 25488 | J53: 2124 | K53: =I53/12 -> 2124 | L53: =G53-F53+1 -> 365 | M53: =$H$1-F53+1 -> 6 | N53: =I53/L53*M53 -> 418.98082 | O53: =IF(F53<$O$1,31,$O$1-F53) -> 31 | P53: =O53*I53/L53 -> 2164.7342 | Q53: =I53/12 -> 2124 | R53: =IF(F53<$R$2,30,$R$2-F53) -> 30 | S53: =R53*I53/L53 -> 2094.9041 | T53: =I53/12 -> 2124 | U53: =IF(F54<$U$2,31,$U$2-F54) -> 31 | V53: =I53*U53/L53 -> 2164.7342 | W53: =IF(F53<$W$2,31,$W$2-F53) -> 31 | X53: =I53/12 -> 2124 | Y53: =I53*W53/L53 -> 2164.7342 | Z53: =IF(F53<$Z$2,30,$Z$2-I53) -> 30 | AA53: =I53/12 -> 2124 | AB53: =I53*Z53/L53 -> 2094.9041
A54: 0 | B54: Apr 25 & sept 25 | C54: Pradeep Sancheti | D54: INV-25-26-000056, CN 25 | E54: subscription based service | F54: 45772 | G54: 46136 | H54: Annual Upfront | I54: =25488-25488 -> 0 | J54: 0 | K54: =I54/12 -> 0 | L54: =G54-F54+1 -> 365 | M54: =$H$1-F54+1 -> 6 | N54: =I54/L54*M54 -> 0 | O54: =IF(F54<$O$1,31,$O$1-F54) -> 31 | P54: =O54*I54/L54 -> 0 | Q54: =I54/12 -> 0 | R54: =IF(F54<$R$2,30,$R$2-F54) -> 30 | S54: =R54*I54/L54 -> 0 | T54: =I54/12 -> 0 | U54: =IF(F55<$U$2,31,$U$2-F55) -> 31 | V54: =I54*U54/L54 -> 0 | W54: =IF(F54<$W$2,31,$W$2-F54) -> 31 | X54: =I54/12 -> 0 | Y54: =I54*W54/L54 -> 0 | Z54: =IF(F54<$Z$2,30,$Z$2-I54) -> 30 | AA54: =I54/12 -> 0 | AB54: =Z54*I54/L54 -> 0
A55: 0 | B55: 45748 | C55: AHUJA VALECHA & ASSOCIATES LLP | D55: INV-25-26-000057 | E55: subscription based service | F55: 45775 | G55: 45865 | H55: 3 months subscription, upfront | I55: 88500 | J55: 29500 | K55: =I55/3 -> 29500 | L55: =G55-F55+1 -> 91 | M55: =$H$1-F55+1 -> 3 | N55: =I55/L55*M55 -> 2917.5824 | O55: =IF(F55<$O$1,31,$O$1-F55) -> 31 | P55: =O55*I55/L55 -> 30148.352 | Q55: =I55/3 -> 29500 | R55: =IF(F55<$R$2,30,$R$2-F55) -> 30 | S55: =R55*I55/L55 -> 29175.824 | U55: =G55-$R$2 -> 27 | V55: =U55*I55/L55 -> 26258.242 | W55: 0 | X55: 0 | Y55: 0
A56: 0 | B56: 45748 | C56: ICL CORPORATE ADVISORY PRIVATE LIMITED | D56: INV-25-26-000058 | E56: subscription based service | F56: 45772 | G56: 45832 | H56: 2 months- Upfront | I56: 47200 | J56: =I56/2 -> 23600 | K56: =I56/2 -> 23600 | L56: =G56-F56+1 -> 61 | M56: =$H$1-F56+1 -> 6 | N56: =I56/L56*M56 -> 4642.623 | O56: =IF(F56<$O$1,31,$O$1-F56) -> 31 | P56: =O56*I56/L56 -> 23986.885 | R56: 24 | S56: =R56*I56/L56 -> 18570.492
A57: Closed- May 25 | B57: 45748 | C57: Argus Partners | D57: INV-25-26-000059 | E57: subscription based service | F57: 45773 | G57: 45803 | H57: 1 month-Upfront | I57: 11800 | J57: 11800 | L57: =G57-F57+1 -> 31 | M57: =$H$1-F57+1 -> 5 | N57: =I57/L57*M57 -> 1903.2258 | O57: =L57-M57 -> 26 | P57: =O57*I57/L57 -> 9896.7742 | R57: =IF(F57<$R$2,30,$R$2-F57) -> 30 | U57: =IF(F58<$U$2,31,$U$2-F58) -> 31 | W57: 0 | X57: 0 | Y57: 0
B58: Apr to Oct 25 | C58: Pratik Patnaik | D58: INV-25-26-000060,144, 230, 333, 382, 468,558 | E58: subscription based service | F58: 45773 | G58: 46137 | H58: Annual-Monthly | I58: =14160*12 -> 169920 | J58: 14160 | K58: =J58 -> 14160 | L58: =G58-F58+1 -> 365 | M58: =$H$1-F58+1 -> 5 | N58: =I58/L58*M58 -> 2327.6712 | O58: =L58-M58 -> 360 | P58: =O58*I58/L58 -> 167592.33 | Q58: =I58/12 -> 14160 | R58: =IF(F58<$R$2,30,$R$2-F58) -> 30 | S58: =R58*I58/L58 -> 13966.027 | T58: =I58/12 -> 14160 | U58: =IF(F59<$U$2,31,$U$2-F59) -> 31 | V58: =I58*U58/L58 -> 14431.562 | W58: =IF(F58<$W$2,31,$W$2-F58) -> 31 | X58: =I58/12 -> 14160 | Y58: =I58*W58/L58 -> 14431.562 | Z58: =IF(F58<$Z$2,30,$Z$2-I58) -> 30 | AA58: =I58/12 -> 14160 | AB58: =I58*Z58/L58 -> 13966.027
A59: 0 | B59: Jan, Apr & May 25 | C59: Saswat Mohanty | D59: INV-25-26-000061, 145 | E59: subscription based service | F59: 45687 | G59: 46052 | H59: Three Installments of 50k | I59: 159000 | J59: 13250 | K59: =53000/4 -> 13250 | L59: =G59-F59+1 -> 366 | M59: =IF(F59<H44,30,H44-F59) -> 30 | N59: =I59/L59*M59 -> 13032.787 | O59: =IF(F59<$O$1,31,$O$1-F59) -> 31 | P59: =O59*I59/L59 -> 13467.213 | Q59: =I59/12 -> 13250 | R59: =IF(F59<$R$2,30,$R$2-F59) -> 30 | S59: =R59*I59/L59 -> 13032.787 | T59: =I59/12 -> 13250 | U59: =IF(F60<$U$2,31,$U$2-F60) -> 31 | V59: =I59*U59/L59 -> 13467.213 | W59: =IF(F59<$W$2,31,$W$2-F59) -> 31 | X59: =I59/12 -> 13250 | Y59: =I59*W59/L59 -> 13467.213 | Z59: =IF(F59<$Z$2,30,$Z$2-I59) -> 30 | AA59: =I59/12 -> 13250 | AB59: =Z59*I59/L59 -> 13032.787
A60: 0 | B60: 45748 | C60: Chambers of Aman Vachher | D60: INV-25-26-000062 | E60: subscription based service | F60: 45744 | G60: 46109 | H60: Annual Upfront | I60: 203904 | J60: 16992 | K60: =I60/12 -> 16992 | L60: =G60-F60+1 -> 366 | M60: =IF(F60<H45,30,H45-F60) -> 30 | N60: =I60/L60*M60 -> 16713.443 | O60: =IF(F60<$O$1,31,$O$1-F60) -> 31 | P60: =O60*I60/L60 -> 17270.557 | Q60: =I60/12 -> 16992 | R60: =IF(F60<$R$2,30,$R$2-F60) -> 30 | S60: =R60*I60/L60 -> 16713.443 | T60: =I60/12 -> 16992 | U60: =IF(F61<$U$2,31,$U$2-F61) -> 31 | V60: =I60*U60/L60 -> 17270.557 | W60: =IF(F60<$W$2,31,$W$2-F60) -> 31 | X60: =I60/12 -> 16992 | Y60: =I60*W60/L60 -> 17270.557 | Z60: =IF(F60<$Z$2,30,$Z$2-I60) -> 30 | AA60: =I60/12 -> 16992 | AB60: =I60*Z60/L60 -> 16713.443
A61: 0 | B61: 45748 | C61: SK Singhi and Partners | D61: INV-25-26-000063 | E61: subscription based service | F61: 45744 | G61: 46109 | H61: Annual Upfront | I61: 318600 | J61: 26550 | K61: =I61/12 -> 26550 | L61: =G61-F61+1 -> 366 | M61: =IF(F61<H46,30,H46-F61) -> 30 | N61: =I61/L61*M61 -> 26114.754 | O61: =IF(F61<$O$1,31,$O$1-F61) -> 31 | P61: =O61*I61/L61 -> 26985.246 | Q61: =I61/12 -> 26550 | R61: =IF(F61<$R$2,30,$R$2-F61) -> 30 | S61: =R61*I61/L61 -> 26114.754 | T61: =I61/12 -> 26550 | U61: =IF(F62<$U$2,31,$U$2-F62) -> 31 | V61: =I61*U61/L61 -> 26985.246 | W61: =IF(F61<$W$2,31,$W$2-F61) -> 31 | X61: =I61/12 -> 26550 | Y61: =I61*W61/L61 -> 26985.246 | Z61: =IF(F61<$Z$2,30,$Z$2-I61) -> 30 | AA61: =I61/12 -> 26550 | AB61: =I61*Z61/L61 -> 26114.754
A62: Closed- May 25 | B62: 45748 | C62: Centre for Law and Policy Research Trust | D62: INV-25-26-000064 | E62: subscription based service | F62: 45776 | G62: 45805 | H62: 1 month-Upfront | I62: 4720 | J62: 4720 | L62: =G62-F62+1 -> 30 | M62: =$H$1-F62+1 -> 2 | N62: =I62/L62*M62 -> 314.66667 | O62: =L62-M62 -> 28 | P62: =O62*I62/L62 -> 4405.3333 | R62: =IF(F62<$R$2,30,$R$2-F62) -> 30 | U62: =IF(F63<$U$2,31,$U$2-F63) -> 31 | W62: 0 | X62: 0 | Y62: 0
A63: 0 | B63: Apr to Oct 25 | C63: SKR & associates | D63: INV-25-26-000065,114,0185, 260, 344, 425, 510 | E63: subscription based service | F63: 45757 | G63: 46121 | H63: Annual-Monthly | I63: =10300*12 -> 123600 | J63: 10300 | K63: 10300 | L63: =G63-F63+1 -> 365 | M63: =$H$1-F63+1 -> 21 | N63: =I63/L63*M63 -> 7111.2329 | O63: =IF(F63<$O$1,31,$O$1-F63) -> 31 | P63: =O63*I63/L63 -> 10497.534 | Q63: =I63/12 -> 10300 | R63: =IF(F63<$R$2,30,$R$2-F63) -> 30 | S63: =R63*I63/L63 -> 10158.904 | T63: =I63/12 -> 10300 | U63: =IF(F64<$U$2,31,$U$2-F64) -> 31 | V63: =I63*U63/L63 -> 10497.534 | W63: =IF(F63<$W$2,31,$W$2-F63) -> 31 | X63: =I63/12 -> 10300 | Y63: =I63*W63/L63 -> 10497.534 | Z63: =IF(F63<$Z$2,30,$Z$2-I63) -> 30 | AA63: =I63/12 -> 10300 | AB63: =I63*Z63/L63 -> 10158.904
A64: 0 | B64: Apr & Oct 25 | C64: Srivastava & Company | D64: INV-25-26-000066,564 | E64: subscription based service | F64: 45776 | G64: 46140 | H64: Annual- Half Yearly Payment | I64: 80000 | J64: 6666.6667 | K64: =I64/12 -> 6666.6667 | L64: =G64-F64+1 -> 365 | M64: =$H$1-F64+1 -> 2 | N64: =I64/L64*M64 -> 438.35616 | O64: =IF(F64<$O$1,31,$O$1-F64) -> 31 | P64: =O64*I64/L64 -> 6794.5205 | Q64: =I64/12 -> 6666.6667 | R64: =IF(F64<$R$2,30,$R$2-F64) -> 30 | S64: =R64*I64/L64 -> 6575.3425 | T64: =I64/12 -> 6666.6667 | U64: =IF(F65<$U$2,31,$U$2-F65) -> 31 | V64: =I64*U64/L64 -> 6794.5205 | W64: =IF(F64<$W$2,31,$W$2-F64) -> 31 | X64: =I64/12 -> 6666.6667 | Y64: =I64*W64/L64 -> 6794.5205 | Z64: =IF(F64<$Z$2,30,$Z$2-I64) -> 30 | AA64: =I64/12 -> 6666.6667 | AB64: =I64*Z64/L64 -> 6575.3425
A65: 0 | B65: 45748 | C65: Piyush Raheja | D65: INV-25-26-000067 | E65: subscription based service | F65: 45776 | G65: 46140 | H65: Annual Upfront | I65: 26000 | J65: 2166.6667 | K65: =I65/12 -> 2166.6667 | L65: =G65-F65+1 -> 365 | M65: =$H$1-F65+1 -> 2 | N65: =I65/L65*M65 -> 142.46575 | O65: =IF(F65<$O$1,31,$O$1-F65) -> 31 | P65: =O65*I65/L65 -> 2208.2192 | Q65: =I65/12 -> 2166.6667 | R65: =IF(F65<$R$2,30,$R$2-F65) -> 30 | S65: =R65*I65/L65 -> 2136.9863 | T65: =I65/12 -> 2166.6667 | U65: =IF(F66<$U$2,31,$U$2-F66) -> 31 | V65: =I65*U65/L65 -> 2208.2192 | W65: =IF(F65<$W$2,31,$W$2-F65) -> 31 | X65: =I65/12 -> 2166.6667 | Y65: =I65*W65/L65 -> 2208.2192 | Z65: =IF(F65<$Z$2,30,$Z$2-I65) -> 30 | AA65: =I65/12 -> 2166.6667 | AB65: =I65*Z65/L65 -> 2136.9863
A66: 0 | B66: 45748 | C66: ⁠Feroze Patel | D66: INV-25-26-000068 | E66: subscription based service | F66: 45776 | G66: 46140 | H66: Annual Upfront | I66: 26000 | J66: 2166.6667 | K66: =I66/12 -> 2166.6667 | L66: =G66-F66+1 -> 365 | M66: =$H$1-F66+1 -> 2 | N66: =I66/L66*M66 -> 142.46575 | O66: =IF(F66<$O$1,31,$O$1-F66) -> 31 | P66: =O66*I66/L66 -> 2208.2192 | Q66: =I66/12 -> 2166.6667 | R66: =IF(F66<$R$2,30,$R$2-F66) -> 30 | S66: =R66*I66/L66 -> 2136.9863 | T66: =I66/12 -> 2166.6667 | U66: =IF(F67<$U$2,31,$U$2-F67) -> 31 | V66: =I66*U66/L66 -> 2208.2192 | W66: =IF(F66<$W$2,31,$W$2-F66) -> 31 | X66: =I66/12 -> 2166.6667 | Y66: =I66*W66/L66 -> 2208.2192 | Z66: =IF(F66<$Z$2,30,$Z$2-I66) -> 30 | AA66: =I66/12 -> 2166.6667 | AB66: =I66*Z66/L66 -> 2136.9863
A67: 0 | B67: 45748 | C67: Kazan Shroff | D67: INV-25-26-000069 | E67: subscription based service | F67: 45776 | G67: 46140 | H67: Annual Upfront | I67: 26000 | J67: 2166.6667 | K67: =I67/12 -> 2166.6667 | L67: =G67-F67+1 -> 365 | M67: =$H$1-F67+1 -> 2 | N67: =I67/L67*M67 -> 142.46575 | O67: =IF(F67<$O$1,31,$O$1-F67) -> 31 | P67: =O67*I67/L67 -> 2208.2192 | Q67: =I67/12 -> 2166.6667 | R67: =IF(F67<$R$2,30,$R$2-F67) -> 30 | S67: =R67*I67/L67 -> 2136.9863 | T67: =I67/12 -> 2166.6667 | U67: =IF(F68<$U$2,31,$U$2-F68) -> 31 | V67: =I67*U67/L67 -> 2208.2192 | W67: =IF(F67<$W$2,31,$W$2-F67) -> 31 | X67: =I67/12 -> 2166.6667 | Y67: =I67*W67/L67 -> 2208.2192 | Z67: =IF(F67<$Z$2,30,$Z$2-I67) -> 30 | AA67: =I67/12 -> 2166.6667 | AB67: =I67*Z67/L67 -> 2136.9863
A68: 0 | B68: 45748 | C68: Kajol Punjabi | D68: INV-25-26-000070 | E68: subscription based service | F68: 45776 | G68: 46140 | H68: Annual Upfront | I68: 26000 | J68: 2166.6667 | K68: =I68/12 -> 2166.6667 | L68: =G68-F68+1 -> 365 | M68: =$H$1-F68+1 -> 2 | N68: =I68/L68*M68 -> 142.46575 | O68: =IF(F68<$O$1,31,$O$1-F68) -> 31 | P68: =O68*I68/L68 -> 2208.2192 | Q68: =I68/12 -> 2166.6667 | R68: =IF(F68<$R$2,30,$R$2-F68) -> 30 | S68: =R68*I68/L68 -> 2136.9863 | T68: =I68/12 -> 2166.6667 | U68: =IF(F69<$U$2,31,$U$2-F69) -> 31 | V68: =I68*U68/L68 -> 2208.2192 | W68: =IF(F68<$W$2,31,$W$2-F68) -> 31 | X68: =I68/12 -> 2166.6667 | Y68: =I68*W68/L68 -> 2208.2192 | Z68: =IF(F68<$Z$2,30,$Z$2-I68) -> 30 | AA68: =I68/12 -> 2166.6667 | AB68: =I68*Z68/L68 -> 2136.9863
A69: 0 | B69: 45748 | C69: Neeta Jain | D69: INV-25-26-000071 | E69: subscription based service | F69: 45776 | G69: 46140 | H69: Annual Upfront | I69: 26000 | J69: 2166.6667 | K69: =I69/12 -> 2166.6667 | L69: =G69-F69+1 -> 365 | M69: =$H$1-F69+1 -> 2 | N69: =I69/L69*M69 -> 142.46575 | O69: =IF(F69<$O$1,31,$O$1-F69) -> 31 | P69: =O69*I69/L69 -> 2208.2192 | Q69: =I69/12 -> 2166.6667 | R69: =IF(F69<$R$2,30,$R$2-F69) -> 30 | S69: =R69*I69/L69 -> 2136.9863 | T69: =I69/12 -> 2166.6667 | U69: =IF(F70<$U$2,31,$U$2-F70) -> 31 | V69: =I69*U69/L69 -> 2208.2192 | W69: =IF(F69<$W$2,31,$W$2-F69) -> 31 | X69: =I69/12 -> 2166.6667 | Y69: =I69*W69/L69 -> 2208.2192 | Z69: =IF(F69<$Z$2,30,$Z$2-I69) -> 30 | AA69: =I69/12 -> 2166.6667 | AB69: =I69*Z69/L69 -> 2136.9863
A70: 0 | B70: 45748 | C70: Amrut Joshi | D70: INV-25-26-000072 | E70: subscription based service | F70: 45776 | G70: 46140 | H70: Annual Upfront | I70: 26000 | J70: 2166.6667 | K70: =I70/12 -> 2166.6667 | L70: =G70-F70+1 -> 365 | M70: =$H$1-F70+1 -> 2 | N70: =I70/L70*M70 -> 142.46575 | O70: =IF(F70<$O$1,31,$O$1-F70) -> 31 | P70: =O70*I70/L70 -> 2208.2192 | Q70: =I70/12 -> 2166.6667 | R70: =IF(F70<$R$2,30,$R$2-F70) -> 30 | S70: =R70*I70/L70 -> 2136.9863 | T70: =I70/12 -> 2166.6667 | U70: =IF(F71<$U$2,31,$U$2-F71) -> 31 | V70: =I70*U70/L70 -> 2208.2192 | W70: =IF(F70<$W$2,31,$W$2-F70) -> 31 | X70: =I70/12 -> 2166.6667 | Y70: =I70*W70/L70 -> 2208.2192 | Z70: =IF(F70<$Z$2,30,$Z$2-I70) -> 30 | AA70: =I70/12 -> 2166.6667 | AB70: =I70*Z70/L70 -> 2136.9863
A71: 0 | B71: Jan & Apr 25 | C71: Gaurav Joshi | D71: INV-25-26-000073 | E71: subscription based service | F71: 45776 | G71: 46140 | H71: Annual subscription, Quarterly upfront | I71: 216000 | J71: 18000 | K71: =I71/12 -> 18000 | L71: =G71-F71+1 -> 365 | M71: 30 | N71: =I71/L71*M71 -> 17753.425 | O71: =IF(F71<$O$1,31,$O$1-F71) -> 31 | P71: =O71*I71/L71 -> 18345.205 | Q71: =I71/12 -> 18000 | R71: =IF(F71<$R$2,30,$R$2-F71) -> 30 | S71: =R71*I71/L71 -> 17753.425 | T71: =I71/12 -> 18000 | U71: =IF(F72<$U$2,31,$U$2-F72) -> 31 | V71: =I71*U71/L71 -> 18345.205 | W71: =IF(F71<$W$2,31,$W$2-F71) -> 31 | X71: =I71/12 -> 18000 | Y71: =I71*W71/L71 -> 18345.205 | Z71: =IF(F71<$Z$2,30,$Z$2-I71) -> 30 | AA71: =I71/12 -> 18000 | AB71: =I71*Z71/L71 -> 17753.425
A72: 0 | B72: 45748 | C72: Kamaljeet Singh | D72: INV-25-26-000074 | E72: subscription based service | F72: 45776 | G72: 45958 | H72: 6 month-Upfront | I72: 42480 | J72: 7080 | K72: =I72/6 -> 7080 | L72: =G72-F72+1 -> 183 | M72: =$H$1-F72+1 -> 2 | N72: =I72/L72*M72 -> 464.2623 | O72: =IF(F72<$O$1,31,$O$1-F72) -> 31 | P72: =O72*I72/L72 -> 7196.0656 | Q72: =I72/6 -> 7080 | R72: =IF(F72<$R$2,30,$R$2-F72) -> 30 | S72: =R72*I72/L72 -> 6963.9344 | T72: =I72/6 -> 7080 | U72: =IF(F73<$U$2,31,$U$2-F73) -> 31 | V72: =I72*U72/L72 -> 7196.0656 | W72: =IF(F72<$W$2,31,$W$2-F72) -> 31 | X72: =I72/6 -> 7080 | Y72: =I72*W72/L72 -> 7196.0656 | Z72: =IF(F72<$Z$2,30,$Z$2-I72) -> 30 | AA72: =I72/6 -> 7080 | AB72: =Z72*I72/L72 -> 6963.9344
A73: Closed- May 25 | B73: 45748 | C73: Saraf and Partners | D73: INV-25-26-000075 | E73: subscription based service | F73: 45778 | G73: 45808 | H73: 1 month-Upfront | I73: 50150 | K73: =I73 -> 50150 | L73: =G73-F73+1 -> 31 | M73: =$H$1-F73+1 -> 0 | N73: =I73/L73*M73 -> 0 | O73: =$O$1-F73+1 -> 31 | P73: =O73*I73/L73 -> 50150 | R73: =IF(F73<$R$2,30,$R$2-F73) -> 30 | U73: =IF(F74<$U$2,31,$U$2-F74) -> 31 | W73: 0 | X73: 0 | Y73: 0
A74: Closed- May 25 | B74: 45748 | C74: Pioneer Legal | D74: INV-25-26-000076 | E74: subscription based service | F74: 45776 | G74: 45808 | H74: 1 month-Upfront | I74: 17700 | J74: 17700 | L74: =G74-F74+1 -> 33 | M74: =$H$1-F74+1 -> 2 | N74: =I74/L74*M74 -> 1072.7273 | O74: =L74-M74 -> 31 | P74: =O74*I74/L74 -> 16627.273 | R74: =IF(F74<$R$2,30,$R$2-F74) -> 30 | U74: =IF(F75<$U$2,31,$U$2-F75) -> 31 | W74: 0 | X74: 0 | Y74: 0
A75: 0 | B75: 45748 | C75: Dua Associates | D75: INV-25-26-000077 | E75: subscription based service | F75: 45778 | G75: 45838 | H75: 2 months- Upfront | I75: 18880 | K75: =I75/2 -> 9440 | L75: =G75-F75+1 -> 61 | M75: =$H$1-F75+1 -> 0 | N75: =I75/L75*M75 -> 0 | O75: =$O$1-F75+1 -> 31 | P75: =O75*I75/L75 -> 9594.7541 | Q75: =I75/2 -> 9440 | R75: 30 | S75: =R75*I75/L75 -> 9285.2459 | U75: =IF(F76<$U$2,31,$U$2-F76) -> 31 | W75: 0 | X75: 0 | Y75: 0
A76: 0 | B76: Nov 24 to Oct 25 | C76: Manish kelker | D76: 40, INV-000088, 0112, INV-25-26-000078, 111,0180, 256, 343, 420, 505 | E76: subscription based service | F76: 45605 | G76: 45970 | H76: Annual-Monthly | I76: 47988 | J76: 3999 | K76: 3999 | L76: =G76-F76+1 -> 366 | M76: =IF(F76<H1,30,H1-G76) -> 30 | N76: =I76/L76*M76 -> 3933.4426 | O76: =IF(F76<$O$1,31,$O$1-F76) -> 31 | P76: =O76*I76/L76 -> 4064.5574 | Q76: =I76/12 -> 3999 | R76: =IF(F76<$R$2,30,$R$2-F76) -> 30 | S76: =R76*I76/L76 -> 3933.4426 | T76: =I76/12 -> 3999 | U76: =IF(F77<$U$2,31,$U$2-F77) -> 31 | V76: =I76*U76/L76 -> 4064.5574 | W76: =IF(F76<$W$2,31,$W$2-F76) -> 31 | X76: =I76/12 -> 3999 | Y76: =I76*W76/L76 -> 4064.5574 | Z76: =IF(F76<$Z$2,30,$Z$2-I76) -> 30 | AA76: =I76/12 -> 3999 | AB76: =I76*Z76/L76 -> 3933.4426
A77: 0 | B77: Dec 24 to Oct 25 | C77: Diwan Law Associates | D77: INV-000091, 0114, INV-25-26-000079, 115,191, 263,346, 513 | E77: subscription based service | F77: 45637 | G77: 46002 | H77: Annual-Monthly | I77: =5000*12 -> 60000 | J77: 5000 | K77: 5000 | L77: =G77-F77+1 -> 366 | M77: =IF(F77>1-4-2025,30,H1-F77) -> 30 | N77: =I77/L77*M77 -> 4918.0328 | O77: =IF(F77<$O$1,31,$O$1-F77) -> 31 | P77: =O77*I77/L77 -> 5081.9672 | Q77: =I77/12 -> 5000 | R77: =IF(F77<$R$2,30,$R$2-F77) -> 30 | S77: =R77*I77/L77 -> 4918.0328 | T77: =I77/12 -> 5000 | U77: =IF(F78<$U$2,31,$U$2-F78) -> 31 | V77: =I77*U77/L77 -> 5081.9672 | W77: =IF(F77<$W$2,31,$W$2-F77) -> 31 | X77: =I77/12 -> 5000 | Y77: =I77*W77/L77 -> 5081.9672 | Z77: =IF(F77<$Z$2,30,$Z$2-I77) -> 30 | AA77: =I77/12 -> 5000 | AB77: =I77*Z77/L77 -> 4918.0328
A78: 0 | B78: Sept to Sept 25 | C78: SRCO Legal / Salvador Raghav & Co. | D78: INV-000145,00011, INV-25-26-000080,0106, 0223, 312, 390, 474 | E78: subscription based service | F78: 45594 | G78: 45959 | H78: Annual-Monthly | I78: =8000*12 -> 96000 | J78: 8000 | K78: 8000 | L78: =G78-F78+1 -> 366 | M78: =IF(F78>1-4-2025,30,H3-F78) -> 30 | N78: =I78/L78*M78 -> 7868.8525 | O78: =IF(F78<$O$1,31,$O$1-F78) -> 31 | P78: =O78*I78/L78 -> 8131.1475 | Q78: =I78/12 -> 8000 | R78: =IF(F78<$R$2,30,$R$2-F78) -> 30 | S78: =R78*I78/L78 -> 7868.8525 | T78: =I78/12 -> 8000 | U78: =IF(F79<$U$2,31,$U$2-F79) -> 31 | V78: =I78*U78/L78 -> 8131.1475 | W78: =IF(F78<$W$2,31,$W$2-F78) -> 31 | X78: =I78/12 -> 8000 | Y78: =I78*W78/L78 -> 8131.1475 | Z78: =IF(F78<$Z$2,30,$Z$2-I78) -> 30 | AA78: =I78/12 -> 8000 | AB78: =I78*Z78/L78 -> 7868.8525
A79: 0 | B79: 45778 | C79: Sarthak Advocates & Solicitors | D79: INV-25-26-000096 | E79: One time work | F79: 45779 | G79: 45809 | H79: 1 month-Upfront | I79: 11800 | K79: 11800 | L79: =G79-F79+1 -> 31 | O79: =$O$1-F79+1 -> 30 | P79: =O79*I79/L79 -> 11419.355 | R79: 1 | S79: =R79*I79/L79 -> 380.64516 | U79: =IF(F80<$U$2,31,$U$2-F80) -> 31 | W79: 0 | X79: 0 | Y79: 0
A80: 0 | B80: 45778 | C80: Gupta Law Associates | D80: INV-25-26-000097 | E80: One time work | F80: 45779 | G80: 45809 | H80: 1 month-Upfront | I80: 17700 | K80: 17700 | L80: =G80-F80+1 -> 31 | O80: =$O$1-F80+1 -> 30 | P80: =O80*I80/L80 -> 17129.032 | R80: 1 | S80: =R80*I80/L80 -> 570.96774 | U80: =IF(F81<$U$2,31,$U$2-F81) -> 31 | W80: 0 | X80: 0 | Y80: 0
A81: Closed- May 25 | B81: 45778 | C81: Saraf and Partners | D81: INV-25-26-000100 | E81: One time work | F81: 45778 | G81: 45808 | H81: 1 month-Upfront | I81: 11800 | K81: 11800 | L81: =G81-F81+1 -> 31 | O81: =$O$1-F81+1 -> 31 | P81: =O81*I81/L81 -> 11800 | R81: =IF(F81<$R$2,30,$R$2-F81) -> 30 | U81: =IF(F82<$U$2,31,$U$2-F82) -> 31 | W81: 0 | X81: 0 | Y81: 0
A82: 0 | B82: 45778 | C82: Kunal Kunango | D82: INV-25-26-000101 | E82: subscription based service | F82: 45780 | G82: 46144 | H82: Annual Upfront | I82: 47988 | K82: =I82/12 -> 3999 | L82: =G82-F82+1 -> 365 | O82: =$O$1-F82+1 -> 29 | P82: =O82*I82/L82 -> 3812.7452 | Q82: =I82/12 -> 3999 | R82: =IF(F82<$R$2,30,$R$2-F82) -> 30 | S82: =R82*I82/L82 -> 3944.2192 | T82: =I82/12 -> 3999 | U82: =IF(F83<$U$2,31,$U$2-F83) -> 31 | V82: =I82*U82/L82 -> 4075.6932 | W82: =IF(F82<$W$2,31,$W$2-F82) -> 31 | X82: =I82/12 -> 3999 | Y82: =I82*W82/L82 -> 4075.6932 | Z82: =IF(F82<$Z$2,30,$Z$2-I82) -> 30 | AA82: =I82/12 -> 3999 | AB82: =I82*Z82/L82 -> 3944.2192
A83: 0 | B83: 45778 | C83: Divyanshu Rai | D83: INV-25-26-000102 | E83: subscription based service | F83: 45782 | G83: 46146 | H83: Annual Upfront | I83: 76464 | K83: =I83/12 -> 6372 | L83: =G83-F83+1 -> 365 | O83: =$O$1-F83+1 -> 27 | P83: =O83*I83/L83 -> 5656.2411 | Q83: =I83/12 -> 6372 | R83: =IF(F83<$R$2,30,$R$2-F83) -> 30 | S83: =R83*I83/L83 -> 6284.7123 | T83: =I83/12 -> 6372 | U83: =IF(F84<$U$2,31,$U$2-F84) -> 31 | V83: =I83*U83/L83 -> 6494.2027 | W83: =IF(F83<$W$2,31,$W$2-F83) -> 31 | X83: =I83/12 -> 6372 | Y83: =I83*W83/L83 -> 6494.2027 | Z83: =IF(F83<$Z$2,30,$Z$2-I83) -> 30 | AA83: =I83/12 -> 6372 | AB83: =I83*Z83/L83 -> 6284.7123
B84: May & Aug 25 | C84: Hamza mir | D84: INV-25-26-000103, 212, 265, 365 | E84: One time work | F84: 45727 | G84: 45910 | H84: 6 months subscription, Monthly | I84: =5900*6 -> 35400 | J84: =I84/6 -> 5900 | K84: 5900 | L84: =G84-F84+1 -> 184 | M84: 30 | N84: =M84*I84/L84 -> 5771.7391 | O84: 31 | P84: =O84*I84/L84 -> 5964.1304 | Q84: 5900 | R84: =IF(F84<$R$2,30,$R$2-F84) -> 30 | S84: =R84*I84/L84 -> 5771.7391 | T84: =I84/6 -> 5900 | U84: =IF(F85<$U$2,31,$U$2-F85) -> 31 | V84: =I84*U84/L84 -> 5964.1304 | W84: =IF(F84<$W$2,31,$W$2-F84) -> 31 | X84: =I84/6 -> 5900 | Y84: =I84*W84/L84 -> 5964.1304 | Z84: 10 | AB84: =I84*Z84/L84 -> 1923.913
A85: 0 | B85: May to Oct 25 | C85: Chambers of Ninad Laud | D85: INV-25-26-000105,0171, 246, 332,415, CN-00029, 496 | E85: subscription based service | F85: 45783 | G85: 46117 | H85: Annual-Monthly | I85: =11800*12-11800 -> 129800 | K85: =I85/12 -> 10816.667 | L85: =G85-F85+1 -> 335 | O85: =O1-F85+1 -> 26 | P85: =O85*I85/L85 -> 10074.03 | Q85: =I85/12 -> 10816.667 | R85: 30 | S85: 11638.356 | T85: =I85/12 -> 10816.667 | U85: 31 | V85: 12026.301 | W85: 31 | X85: =I85/12 -> 10816.667 | Y85: 12026.301 | Z85: =IF(F85<$Z$2,30,$Z$2-I85) -> 30 | AA85: =I85/12 -> 10816.667 | AB85: =Z85*I85/L85 -> 11623.881
A86: 0 | B86: 45778 | C86: Gera Developments Pvt. Ltd. | D86: INV-25-26-000106 | E86: subscription based service | F86: 45783 | G86: 45813 | H86: 1 month-Upfront | I86: 16520 | K86: 16520 | L86: =G86-F86+1 -> 31 | O86: =$O$1-F86+1 -> 26 | P86: =O86*I86/L86 -> 13855.484 | R86: 5 | S86: =R86*I86/L86 -> 2664.5161 | U86: =IF(F87<$U$2,31,$U$2-F87) -> 31 | W86: 0 | X86: 0 | Y86: 0
A87: 0 | B87: 45778 | C87: Gaurav Mehta | D87: INV-25-26-000108 | E87: subscription based service | F87: 45784 | G87: 45875 | H87: 3 months subscription, upfront | I87: 37760 | K87: =I87/3 -> 12586.667 | L87: =G87-F87+1 -> 92 | O87: =$O$1-F87+1 -> 25 | P87: =O87*I87/L87 -> 10260.87 | Q87: =I87/3 -> 12586.667 | R87: =IF(F87<$R$2,30,$R$2-F87) -> 30 | S87: =R87*I87/L87 -> 12313.043 | T87: =I87/3 -> 12586.667 | U87: =IF(F88<$U$2,31,$U$2-F88) -> 31 | V87: =I87*U87/L87 -> 12723.478 | W87: =G87-$W$1+1 -> 6 | X87: 0 | Y87: =I87*W87/L87 -> 2462.6087
A88: 0 | B88: 45778 | C88: MD&T Partners | D88: INV-25-26-000110 | E88: One time work | F88: 45785 | G88: 45815 | H88: 1 month-Upfront | I88: 4720 | K88: 4720 | L88: =G88-F88+1 -> 31 | O88: =$O$1-F88+1 -> 24 | P88: =O88*I88/L88 -> 3654.1935 | R88: 7 | S88: =R88*I88/L88 -> 1065.8065 | U88: =IF(F89<$U$2,31,$U$2-F89) -> 31 | W88: 0 | X88: 0 | Y88: 0
A89: 0 | B89: 45778 | C89: Kachwaha & Partners | D89: INV-25-26-000112 | E89: subscription based service | F89: 45789 | G89: 46153 | H89: Annual Upfront | I89: 254880 | K89: =I89/12 -> 21240 | L89: =G89-F89+1 -> 365 | O89: =$O$1-F89+1 -> 20 | P89: =O89*I89/L89 -> 13966.027 | Q89: =I89/12 -> 21240 | R89: =IF(F89<$R$2,30,$R$2-F89) -> 30 | S89: =R89*I89/L89 -> 20949.041 | T89: =I89/12 -> 21240 | U89: =IF(F90<$U$2,31,$U$2-F90) -> 31 | V89: =I89*U89/L89 -> 21647.342 | W89: =IF(F89<$W$2,31,$W$2-F89) -> 31 | X89: =I89/12 -> 21240 | Y89: =I89*W89/L89 -> 21647.342 | Z89: =IF(F89<$Z$2,30,$Z$2-I89) -> 30 | AA89: =I89/12 -> 21240 | AB89: =I89*Z89/L89 -> 20949.041
A90: Closed- May 25 | B90: 45778 | C90: Zoheb Hossain | D90: INV-25-26-000116 | E90: One time work | F90: 45773 | G90: 45802 | H90: 1 month-Upfront | I90: 15000 | J90: 15000 | L90: =G90-F90+1 -> 30 | M90: =H1-F90+1 -> 5 | N90: =I90/L90*M90 -> 2500 | O90: =L90-M90 -> 25 | P90: =O90*I90/L90 -> 12500 | R90: =IF(F90<$R$2,30,$R$2-F90) -> 30 | U90: =IF(F91<$U$2,31,$U$2-F91) -> 31 | W90: 0 | X90: 0 | Y90: 0
A91: 0 | B91: 45778 | C91: Vishal Kanade | D91: INV-25-26-000117 | E91: subscription based service | F91: 45793 | G91: 45823 | H91: 1 month-Upfront | I91: 15000 | K91: 15000.007 | L91: =G91-F91+1 -> 31 | O91: =$O$1-F91+1 -> 16 | P91: =O91*I91/L91 -> 7741.9355 | R91: 15 | S91: =R91*I91/L91 -> 7258.0645 | U91: =IF(F92<$U$2,31,$U$2-F92) -> 31 | W91: 0 | X91: 0 | Y91: 0
A92: 0 | B92: 45778 | C92: Vritti Law Partners | D92: INV-25-26-000118 | E92: One time work | F92: 45789 | G92: 45819 | H92: 1 month-Upfront | I92: 7080 | K92: 7080 | L92: =G92-F92+1 -> 31 | O92: =$O$1-F92+1 -> 20 | P92: =O92*I92/L92 -> 4567.7419 | R92: 11 | S92: =R92*I92/L92 -> 2512.2581 | U92: =IF(F93<$U$2,31,$U$2-F93) -> 31 | W92: 0 | X92: 0 | Y92: 0
A93: 0 | B93: 45778 | C93: SINHA & COMPANY | D93: INV-25-26-000119 | E93: subscription based service | F93: 45790 | G93: 46154 | H93: Annual Upfront | I93: 177000 | K93: =I93/12 -> 14750 | L93: =G93-F93+1 -> 365 | O93: =$O$1-F93+1 -> 19 | P93: =O93*I93/L93 -> 9213.6986 | Q93: =I93/12 -> 14750 | R93: =IF(F93<$R$2,30,$R$2-F93) -> 30 | S93: =R93*I93/L93 -> 14547.945 | T93: =I93/12 -> 14750 | U93: =IF(F94<$U$2,31,$U$2-F94) -> 31 | V93: =I93*U93/L93 -> 15032.877 | W93: =IF(F93<$W$2,31,$W$2-F93) -> 31 | X93: =I93/12 -> 14750 | Y93: =I93*W93/L93 -> 15032.877 | Z93: =IF(F93<$Z$2,30,$Z$2-I93) -> 30 | AA93: =I93/12 -> 14750 | AB93: =I93*Z93/L93 -> 14547.945
A94: 0 | B94: 45778 | C94: C&S Partners | D94: INV-25-26-000120 | E94: One time work | F94: 45791 | G94: 45821 | H94: 1 month-Upfront | I94: 14160 | K94: 14160 | L94: =G94-F94+1 -> 31 | O94: =$O$1-F94+1 -> 18 | P94: =O94*I94/L94 -> 8221.9355 | R94: 13 | S94: =R94*I94/L94 -> 5938.0645 | U94: =IF(F95<$U$2,31,$U$2-F95) -> 31 | W94: 0 | X94: 0 | Y94: 0
A95: 0 | B95: 45778 | C95: Asahi Legal LLP | D95: INV-25-26-000121 | E95: subscription based service | F95: 45781 | G95: 45873 | H95: 3 months subscription, upfront | I95: 22500 | K95: =I95/3 -> 7500 | L95: =G95-F95+1 -> 93 | O95: =$O$1-F95+1 -> 28 | P95: =O95*I95/L95 -> 6774.1935 | Q95: =I95/3 -> 7500 | R95: =IF(F95<$R$2,30,$R$2-F95) -> 30 | S95: =R95*I95/L95 -> 7258.0645 | T95: =I95/3 -> 7500 | U95: =IF(F96<$U$2,31,$U$2-F96) -> 31 | V95: =I95*U95/L95 -> 7500 | W95: =G95-$W$1+1 -> 4 | X95: 0 | Y95: =I95*W95/L95 -> 967.74194
A96: 0 | B96: 45778 | C96: Chambers of Moazzam Khan | D96: INV-25-26-000122 | E96: subscription based service | F96: 45790 | G96: 45973 | H96: 6 month-Upfront | I96: 95580 | K96: =I96/6 -> 15930 | L96: =G96-F96+1 -> 184 | O96: =$O$1-F96+1 -> 19 | P96: =O96*I96/L96 -> 9869.6739 | Q96: =I96/6 -> 15930 | R96: =IF(F96<$R$2,30,$R$2-F96) -> 30 | S96: =R96*I96/L96 -> 15583.696 | T96: =I96/6 -> 15930 | U96: =IF(F97<$U$2,31,$U$2-F97) -> 31 | V96: =I96*U96/L96 -> 16103.152 | W96: =IF(F96<$W$2,31,$W$2-F96) -> 31 | X96: =I96/6 -> 15930 | Y96: =I96*W96/L96 -> 16103.152 | Z96: =IF(F96<$Z$2,30,$Z$2-I96) -> 30 | AA96: =I96/6 -> 15930 | AB96: =Z96*I96/L96 -> 15583.696
A97: 0 | B97: 45778 | C97: Vis Legis Law Practice | D97: INV-25-26-000123 | E97: subscription based service | F97: 45782 | G97: 45813 | H97: 1 month-Upfront | I97: 23600 | K97: 23600 | L97: =G97-F97+1 -> 32 | O97: =$O$1-F97+1 -> 27 | P97: =O97*I97/L97 -> 19912.5 | R97: 5 | S97: =R97*I97/L97 -> 3687.5 | U97: =IF(F98<$U$2,31,$U$2-F98) -> 31 | W97: 0 | X97: 0 | Y97: 0
A98: 0 | B98: 45778 | C98: Phoenix Legal | D98: INV-25-26-000126 | E98: subscription based service | F98: 45793 | G98: 45854 | H98: 2 months- Upfront | I98: 118000 | K98: =I98/2 -> 59000 | L98: =G98-F98+1 -> 62 | O98: =$O$1-F98+1 -> 16 | P98: =O98*I98/L98 -> 30451.613 | Q98: =I98/2 -> 59000 | R98: =IF(F98<$R$2,30,$R$2-F98) -> 30 | S98: =R98*I98/L98 -> 57096.774 | U98: =G98-$R$2 -> 16 | V98: =U98*I98/L98 -> 30451.613 | W98: 0 | X98: 0 | Y98: 0
A99: 0 | B99: 45778 | C99: Nikhil Pai | D99: INV-25-26-000128 | E99: subscription based service | F99: 45793 | G99: 46157 | H99: Annual Upfront | I99: 64900 | K99: =I99/12 -> 5408.3333 | L99: =G99-F99+1 -> 365 | O99: =$O$1-F99+1 -> 16 | P99: =O99*I99/L99 -> 2844.9315 | Q99: =I99/12 -> 5408.3333 | R99: =IF(F99<$R$2,30,$R$2-F99) -> 30 | S99: =R99*I99/L99 -> 5334.2466 | T99: =I99/12 -> 5408.3333 | U99: =IF(F100<$U$2,31,$U$2-F100) -> 31 | V99: =I99*U99/L99 -> 5512.0548 | W99: =IF(F99<$W$2,31,$W$2-F99) -> 31 | X99: =I99/12 -> 5408.3333 | Y99: =I99*W99/L99 -> 5512.0548 | Z99: =IF(F99<$Z$2,30,$Z$2-I99) -> 30 | AA99: =I99/12 -> 5408.3333 | AB99: =I99*Z99/L99 -> 5334.2466
A100: 0 | B100: 45778 | C100: J INFRATECH LIMITED | D100: INV-25-26-000129 | E100: One time work | F100: 45793 | G100: 45824 | H100: 1 month-Upfront | I100: 4720 | K100: 4720 | L100: =G100-F100+1 -> 32 | O100: =$O$1-F100+1 -> 16 | P100: =O100*I100/L100 -> 2360 | R100: 16 | S100: =R100*I100/L100 -> 2360 | U100: =IF(F101<$U$2,31,$U$2-F101) -> 31 | W100: 0 | X100: 0 | Y100: 0
...

Sheet Invoices
F2: =SUBTOTAL(9,F23:F54) -> 1496307 | H2: =SUBTOTAL(9,H23:H54) -> 1564555
A3: Months | B3: Invoice Date | C3: Invoice Number | D3: Invoice Status | E3: Customer Name | F3: Taxable Value | G3: Total Tax | H3: Total | I3: Nature
A4: 45627 | B4: 45628 | C4: INV-000027 | D4: Closed | E4: B2C | F4: 1295 | G4: 0 | H4: 1295 | I4: B2C | K4: Sum of Taxable Value | L4: Nature
A5: 45627 | B5: 45628 | C5: INV-000028 | D5: Closed | E5: Office of ASG (N. Venkatraman) | F5: 195000 | G5: 0 | H5: 195000 | I5: B2B | K5: Months | L5: B2B | M5: B2C | N5: (empty) | O5: Total Result
A6: 45627 | B6: 45635 | C6: INV-000029 | D6: Closed | E6: B2C | F6: 9164 | G6: 0 | H6: 9164 | I6: B2C | K6: 45536 | L6: 3999 | M6: 23809 | O6: 27808
A7: 45627 | B7: 45635 | C7: INV-000030 | D7: Closed | E7: Kanungo & Co. | F7: 3999 | G7: 0 | H7: 3999 | I7: B2B | K7: 45566 | L7: 49997 | M7: 41135 | O7: 91132
A8: 45627 | B8: 45638 | C8: INV-000031 | D8: Closed | E8: B2C | F8: 3786 | G8: 0 | H8: 3786 | I8: B2C | K8: 45597 | L8: 158496 | M8: 20926 | O8: 179422
A9: 45627 | B9: 45638 | C9: INV-000032 | D9: Closed | E9: Diwan Law Associates | F9: 5000 | G9: 0 | H9: 5000 | I9: B2B | K9: 45627 | L9: 514892 | M9: 34284 | O9: 549176
A10: 45627 | B10: 45639 | C10: INV-000033 | D10: Closed | E10: Aditya Sikka / Tvashta Law | F10: 45000 | G10: 0 | H10: 45000 | I10: B2B | K10: 45658 | L10: 1464041 | M10: 32266 | O10: 1496307
A11: 45627 | B11: 45639 | C11: INV-000034 | D11: Closed | E11: B2C | F11: 1493 | G11: 0 | H11: 1493 | I11: B2C | K11: 45689 | L11: 1192593 | M11: 33183 | O11: 1225776
A12: 45627 | B12: 45640 | C12: INV-000035 | D12: Closed | E12: Amrita Panda / Chambers of Amrita Panda | F12: 10000 | G12: 0 | H12: 10000 | I12: B2B | K12: 45717 | L12: 4569923 | M12: 50543 | O12: 4620466
A13: 45627 | B13: 45644 | C13: INV-000036 | D13: Closed | E13: B2C | F13: 5481 | G13: 0 | H13: 5481 | I13: B2C | K13: 45748 | L13: 4040388 | M13: 42252 | O13: 4082640
A14: 45627 | B14: 45644 | C14: INV-000037 | D14: Closed | E14: Ish Jain / Regius Partners LLP | F14: 146994 | G14: 0 | H14: 146994 | I14: B2B | K14: 45778 | L14: 4666763 | M14: 24128 | O14: 4690891
A15: 45627 | B15: 45645 | C15: INV-000038 | D15: Closed | E15: The Guild | Advocates & Associate Counsel | F15: 60000 | G15: 0 | H15: 60000 | I15: B2B | K15: 45809 | L15: 3054847.7 | M15: 24554.28 | O15: 3079401.9
A16: 45627 | B16: 45648 | C16: INV-000039 | D16: Closed | E16: B2C | F16: 2293 | G16: 0 | H16: 2293 | I16: B2C | K16: 45839 | L16: 8195261 | M16: 19474 | O16: 8214735
A17: 45627 | B17: 45648 | C17: INV-000040 | D17: Closed | E17: Manish kelker | F17: 3999 | G17: 0 | H17: 3999 | I17: B2B | K17: 45870 | L17: 9351621 | M17: 18627 | O17: 9370248
A18: 45627 | B18: 45651 | C18: INV-000041 | D18: Closed | E18: B2C | F18: 2095 | G18: 0 | H18: 2095 | I18: B2C | K18: 45901 | L18: 4189179.5 | M18: 14394.92 | O18: 4203574.5
A19: 45627 | B19: 45651 | C19: INV-000042 | D19: Closed | E19: Abhimanyu Garg / Methodica Legal | F19: 36900 | G19: 0 | H19: 36900 | I19: B2B | K19: (empty)
A20: 45627 | B20: 45655 | C20: INV-000043 | D20: Closed | E20: B2C | F20: 3687 | G20: 0 | H20: 3687 | I20: B2C | K20: 45931 | L20: 5730227.7 | M20: 13549.16 | O20: 5743776.8
A21: 45627 | B21: 45655 | C21: INV-000044 | D21: Closed | E21: SRCO Legal / Salvador Raghav & Co. | F21: 8000 | G21: 0 | H21: 8000 | I21: B2B | K21: Total Result | L21: 47182229 | M21: 393125.36 | O21: 47575354
A22: 45627 | B22: 45657 | C22: INV-000045 | D22: Closed | E22: B2C | F22: 4990 | G22: 0 | H22: 4990 | I22: B2C
A23: 45658 | B23: 45658 | C23: INV-000046 | D23: Closed | E23: Agama Law Associates | F23: 80000 | G23: 0 | H23: 80000 | I23: B2B
A24: 45658 | B24: 45662 | C24: INV-000047 | D24: Closed | E24: B2C | F24: 6780 | G24: 0 | H24: 6780 | I24: B2C
A25: 45658 | B25: 45662 | C25: INV-000048 | D25: Closed | E25: Gourab Banerji | F25: 49998 | G25: 0 | H25: 49998 | I25: B2B
A26: 45658 | B26: 45665 | C26: INV-000049 | D26: Closed | E26: B2C | F26: 1691 | G26: 0 | H26: 1691 | I26: B2C
A27: 45658 | B27: 45665 | C27: INV-000050 | D27: Closed | E27: Parakram Legal | F27: 5000 | G27: 0 | H27: 5000 | I27: B2B
A28: 45658 | B28: 45666 | C28: INV-000051 | D28: Closed | E28: Kanungo & Co. | F28: 3999 | G28: 0 | H28: 3999 | I28: B2B
A29: 45658 | B29: 45668 | C29: INV-000052 | D29: Closed | E29: B2C | F29: 4487 | G29: 0 | H29: 4487 | I29: B2C
A30: 45658 | B30: 45668 | C30: INV-000053 | D30: Closed | E30: Diwan Law Associates | F30: 5000 | G30: 0 | H30: 5000 | I30: B2B
A31: 45658 | B31: 45671 | C31: INV-000054 | D31: Closed | E31: B2C | F31: 1889 | G31: 0 | H31: 1889 | I31: B2C
A32: 45658 | B32: 45671 | C32: INV-000055 | D32: Closed | E32: Mustafa S. Doctor | F32: 162000 | G32: 0 | H32: 162000 | I32: B2B
A33: 45658 | B33: 45674 | C33: INV-000056 | D33: Closed | E33: B2C | F33: 5683 | G33: 0 | H33: 5683 | I33: B2C
... A308: 45597 | B308: 45626 | C308: INV-000026 | D308: Closed | E308: B2C | F308: 2293 | G308: 0 | H308: 2293 | I308: B2C
A309: 45809 | B309: 45809 | C309: INV-25-26-000161 | D309: Overdue | E309: LEGALOGIC CONSULTING LLP | F309: 38000 | G309: 6840 | H309: =F309+G309 -> 44840 | I309: B2B | J309: =VLOOKUP(C309,'FY 25-26-Accrual'!$D$192:$D$233,1,0) -> INV-25-26-000161
A310: 45809 | B310: 45810 | C310: INV-25-26-000162 | D310: Closed | E310: B2C | F310: 6772.88 | G310: 1219.1184 | H310: =F310+G310 -> 7991.9984 | I310: B2C | J310: =VLOOKUP(C310,'FY 25-26-Accrual'!$D$192:$D$233,1,0) -> #N/A
A311: 45809 | B311: 45810 | C311: INV-25-26-000163 | D311: Closed | E311: Poovayya & CO | F311: 20000 | G311: 3600 | H311: =F311+G311 -> 23600 | I311: B2B | J311: =VLOOKUP(C311,'FY 25-26-Accrual'!$D$192:$D$233,1,0) -> INV-25-26-000163
A312: 45809 | B312: 45810 | C312: INV-25-26-000164 | D312: Closed | E312: Sajan Poovayya | F312: 20000 | G312: 3600 | H312: =F312+G312 -> 23600 | I312: B2B | J312: =VLOOKUP(C312,'FY 25-26-Accrual'!$D$192:$D$233,1,0) -> INV-25-26-000164
A313: 45809 | B313: 45811 | C313: INV-25-26-000165 | D313: Overdue | E313: Shrey Lodha | F313: 10000 | G313: 1800 | H313: =F313+G313 -> 11800 | I313: B2B | J313: ='FY 25-26-Accrual'!$D$234 -> INV-25-26-000165 & CN-00011
A314: 45809 | B314: 45812 | C314: INV-25-26-000166 | D314: Closed | E314: Gupta Law Associates | F314: 15000 | G314: 2700 | H314: =F314+G314 -> 17700 | I314: B2B | J314: =VLOOKUP(C314,'FY 25-26-Accrual'!$D$192:$D$233,1,0) -> INV-25-26-000166
A315: 45809 | B315: 45812 | C315: INV-25-26-000167 | D315: Overdue | E315: Vardharma Chambers | F315: 7000 | G315: 1260 | H315: =F315+G315 -> 8260 | I315: B2B | J315: =VLOOKUP(C315,'FY 25-26-Accrual'!$D$192:$D$233,1,0) -> INV-25-26-000167
A316: 45809 | B316: 45812 | C316: INV-25-26-000168 | D316: Closed | E316: Birendra Saraf | F316: 216000 | G316: 38880 | H316: =F316+G316 -> 254880 | I316: B2B | J316: =VLOOKUP(C316,'FY 25-26-Accrual'!$D$192:$D$233,1,0) -> INV-25-26-000168
A317: 45809 | B317: 45812 | C317: INV-25-26-000169 | D317: Closed | E317: IRIS LEGAL | F317: 8474.58 | G317: 1525.4244 | H317: =F317+G317 -> 10000.004 | I317: B2B | J317: =VLOOKUP(C317,'FY 25-26-Accrual'!$D$192:$D$233,1,0) -> INV-25-26-000169
A318: 45809 | B318: 45813 | C318: INV-25-26-000170 | D318: Closed | E318: B2C | F318: 17781.4 | G318: 3200.652 | H318: =F318+G318 -> 20982.052 | I318: B2C | J318: =VLOOKUP(C318,'FY 25-26-Accrual'!$D$192:$D$233,1,0) -> #N/A
A319: 45809 | B319: 45814 | C319: INV-25-26-000171 | D319: Closed | E319: Chambers of Ninad Laud | F319: 10000 | G319: 1800 | H319: =F319+G319 -> 11800 | I319: B2B | J319: ='FY 25-26-Accrual'!$D$85 -> INV-25-26-000105,0171, 246, 332,415, CN-00029, 496
A320: 45809 | B320: 45814 | C320: INV-25-26-000172 | D320: Closed | E320: JYOT-A Public Trust | F320: 63000 | G320: 11340 | H320: =F320+G320 -> 74340 | I320: B2B | J320: =VLOOKUP(C320,'FY 25-26-Accrual'!$D$192:$D$233,1,0) -> INV-25-26-000172
A321: 45809 | B321: 45814 | C321: INV-25-26-000173 | D321: Closed | E321: Yakshay Chheda | F321: 8474.58 | G321: 1525.4244 | H321: =F321+G321 -> 10000.004 | I321: B2B | J321: =VLOOKUP(C321,'FY 25-26-Accrual'!$D$192:$D$233,1,0) -> INV-25-26-000173
A322: 45809 | B322: 45814 | C322: INV-25-26-000174 | D322: Closed | E322: Tipping Mr Pink Private Limited | F322: 7000 | G322: 1260 | H322: =F322+G322 -> 8260 | I322: B2B | J322: =VLOOKUP(C322,'FY 25-26-Accrual'!$D$192:$D$233,1,0) -> INV-25-26-000174
A323: 45809 | B323: 45814 | C323: INV-25-26-000175 | D323: Closed | E323: KUAJ LEGAL | F323: 80000 | G323: 14400 | H323: =F323+G323 -> 94400 | I323: B2B | J323: =VLOOKUP(C323,'FY 25-26-Accrual'!$D$192:$D$233,1,0) -> INV-25-26-000175
A324: 45809 | B324: 45814 | C324: INV-25-26-000176 | D324: Closed | E324: AJNM LAW INDIA LLP | F324: 20000 | G324: 3600 | H324: =F324+G324 -> 23600 | I324: B2B | J324: =VLOOKUP(C324,'FY 25-26-Accrual'!$D$192:$D$233,1,0) -> INV-25-26-000176
A325: 45809 | B325: 45815 | C325: INV-25-26-000177 | D325: Closed | E325: Advocate Rohit Jaiswal | F325: 5000 | G325: 900 | H325: =F325+G325 -> 5900 | I325: B2B | J325: ='FY 25-26-Accrual'!$D$11 -> INV-25-26-000009,00107,00177
A326: 45809 | B326: 45815 | C326: INV-25-26-000178 | D326: Overdue | E326: Darius J. Khambata | F326: 16949.15 | G326: 3050.847 | H326: =F326+G326 -> 19999.997 | I326: B2B | J326: ='FY 25-26-Accrual'!$D$22 -> INV-000085, INV-25-26-000021,INV-25-26-000022, 148,178, 248, 337, 416, 500
A327: 45809 | B327: 45815 | C327: INV-25-26-000179 | D327: Overdue | E327: Harshit Malik | F327: 10000 | G327: 1800 | H327: =F327+G327 -> 11800 | I327: B2B | J327: ='FY 25-26-Accrual'!$D$18 -> INV-000111, INV-25-26-000016, 0109
A328: 45809 | B328: 45817 | C328: INV-25-26-000180 | D328: Closed | E328: Manish kelker | F328: 3388.98 | G328: 610.0164 | H328: =F328+G328 -> 3998.9964 | I328: B2B | J328: ='FY 25-26-Accrual'!$D$76 -> 40, INV-000088, 0112, INV-25-26-000078, 111,0180, 256, 343, 420, 505
A329: 45809 | B329: 45817 | C329: INV-25-26-000181 | D329: Closed | E329: Agraa Legal | F329: 420000 | G329: 75600 | H329: =F329+G329 -> 495600 | I329: B2B | J329: =VLOOKUP(C329,'FY 25-26-Accrual'!$D$192:$D$233,1,0) -> INV-25-26-000181
A330: 45809 | B330: 45817 | C330: INV-25-26-000182 | D330: Overdue | E330: KINJAL CIVILCON LLP | F330: 15000 | G330: 2700 | H330: =F330+G330 -> 17700 | I330: B2B | J330: =VLOOKUP(C330,'FY 25-26-Accrual'!$D$192:$D$233,1,0) -> INV-25-26-000182
A331: 45809 | B331: 45817 | C331: INV-25-26-000183 | D331: Closed | E331: Abhimanyu Garg / Methodica Legal | F331: 31271.19 | G331: 5628.8142 | H331: =F331+G331 -> 36900.004 | I331: B2B | J331: ='FY 25-26-Accrual'!$D$161 -> INV-000042, 000183 000218,421
A332: 45809 | B332: 45818 | C332: INV-25-26-000184 | D332: Closed | E332: Swapna Sheshadri | F332: 10000 | G332: 1800 | H332: =F332+G332 -> 11800 | I332: B2B | J332: ='FY 25-26-Accrual'!$D$20 -> INV-25-26-000019, 113, 0184, 259
A333: 45809 | B333: 45818 | C333: INV-25-26-000185 | D333: Closed | E333: SKR & associates | F333: 8729 | G333: 1571.22 | H333: =F333+G333 -> 10300.22 | I333: B2B | J333: ='FY 25-26-Accrual'!$D$63 -> INV-25-26-000065,114,0185, 260, 344, 425, 510
A334: 45809 | B334: 45818 | C334: INV-25-26-000186 | D334: Closed | E334: Shobit Phutela | F334: 108000 | G334: 19440 | H334: =F334+G334 -> 127440 | I334: B2B | J334: =VLOOKUP(C334,'FY 25-26-Accrual'!$D$192:$D$233,1,0) -> INV-25-26-000186
A335: 45809 | B335: 45818 | C335: INV-25-26-000187 | D335: Overdue | E335: Narottam Sharma | F335: 108000 | G335: 19440 | H335: =F335+G335 -> 127440 | I335: B2B | J335: =VLOOKUP(C335,'FY 25-26-Accrual'!$D$192:$D$233,1,0) -> INV-25-26-000187
A336: 45809 | B336: 45818 | C336: INV-25-26-000188 | D336: Closed | E336: Monalisa Kosaria | F336: 30000 | G336: 5400 | H336: =F336+G336 -> 35400 | I336: B2B | J336: =VLOOKUP(C336,'FY 25-26-Accrual'!$D$192:$D$233,1,0) -> INV-25-26-000188
A337: 45809 | B337: 45819 | C337: INV-25-26-000189 | D337: Closed | E337: Rahul Saboo, Advocate | F337: 8474.58 | G337: 1525.4244 | H337: =F337+G337 -> 10000.004 | I337: B2B | J337: =VLOOKUP(C337,'FY 25-26-Accrual'!$D$192:$D$233,1,0) -> #N/A
A338: 45809 | B338: 45819 | C338: INV-25-26-000190 | D338: Overdue | E338: DSK Legal | F338: 50000 | G338: 9000 | H338: =F338+G338 -> 59000 | I338: B2B | J338: =VLOOKUP(C338,'FY 25-26-Accrual'!$D$192:$D$233,1,0) -> INV-25-26-000190
A339: 45809 | B339: 45820 | C339: INV-25-26-000191 | D339: Closed | E339: Diwan Law Associates | F339: 4237.29 | G339: 762.7122 | H339: =F339+G339 -> 5000.0022 | I339: B2B | J339: ='FY 25-26-Accrual'!$D$77 -> INV-000091, 0114, INV-25-26-000079, 115,191, 263,346, 513
A340: 45809 | B340: 45820 | C340: INV-25-26-000192 | D340: Closed | E340: RAJANI ASSOCIATES | F340: 21000 | G340: 3780 | H340: =F340+G340 -> 24780 | I340: B2B | J340: =VLOOKUP(C340,'FY 25-26-Accrual'!$D$192:$D$233,1,0) -> INV-25-26-000192
A341: 45809 | B341: 45820 | C341: INV-25-26-000193 | D341: Closed | E341: RAJANI ASSOCIATES | F341: 14000 | G341: 2520 | H341: =F341+G341 -> 16520 | I341: B2B | J341: =VLOOKUP(C341,'FY 25-26-Accrual'!$D$192:$D$233,1,0) -> INV-25-26-000193
A342: 45809 | B342: 45821 | C342: INV-25-26-000194 | D342: Closed | E342: Meghna Talwar | F342: 60000 | G342: 10800 | H342: =F342+G342 -> 70800 | I342: B2B | J342: =VLOOKUP(C342,'FY 25-26-Accrual'!$D$192:$D$233,1,0) -> INV-25-26-000194
A343: 45809 | B343: 45821 | C343: INV-25-26-000195 | D343: Closed | E343: Miglani Varma & Co. | F343: 70000 | G343: 12600 | H343: =F343+G343 -> 82600 | I343: B2B | J343: =VLOOKUP(C343,'FY 25-26-Accrual'!$D$192:$D$233,1,0) -> INV-25-26-000195
A344: 45809 | B344: 45821 | C344: INV-25-26-000196 | D344: Closed | E344: S Priya | F344: 8000 | G344: 1440 | H344: =F344+G344 -> 9440 | I344: B2B | J344: =VLOOKUP(C344,'FY 25-26-Accrual'!$D$192:$D$233,1,0) -> INV-25-26-000196
A345: 45809 | B345: 45822 | C345: INV-25-26-000197 | D345: Closed | E345: Megha Chandra | F345: 10000 | G345: 1800 | H345: =F345+G345 -> 11800 | I345: B2B | J345: ='FY 25-26-Accrual'!$D$162 -> INV-000116, INV-25-26-000099,197,264, 347, 430, 514
A346: 45809 | B346: 45823 | C346: INV-25-26-000198 | D346: Overdue | E346: TLH, Advocates & Solicitors | F346: 150000 | G346: 27000 | H346: =F346+G346 -> 177000 | I346: B2B | J346: ='FY 25-26-Accrual'!$D$29 -> INV-25-26-000030, 124, 198,271
A347: 45809 | B347: 45823 | C347: INV-25-26-000199 | D347: Closed | E347: R. Vishnu Kumar, Advocate | F347: 16950 | G347: 3051 | H347: =F347+G347 -> 20001 | I347: B2B | J347: ='FY 25-26-Accrual'!$D$32 -> INV-25-26-000034, 125, 199, 272, 358, 528
A348: 45809 | B348: 45824 | C348: INV-25-26-000200 | D348: Overdue | E348: Yash Momaya | F348: 10000 | G348: 1800 | H348: =F348+G348 -> 11800 | I348: B2B | J348: ='FY 25-26-Accrual'!$D$33 -> INV-25-26-000035, 0127, 0200
A349: 45809 | B349: 45824 | C349: INV-25-26-000201 | D349: Closed | E349: Joy Baxi & Associates | F349: 36000 | G349: 6480 | H349: =F349+G349 -> 42480 | I349: B2B | J349: =VLOOKUP(C349,'FY 25-26-Accrual'!$D$192:$D$233,1,0) -> INV-25-26-000201
A350: 45809 | B350: 45825 | C350: INV-25-26-000202 | D350: Closed | E350: Dewani Associates | F350: 108000 | G350: 19440 | H350: =F350+G350 -> 127440 | I350: B2B | J350: =VLOOKUP(C350,'FY 25-26-Accrual'!$D$192:$D$233,1,0) -> INV-25-26-000202
A351: 45809 | B351: 45825 | C351: INV-25-26-000203 | D351: Overdue | E351: Ganesh & Co. | F351: 205000 | G351: 36900 | H351: =F351+G351 -> 241900 | I351: B2B | J351: =VLOOKUP(C351,'FY 25-26-Accrual'!$D$192:$D$233,1,0) -> INV-25-26-000203
A352: 45809 | B352: 45826 | C352: INV-25-26-000204 | D352: Closed | E352: AMS Legal | F352: 7000 | G352: 1260 | H352: =F352+G352 -> 8260 | I352: B2B | J352: =VLOOKUP(C352,'FY 25-26-Accrual'!$D$192:$D$233,1,0) -> INV-25-26-000204
A353: 45809 | B353: 45827 | C353: INV-25-26-000205 | D353: Closed | E353: Vis Legis Law Practice | F353: 126000 | G353: 22680 | H353: =F353+G353 -> 148680 | I353: B2B | J353: =VLOOKUP(C353,'FY 25-26-Accrual'!$D$192:$D$233,1,0) -> #N/A
A354: 45809 | B354: 45827 | C354: INV-25-26-000206 | D354: Overdue | E354: U. S. GANDHI & CO. | F354: 18000 | G354: 3240 | H354: =F354+G354 -> 21240 | I354: B2B | J354: =VLOOKUP(C354,'FY 25-26-Accrual'!$D$192:$D$233,1,0) -> #N/A
A355: 45809 | B355: 45827 | C355: INV-25-26-000207 | D355: Closed | E355: Gauri Puri | F355: 5000 | G355: 900 | H355: =F355+G355 -> 5900 | I355: B2B | J355: =VLOOKUP(C355,'FY 25-26-Accrual'!$D$192:$D$233,1,0) -> #N/A
A356: 45809 | B356: 45827 | C356: INV-25-26-000208 | D356: Closed | E356: Amit Bhagat | F356: 5000 | G356: 900 | H356: =F356+G356 -> 5900 | I356: B2B | J356: =VLOOKUP(C356,'FY 25-26-Accrual'!$D$192:$D$233,1,0) -> #N/A
A357: 45809 | B357: 45828 | C357: INV-25-26-000209 | D357: Closed | E357: Vishal Kanade | F357: 162000 | G357: 29160 | H357: =F357+G357 -> 191160 | I357: B2B | J357: =VLOOKUP(C357,'FY 25-26-Accrual'!$D$192:$D$233,1,0) -> INV-25-26-000209
A358: 45809 | B358: 45829 | C358: INV-25-26-000210 | D358: Overdue | E358: Stride Legal | F358: 10000 | G358: 1800 | H358: =F358+G358 -> 11800 | I358: B2B | J358: ='FY 25-26-Accrual'!$D$107 -> INV-25-26-000136, 0210, 292, 372, 457, CN- 30 to 33
A359: 45809 | B359: 45829 | C359: INV-25-26-000211 | D359: Closed | E359: Sundeep Karnik | F359: 56000 | G359: 10080 | H359: =F359+G359 -> 66080 | I359: B2B | J359: =VLOOKUP(C359,'FY 25-26-Accrual'!$D$192:$D$233,1,0) -> INV-25-26-000211
A360: 45809 | B360: 45829 | C360: INV-25-26-000212 | D360: Closed | E360: Hamza mir | F360: 5000 | G360: 900 | H360: =F360+G360 -> 5900 | I360: B2B | J360: ='FY 25-26-Accrual'!$D$84 -> INV-25-26-000103, 212, 265, 365
A361: 45809 | B361: 45831 | C361: INV-25-26-000213 | D361: Overdue | E361: Pranay Chitale | F361: 15000 | G361: 2700 | H361: =F361+G361 -> 17700 | I361: B2B | J361: ='FY 25-26-Accrual'!$D$40 -> INV-25-26-000042, 137, 213
A362: 45809 | B362: 45831 | C362: INV-25-26-000214 | D362: Closed | E362: Rohan Talwar | F362: 35000 | G362: 6300 | H362: =F362+G362 -> 41300 | I362: B2B | J362: =VLOOKUP(C362,'FY 25-26-Accrual'!$D$192:$D$233,1,0) -> INV-25-26-000214
A363: 45809 | B363: 45831 | C363: INV-25-26-000215 | D363: Overdue | E363: ZEUS Law Associates | F363: 40000 | G363: 7200 | H363: =F363+G363 -> 47200 | I363: B2B | J363: =VLOOKUP(C363,'FY 25-26-Accrual'!$D$192:$D$233,1,0) -> INV-25-26-000215
A364: 45809 | B364: 45832 | C364: INV-25-26-000216 | D364: Overdue | E364: Aurtus Consulting LLP | F364: 54000 | G364: 9720 | H364: =F364+G364 -> 63720 | I364: B2B | J364: =VLOOKUP(C364,'FY 25-26-Accrual'!$D$192:$D$233,1,0) -> INV-25-26-000216
A365: 45809 | B365: 45832 | C365: INV-25-26-000217 | D365: Overdue | E365: Tvashta Law | F365: 180000 | G365: 32400 | H365: =F365+G365 -> 212400 | I365: B2B | J365: =VLOOKUP(C365,'FY 25-26-Accrual'!$D$192:$D$233,1,0) -> INV-25-26-000217
A366: 45809 | B366: 45833 | C366: INV-25-26-000218 | D366: Closed | E366: Abhimanyu Garg / Methodica Legal | F366: 31271.19 | G366: 5628.8142 | H366: =F366+G366 -> 36900.004 | I366: B2B | J366: ='FY 25-26-Accrual'!$D$161 -> INV-000042, 000183 000218,421
A367: 45809 | B367: 45834 | C367: INV-25-26-000219 | D367: Closed | E367: The Guild | Advocates & Associate Counsel | F367: 50847.46 | G367: 9152.5428 | H367: =F367+G367 -> 60000.003 | I367: B2B | J367: ='FY 25-26-Accrual'!$D$160 -> INV-000038,00219
A368: 45809 | B368: 45834 | C368: CN-00003 | D368: Closed | E368: Advocate Rohit Jaiswal | F368: -5000 | G368: -900 | H368: =F368+G368 -> -5900 | I368: B2B | J368: ='FY 25-26-Accrual'!$D$11 -> INV-25-26-000009,00107,00177
A369: 45809 | B369: 45834 | C369: CN-00004 | D369: Closed | E369: Advocate Rohit Jaiswal | F369: -5000 | G369: -900 | H369: =F369+G369 -> -5900 | I369: B2B | J369: ='FY 25-26-Accrual'!$D$11 -> INV-25-26-000009,00107,00177
A370: 45809 | B370: 45835 | C370: INV-25-26-000220 | D370: Closed | E370: Tejeshwar Singh | F370: 30000 | G370: 5400 | H370: =F370+G370 -> 35400 | I370: B2B | J370: =VLOOKUP(C370,'FY 25-26-Accrual'!$D$192:$D$233,1,0) -> #N/A
A371: 45809 | B371: 45835 | C371: INV-25-26-000221 | D371: Closed | E371: Apoorv Kurup | F371: 35000 | G371: 6300 | H371: =F371+G371 -> 41300 | I371: B2B | J371: =VLOOKUP(C371,'FY 25-26-Accrual'!$D$192:$D$233,1,0) -> INV-25-26-000221
A372: 45809 | B372: 45836 | C372: INV-25-26-000222 | D372: Closed | E372: Elixir Legal Services | F372: 63000 | G372: 11340 | H372: =F372+G372 -> 74340 | I372: B2B | J372: =VLOOKUP(C372,'FY 25-26-Accrual'!$D$192:$D$233,1,0) -> INV-25-26-000222
A373: 45809 | B373: 45837 | C373: INV-25-26-000223 | D373: Closed | E373: SRCO Legal / Salvador Raghav & Co. | F373: 6779.66 | G373: 1220.3388 | H373: =F373+G373 -> 7999.9988 | I373: B2B | J373: ='FY 25-26-Accrual'!$D$78 -> INV-000145,00011, INV-25-26-000080,0106, 0223, 312, 390, 474
A374: 45809 | B374: 45838 | C374: INV-25-26-000224 | D374: Closed | E374: Deep Cover Law- Chirag Narasimiah | F374: 9000 | G374: 1620 | H374: =F374+G374 -> 10620 | I374: B2B | J374: ='FY 25-26-Accrual'!$D$124 -> INV-25-26-000157,000224,313
A375: 45809 | B375: 45838 | C375: INV-25-26-000225 | D375: Closed | E375: Harshit Malik | F375: 60000 | G375: 10800 | H375: =F375+G375 -> 70800 | I375: B2B | J375: =VLOOKUP(C375,'FY 25-26-Accrual'!$D$192:$D$233,1,0) -> INV-25-26-000225
...

Sheet Active Subscriber
A1: 45627 | D1: 45658 | G1: Feb | J1: Mar | M1: 45748 | P1: May | S1: June | U1: July | X1: 45870 | AA1: Sept | AD1: Oct
A2: The Guild | Advocates & Associate Counsel | B2: =VLOOKUP(A2,D:D,1,0) -> The Guild | Advocates & Associate Counsel | D2: Shyam Kapadia | E2: =VLOOKUP(D2,G:G,1,0) -> Shyam Kapadia | G2: The Guild | Advocates & Associate Counsel | H2: =VLOOKUP(G2,J:J,1,0) -> The Guild | Advocates & Associate Counsel | J2: The Guild | Advocates & Associate Counsel | K2: =VLOOKUP(J2,M:M,1,0) -> The Guild | Advocates & Associate Counsel | M2: Touchstone Partners | N2: =VLOOKUP(M2,P:P,1,0) -> Touchstone Partners | P2: Touchstone Partners | Q2: =VLOOKUP(P2,S:S,1,0) -> Touchstone Partners | S2: Touchstone Partners | T2: =VLOOKUP(S2,U:U,1,0) -> #N/A | U2: Veritas Legal Advocates and Solicitors | V2: =VLOOKUP(U2,X:X,1,0) -> Veritas Legal Advocates and Solicitors | X2: The Guild | Advocates & Associate Counsel | Y2: =VLOOKUP(X2,AA:AA,1,0) -> The Guild | Advocates & Associate Counsel | AA2: Veritas Legal Advocates and Solicitors | AB2: =VLOOKUP(AA2,AD:AD,1,0) -> Veritas Legal Advocates and Solicitors | AD2: Veritas Legal Advocates and Solicitors | AE2: =VLOOKUP(AD2,AA:AA,1,0) -> Veritas Legal Advocates and Solicitors
A3: SRCO Legal / Salvador Raghav & Co. | B3: =VLOOKUP(A3,D:D,1,0) -> SRCO Legal / Salvador Raghav & Co. | D3: Naushad Engineer | E3: =VLOOKUP(D3,G:G,1,0) -> Naushad Engineer | G3: Abel Tom Benny // Thomas and Thomas Advocates | H3: =VLOOKUP(G3,J:J,1,0) -> Abel Tom Benny // Thomas and Thomas Advocates | J3: Abel Tom Benny // Thomas and Thomas Advocates | K3: =VLOOKUP(J3,M:M,1,0) -> Abel Tom Benny // Thomas and Thomas Advocates | M3: Bimal Rajasekhar | N3: =VLOOKUP(M3,P:P,1,0) -> Bimal Rajasekhar | P3: Bimal Rajasekhar | Q3: =VLOOKUP(P3,S:S,1,0) -> #N/A | S3: Veritas Legal Advocates and Solicitors | T3: =VLOOKUP(S3,U:U,1,0) -> Veritas Legal Advocates and Solicitors | U3: VACUITAS COUNSELLOR LLP | V3: =VLOOKUP(U3,X:X,1,0) -> VACUITAS COUNSELLOR LLP | X3: Aanchal Basur | Y3: =VLOOKUP(X3,AA:AA,1,0) -> Aanchal Basur | AA3: VACUITAS COUNSELLOR LLP | AB3: =VLOOKUP(AA3,AD:AD,1,0) -> VACUITAS COUNSELLOR LLP | AD3: VACUITAS COUNSELLOR LLP | AE3: =VLOOKUP(AD3,AA:AA,1,0) -> VACUITAS COUNSELLOR LLP
A4: Office of ASG (N. Venkatraman) | B4: =VLOOKUP(A4,D:D,1,0) -> Office of ASG (N. Venkatraman) | D4: SRCO Legal / Salvador Raghav & Co. | E4: =VLOOKUP(D4,G:G,1,0) -> SRCO Legal / Salvador Raghav & Co. | G4: Abhimanyu Garg / Methodica Legal | H4: =VLOOKUP(G4,J:J,1,0) -> Abhimanyu Garg / Methodica Legal | J4: Abhimanyu Garg / Methodica Legal | K4: =VLOOKUP(J4,M:M,1,0) -> Abhimanyu Garg / Methodica Legal | M4: Veritas Legal Advocates and Solicitors | N4: =VLOOKUP(M4,P:P,1,0) -> Veritas Legal Advocates and Solicitors | P4: Veritas Legal Advocates and Solicitors | Q4: =VLOOKUP(P4,S:S,1,0) -> Veritas Legal Advocates and Solicitors | S4: VACUITAS COUNSELLOR LLP | T4: =VLOOKUP(S4,U:U,1,0) -> VACUITAS COUNSELLOR LLP | U4: Dileep Poolakkot | V4: =VLOOKUP(U4,X:X,1,0) -> Dileep Poolakkot | X4: Abel Tom Benny // Thomas and Thomas Advocates | Y4: =VLOOKUP(X4,AA:AA,1,0) -> Abel Tom Benny // Thomas and Thomas Advocates | AA4: Dileep Poolakkot | AB4: =VLOOKUP(AA4,AD:AD,1,0) -> Dileep Poolakkot | AD4: Dileep Poolakkot | AE4: =VLOOKUP(AD4,AA:AA,1,0) -> Dileep Poolakkot
A5: Aditya Sikka / Tvashta Law | B5: =VLOOKUP(A5,D:D,1,0) -> Aditya Sikka / Tvashta Law | D5: Saswat Mohanty | E5: =VLOOKUP(D5,G:G,1,0) -> Saswat Mohanty | G5: Aditya Sikka / Tvashta Law | H5: =J53 -> Tvashta Law | J5: Agama Law Associates | K5: =VLOOKUP(J5,M:M,1,0) -> Agama Law Associates | M5: LEGALOGIC CONSULTING LLP | N5: =VLOOKUP(M5,P:P,1,0) -> LEGALOGIC CONSULTING LLP | P5: LEGALOGIC CONSULTING LLP | Q5: =VLOOKUP(P5,S:S,1,0) -> LEGALOGIC CONSULTING LLP | S5: U. S. GANDHI & CO. | T5: =VLOOKUP(S5,U:U,1,0) -> U. S. GANDHI & CO. | U5: Agama Law Associates | V5: =VLOOKUP(U5,X:X,1,0) -> Agama Law Associates | X5: Abhimanyu Garg / Methodica Legal | Y5: =VLOOKUP(X5,AA:AA,1,0) -> Abhimanyu Garg / Methodica Legal | AA5: Agama Law Associates | AB5: =VLOOKUP(AA5,AD:AD,1,0) -> Agama Law Associates | AD5: Agama Law Associates | AE5: =VLOOKUP(AD5,AA:AA,1,0) -> Agama Law Associates
A6: Chambers of Pujari | B6: =VLOOKUP(A6,D:D,1,0) -> #N/A | D6: Manish kelker | E6: =VLOOKUP(D6,G:G,1,0) -> Manish kelker | G6: Agama Law Associates | H6: =VLOOKUP(G6,J:J,1,0) -> Agama Law Associates | J6: Akriti Chaubey | K6: =VLOOKUP(J6,M:M,1,0) -> Akriti Chaubey | M6: VACUITAS COUNSELLOR LLP | N6: =VLOOKUP(M6,P:P,1,0) -> VACUITAS COUNSELLOR LLP | P6: VACUITAS COUNSELLOR LLP | Q6: =VLOOKUP(P6,S:S,1,0) -> VACUITAS COUNSELLOR LLP | S6: Dileep Poolakkot | T6: =VLOOKUP(S6,U:U,1,0) -> Dileep Poolakkot | U6: Venkatesh Dhond | V6: =VLOOKUP(U6,X:X,1,0) -> Venkatesh Dhond | X6: Acuity Law LLP | Y6: =VLOOKUP(X6,AA:AA,1,0) -> Acuity Law LLP | AA6: PSN Legal Advocates and Legal Consultants | AB6: =VLOOKUP(AA6,AD:AD,1,0) -> PSN Legal Advocates and Legal Consultants | AD6: PSN Legal Advocates and Legal Consultants | AE6: =VLOOKUP(AD6,AA:AA,1,0) -> PSN Legal Advocates and Legal Consultants
A7: Kanungo & Co. | B7: =VLOOKUP(A7,D:D,1,0) -> Kanungo & Co. | D7: Ish Jain / Regius Partners LLP | E7: =VLOOKUP(D7,G:G,1,0) -> Ish Jain / Regius Partners LLP | G7: ANG | H7: =VLOOKUP(G7,J:J,1,0) -> #N/A | J7: Akshat Vachher | K7: =VLOOKUP(J7,M:M,1,0) -> #N/A | M7: Tvashta Law | N7: =VLOOKUP(M7,P:P,1,0) -> Tvashta Law | P7: U. S. GANDHI & CO. | Q7: =VLOOKUP(P7,S:S,1,0) -> U. S. GANDHI & CO. | S7: Utkarsh Joshi | T7: =VLOOKUP(S7,U:U,1,0) -> #N/A | U7: PSN Legal Advocates and Legal Consultants | V7: =VLOOKUP(U7,X:X,1,0) -> PSN Legal Advocates and Legal Consultants | X7: Agama Law Associates | Y7: =VLOOKUP(X7,AA:AA,1,0) -> Agama Law Associates | AA7: Darius J. Khambata | AB7: =VLOOKUP(AA7,AD:AD,1,0) -> Darius J. Khambata | AD7: Darius J. Khambata | AE7: =VLOOKUP(AD7,AA:AA,1,0) -> Darius J. Khambata
A8: ANG | B8: =VLOOKUP(A8,D:D,1,0) -> ANG | D8: Tejas Bhide | E8: =VLOOKUP(D8,G:G,1,0) -> #N/A | G8: Argus Partners | H8: =VLOOKUP(G8,J:J,1,0) -> Argus Partners | J8: Amrita Panda / ADP Chambers- 62 | K8: =VLOOKUP(J8,M:M,1,0) -> Amrita Panda / ADP Chambers- 62 | M8: U. S. GANDHI & CO. | N8: =VLOOKUP(M8,P:P,1,0) -> U. S. GANDHI & CO. | P8: Advocate Rohit Jaiswal | Q8: =VLOOKUP(P8,S:S,1,0) -> #N/A | S8: Karan Butalia | T8: =VLOOKUP(S8,U:U,1,0) -> #N/A | U8: Swapna Sheshadri | V8: =VLOOKUP(U8,X:X,1,0) -> Swapna Sheshadri | X8: Agraa Legal | Y8: =VLOOKUP(X8,AA:AA,1,0) -> Agraa Legal | AA8: Rashmikant and Partners | AB8: =VLOOKUP(AA8,AD:AD,1,0) -> Rashmikant and Partners | AD8: Rashmikant and Partners | AE8: =VLOOKUP(AD8,AA:AA,1,0) -> Rashmikant and Partners
A9: Ratan Kumar Singh | B9: =VLOOKUP(A9,D:D,1,0) -> Ratan Kumar Singh | D9: Abhimanyu Garg / Methodica Legal | E9: =VLOOKUP(D9,G:G,1,0) -> Abhimanyu Garg / Methodica Legal | G9: Asahi Legal LLP | H9: =VLOOKUP(G9,J:J,1,0) -> Asahi Legal LLP | J9: Argus Partners | K9: =VLOOKUP(J9,M:M,1,0) -> Argus Partners | M9: Advocate Rohit Jaiswal | N9: =VLOOKUP(M9,P:P,1,0) -> Advocate Rohit Jaiswal | P9: Dileep Poolakkot | Q9: =VLOOKUP(P9,S:S,1,0) -> Dileep Poolakkot | S9: Agama Law Associates | T9: =VLOOKUP(S9,U:U,1,0) -> Agama Law Associates | U9: Vutts & Associates LLP | V9: =VLOOKUP(U9,X:X,1,0) -> #N/A | X9: AHUJA VALECHA & ASSOCIATES LLP | Y9: =VLOOKUP(X9,AA:AA,1,0) -> AHUJA VALECHA & ASSOCIATES LLP | AA9: Shreeyash Lalit | AB9: =VLOOKUP(AA9,AD:AD,1,0) -> Shreeyash Lalit | AD9: Shreeyash Lalit | AE9: =VLOOKUP(AD9,AA:AA,1,0) -> Shreeyash Lalit
A10: Manish kelker | B10: =VLOOKUP(A10,D:D,1,0) -> Manish kelker | D10: Amrita Panda / ADP Chambers- 5 | E10: =VLOOKUP(D10,G:G,1,0) -> #N/A | G10: Chetan Dedhia | H10: =VLOOKUP(G10,J:J,1,0) -> #N/A | J10: Asahi Legal LLP | K10: =VLOOKUP(J10,M:M,1,0) -> Asahi Legal LLP | M10: Dileep Poolakkot | N10: =VLOOKUP(M10,P:P,1,0) -> Dileep Poolakkot | P10: Utkarsh Joshi | Q10: =VLOOKUP(P10,S:S,1,0) -> Utkarsh Joshi | S10: Venkatesh Dhond | T10: =VLOOKUP(S10,U:U,1,0) -> Venkatesh Dhond | U10: Darius J. Khambata | V10: =VLOOKUP(U10,X:X,1,0) -> Darius J. Khambata | X10: Akkash Bhadana | Y10: =VLOOKUP(X10,AA:AA,1,0) -> Akkash Bhadana | AA10: R. Vishnu Kumar, Advocate | AB10: =VLOOKUP(AA10,AD:AD,1,0) -> R. Vishnu Kumar, Advocate | AD10: R. Vishnu Kumar, Advocate | AE10: =VLOOKUP(AD10,AA:AA,1,0) -> R. Vishnu Kumar, Advocate
A11: Newton School - Incanus Technologies Private Limited | B11: =VLOOKUP(A11,D:D,1,0) -> #N/A | D11: Office of ASG (N. Venkatraman) | E11: =VLOOKUP(D11,G:G,1,0) -> Office of ASG (N. Venkatraman) | G11: Darius J. Khambata | H11: =VLOOKUP(G11,J:J,1,0) -> Darius J. Khambata | J11: Balbir Singh | K11: =VLOOKUP(J11,M:M,1,0) -> Balbir Singh | M11: Utkarsh Joshi | N11: =VLOOKUP(M11,P:P,1,0) -> Utkarsh Joshi | P11: Karan Butalia | Q11: =VLOOKUP(P11,S:S,1,0) -> Karan Butalia | S11: PSN Legal Advocates and Legal Consultants | T11: =VLOOKUP(S11,U:U,1,0) -> PSN Legal Advocates and Legal Consultants | U11: Miglani Varma & Co. | V11: =VLOOKUP(U11,X:X,1,0) -> Miglani Varma & Co. | X11: Amit Bhagat | Y11: =VLOOKUP(X11,AA:AA,1,0) -> Amit Bhagat | AA11: NC Legal | AB11: =VLOOKUP(AA11,AD:AD,1,0) -> NC Legal | AD11: NC Legal | AE11: =VLOOKUP(AD11,AA:AA,1,0) -> NC Legal
A12: Solaris Legal | B12: =VLOOKUP(A12,D:D,1,0) -> #N/A | D12: Shiraz Rustomjee | E12: =VLOOKUP(D12,G:G,1,0) -> Shiraz Rustomjee | G12: Dipankar Majumdar | H12: =VLOOKUP(G12,J:J,1,0) -> Dipankar Majumdar | J12: Burgeon Law LLP | K12: =VLOOKUP(J12,M:M,1,0) -> Burgeon Law LLP | M12: Karan Butalia | N12: =VLOOKUP(M12,P:P,1,0) -> Karan Butalia | P12: Agama Law Associates | Q12: =VLOOKUP(P12,S:S,1,0) -> Agama Law Associates | S12: Swapna Sheshadri | T12: =VLOOKUP(S12,U:U,1,0) -> Swapna Sheshadri | U12: Rashmikant and Partners | V12: =VLOOKUP(U12,X:X,1,0) -> Rashmikant and Partners | X12: Amrit Grewal | Y12: =VLOOKUP(X12,AA:AA,1,0) -> Amrit Grewal | AA12: RPV LEGAL | AB12: =VLOOKUP(AA12,AD:AD,1,0) -> RPV LEGAL | AD12: RPV LEGAL | AE12: =VLOOKUP(AD12,AA:AA,1,0) -> RPV LEGAL
A13: Talha Abdul Rahman | B13: =VLOOKUP(A13,D:D,1,0) -> #N/A | D13: Diwan Law Associates | E13: =VLOOKUP(D13,G:G,1,0) -> Diwan Law Associates | G13: Diwan Law Associates | H13: =VLOOKUP(G13,J:J,1,0) -> Diwan Law Associates | J13: Chambers of Aman Vachher | K13: =VLOOKUP(J13,M:M,1,0) -> Chambers of Aman Vachher | M13: Agama Law Associates | N13: =VLOOKUP(M13,P:P,1,0) -> Agama Law Associates | P13: RAJANI ASSOCIATES | Q13: =VLOOKUP(P13,S:S,1,0) -> RAJANI ASSOCIATES | S13: Vutts & Associates LLP | T13: =VLOOKUP(S13,U:U,1,0) -> Vutts & Associates LLP | U13: TLH, Advocates & Solicitors | V13: =VLOOKUP(U13,X:X,1,0) -> TLH, Advocates & Solicitors | X13: Amrita Panda / ADP Chambers- 62 | Y13: =VLOOKUP(X13,AA:AA,1,0) -> Amrita Panda / ADP Chambers- 62 | AA13: Justice (Retd.) Kurian Joseph | AB13: =VLOOKUP(AA13,AD:AD,1,0) -> Justice (Retd.) Kurian Joseph | AD13: Justice (Retd.) Kurian Joseph | AE13: =VLOOKUP(AD13,AA:AA,1,0) -> Justice (Retd.) Kurian Joseph
A14: Amrita Panda / ADP Chambers- 5 | B14: =VLOOKUP(A14,D:D,1,0) -> Amrita Panda / ADP Chambers- 5 | D14: Agama Law Associates | E14: =VLOOKUP(D14,G:G,1,0) -> Agama Law Associates | G14: Eternity Legal | H14: =VLOOKUP(G14,J:J,1,0) -> Eternity Legal | J14: Chambers of Justice Mohit S Shah (Retd.), Former Chief Justice of Bombay and Calcutta High Court | K14: =VLOOKUP(J14,M:M,1,0) -> Chambers of Justice Mohit S Shah (Retd.), Former Chief Justice of Bombay and Calcutta High Court | M14: RAJANI ASSOCIATES | N14: =VLOOKUP(M14,P:P,1,0) -> RAJANI ASSOCIATES | P14: Venkatesh Dhond | Q14: =VLOOKUP(P14,S:S,1,0) -> Venkatesh Dhond | S14: Darius J. Khambata | T14: =VLOOKUP(S14,U:U,1,0) -> Darius J. Khambata | U14: Shreeyash Lalit | V14: =VLOOKUP(U14,X:X,1,0) -> Shreeyash Lalit | X14: Amrut Joshi | Y14: =VLOOKUP(X14,AA:AA,1,0) -> Amrut Joshi | AA14: SINHA & COMPANY | AB14: =VLOOKUP(AA14,AD:AD,1,0) -> SINHA & COMPANY | AD14: SINHA & COMPANY | AE14: =VLOOKUP(AD14,AA:AA,1,0) -> SINHA & COMPANY
A15: Diwan Law Associates | B15: =VLOOKUP(A15,D:D,1,0) -> Diwan Law Associates | D15: Venkatesh Dhond | E15: =VLOOKUP(D15,G:G,1,0) -> Venkatesh Dhond | G15: Farhan Dubash | H15: =VLOOKUP(G15,J:J,1,0) -> Farhan Dubash | J15: Darius J. Khambata | K15: =VLOOKUP(J15,M:M,1,0) -> Darius J. Khambata | M15: Venkatesh Dhond | N15: =VLOOKUP(M15,P:P,1,0) -> Venkatesh Dhond | P15: Harshit Malik | Q15: =VLOOKUP(P15,S:S,1,0) -> Harshit Malik | S15: Miglani Varma & Co. | T15: =VLOOKUP(S15,U:U,1,0) -> Miglani Varma & Co. | U15: R. Vishnu Kumar, Advocate | V15: =VLOOKUP(U15,X:X,1,0) -> R. Vishnu Kumar, Advocate | X15: Ankit Talsania | Y15: =VLOOKUP(X15,AA:AA,1,0) -> #N/A | AA15: Darshit Jain | AB15: =VLOOKUP(AA15,AD:AD,1,0) -> Darshit Jain | AD15: Darshit Jain | AE15: =VLOOKUP(AD15,AA:AA,1,0) -> Darshit Jain
A16: Abhimanyu Garg / Methodica Legal | B16: =VLOOKUP(A16,D:D,1,0) -> Abhimanyu Garg / Methodica Legal | D16: Parakram Legal | E16: =VLOOKUP(D16,G:G,1,0) -> #N/A | G16: Gourab Banerji | H16: =J22 -> Gourab Banreji | J16: Dipankar Majumdar | K16: =VLOOKUP(J16,M:M,1,0) -> Dipankar Majumdar | M16: Harshit Malik | N16: =VLOOKUP(M16,P:P,1,0) -> Harshit Malik | P16: PSN Legal Advocates and Legal Consultants | Q16: =VLOOKUP(P16,S:S,1,0) -> PSN Legal Advocates and Legal Consultants | S16: Rashmikant and Partners | T16: =VLOOKUP(S16,U:U,1,0) -> Rashmikant and Partners | U16: NC Legal | V16: =VLOOKUP(U16,X:X,1,0) -> NC Legal | X16: ANM Global Inc | Y16: =VLOOKUP(X16,AA:AA,1,0) -> #N/A | AA16: Sagar Ghogre | AB16: =VLOOKUP(AA16,AD:AD,1,0) -> Sagar Ghogre | AD16: Sagar Ghogre | AE16: =VLOOKUP(AD16,AA:AA,1,0) -> Sagar Ghogre
A17: Ish Jain / Regius Partners LLP | B17: =VLOOKUP(A17,D:D,1,0) -> Ish Jain / Regius Partners LLP | D17: Kanungo & Co. | E17: =VLOOKUP(D17,G:G,1,0) -> #N/A | G17: Ish Jain / Regius Partners LLP | H17: =VLOOKUP(G17,J:J,1,0) -> Ish Jain / Regius Partners LLP | J17: Diwan Law Associates | K17: =VLOOKUP(J17,M:M,1,0) -> Diwan Law Associates | M17: PSN Legal Advocates and Legal Consultants | N17: =VLOOKUP(M17,P:P,1,0) -> PSN Legal Advocates and Legal Consultants | P17: Swapna Sheshadri | Q17: =VLOOKUP(P17,S:S,1,0) -> Swapna Sheshadri | S17: TLH, Advocates & Solicitors | T17: =VLOOKUP(S17,U:U,1,0) -> TLH, Advocates & Solicitors | U17: RPV LEGAL | V17: =VLOOKUP(U17,X:X,1,0) -> RPV LEGAL | X17: Anush Raajan | Y17: =VLOOKUP(X17,AA:AA,1,0) -> Anush Raajan | AA17: Chetan shah | AB17: =VLOOKUP(AA17,AD:AD,1,0) -> Chetan shah | AD17: Chetan shah | AE17: =VLOOKUP(AD17,AA:AA,1,0) -> Chetan shah
D18: Farhan Dubash | E18: =VLOOKUP(D18,G:G,1,0) -> Farhan Dubash | G18: Keystone Partners | H18: =VLOOKUP(G18,J:J,1,0) -> Keystone Partners | J18: Eternity Legal | K18: =VLOOKUP(J18,M:M,1,0) -> Eternity Legal | M18: Swapna Sheshadri | N18: =VLOOKUP(M18,P:P,1,0) -> Swapna Sheshadri | P18: Vutts & Associates LLP | Q18: =VLOOKUP(P18,S:S,1,0) -> Vutts & Associates LLP | S18: Shreeyash Lalit | T18: =VLOOKUP(S18,U:U,1,0) -> Shreeyash Lalit | U18: AP & Partners, Advocates | V18: =VLOOKUP(U18,X:X,1,0) -> #N/A | X18: Apoorv Kurup | Y18: =VLOOKUP(X18,AA:AA,1,0) -> Apoorv Kurup | AA18: Sneha Phene | AB18: =VLOOKUP(AA18,AD:AD,1,0) -> Sneha Phene | AD18: Sneha Phene | AE18: =VLOOKUP(AD18,AA:AA,1,0) -> Sneha Phene
D19: Prantar | E19: =VLOOKUP(D19,G:G,1,0) -> #N/A | G19: Manish kelker | H19: =VLOOKUP(G19,J:J,1,0) -> Manish kelker | J19: Farhan Dubash | K19: =VLOOKUP(J19,M:M,1,0) -> Farhan Dubash | M19: Vutts & Associates LLP | N19: =VLOOKUP(M19,P:P,1,0) -> Vutts & Associates LLP | P19: Darius J. Khambata | Q19: =VLOOKUP(P19,S:S,1,0) -> Darius J. Khambata | S19: Dewani Associates | T19: =VLOOKUP(S19,U:U,1,0) -> Dewani Associates | U19: Bathiya Legal | V19: =VLOOKUP(U19,X:X,1,0) -> #N/A | X19: Argus Partners | Y19: =VLOOKUP(X19,AA:AA,1,0) -> Argus Partners | AA19: Gunjan Mangla | AB19: =VLOOKUP(AA19,AD:AD,1,0) -> Gunjan Mangla | AD19: Gunjan Mangla | AE19: =VLOOKUP(AD19,AA:AA,1,0) -> Gunjan Mangla
D20: Gourab Banerji | E20: =VLOOKUP(D20,G:G,1,0) -> Gourab Banerji | G20: Monalisa Kosaria | H20: =VLOOKUP(G20,J:J,1,0) -> Monalisa Kosaria | J20: Federal & Company | K20: =VLOOKUP(J20,M:M,1,0) -> Federal & Company | M20: Darius J. Khambata | N20: =VLOOKUP(M20,P:P,1,0) -> Darius J. Khambata | P20: Miglani Varma & Co. | Q20: =VLOOKUP(P20,S:S,1,0) -> Miglani Varma & Co. | S20: R. Vishnu Kumar, Advocate | T20: =VLOOKUP(S20,U:U,1,0) -> R. Vishnu Kumar, Advocate | U20: Justice (Retd.) Kurian Joseph | V20: =VLOOKUP(U20,X:X,1,0) -> Justice (Retd.) Kurian Joseph | X20: Arpit Gupta | Y20: =VLOOKUP(X20,AA:AA,1,0) -> Arpit Gupta | AA20: Zulfiqar Jariwala | AB20: =VLOOKUP(AA20,AD:AD,1,0) -> Zulfiqar Jariwala | AD20: Zulfiqar Jariwala | AE20: =VLOOKUP(AD20,AA:AA,1,0) -> Zulfiqar Jariwala
D21: Keystone Partners | E21: =VLOOKUP(D21,G:G,1,0) -> Keystone Partners | G21: Mr. Jehangir Jejeebhoy | H21: =VLOOKUP(G21,J:J,1,0) -> Mr. Jehangir Jejeebhoy | J21: GM Legal | K21: =VLOOKUP(J21,M:M,1,0) -> GM Legal | M21: Miglani Varma & Co. | N21: =VLOOKUP(M21,P:P,1,0) -> Miglani Varma & Co. | P21: Venkatesh Mohanraj | Q21: =VLOOKUP(P21,S:S,1,0) -> #N/A | S21: NC Legal | T21: =VLOOKUP(S21,U:U,1,0) -> NC Legal | U21: SINHA & COMPANY | V21: =VLOOKUP(U21,X:X,1,0) -> SINHA & COMPANY | X21: Asahi Legal LLP | Y21: =VLOOKUP(X21,AA:AA,1,0) -> Asahi Legal LLP | AA21: Manjari Shah | AB21: =VLOOKUP(AA21,AD:AD,1,0) -> Manjari Shah | AD21: Manjari Shah | AE21: =VLOOKUP(AD21,AA:AA,1,0) -> Manjari Shah
D22: Mustafa S Doctor | E22: =VLOOKUP(D22,G:G,1,0) -> Mustafa S Doctor | G22: Mustafa S Doctor | H22: =VLOOKUP(G22,J:J,1,0) -> Mustafa S Doctor | J22: Gourab Banreji | K22: =VLOOKUP(J22,M:M,1,0) -> Gourab Banreji | M22: Venkatesh Mohanraj | N22: =VLOOKUP(M22,P:P,1,0) -> Venkatesh Mohanraj | P22: Jade Lex Partners | Q22: =VLOOKUP(P22,S:S,1,0) -> #N/A | S22: RPV LEGAL | T22: =VLOOKUP(S22,U:U,1,0) -> RPV LEGAL | U22: Darshit Jain | V22: =VLOOKUP(U22,X:X,1,0) -> Darshit Jain | X22: ASV Legal LLP | Y22: =VLOOKUP(X22,AA:AA,1,0) -> ASV Legal LLP | AA22: Sagar Sheth | AB22: =VLOOKUP(AA22,AD:AD,1,0) -> Sagar Sheth | AD22: Sagar Sheth | AE22: =VLOOKUP(AD22,AA:AA,1,0) -> Sagar Sheth
D23: Aditya Sikka / Tvashta Law | E23: =VLOOKUP(D23,G:G,1,0) -> Aditya Sikka / Tvashta Law | G23: MV Law Partners | H23: =VLOOKUP(G23,J:J,1,0) -> MV Law Partners | J23: Harshit Malik | K23: =VLOOKUP(J23,M:M,1,0) -> Harshit Malik | M23: Jade Lex Partners | N23: =VLOOKUP(M23,P:P,1,0) -> Jade Lex Partners | P23: Alankrit Bajpai | Q23: =VLOOKUP(P23,S:S,1,0) -> #N/A | S23: AP & Partners, Advocates | T23: =VLOOKUP(S23,U:U,1,0) -> AP & Partners, Advocates | U23: Sagar Ghogre | V23: =VLOOKUP(U23,X:X,1,0) -> Sagar Ghogre | X23: Aurtus Consulting LLP | Y23: =VLOOKUP(X23,AA:AA,1,0) -> Aurtus Consulting LLP | AA23: Mahek Bookwala | AB23: =VLOOKUP(AA23,AD:AD,1,0) -> Mahek Bookwala | AD23: Mahek Bookwala | AE23: =VLOOKUP(AD23,AA:AA,1,0) -> Mahek Bookwala
D24: Victoram Legal / Mr. Sajal Awasthi | E24: =VLOOKUP(D24,G:G,1,0) -> Victoram Legal / Mr. Sajal Awasthi | G24: MZM Legal LLP | H24: =VLOOKUP(G24,J:J,1,0) -> MZM Legal LLP | J24: Innovatus Law | K24: =VLOOKUP(J24,M:M,1,0) -> Innovatus Law | M24: Alankrit Bajpai | N24: =VLOOKUP(M24,P:P,1,0) -> Alankrit Bajpai | P24: Badar Durrez | Q24: =VLOOKUP(P24,S:S,1,0) -> #N/A | S24: Bathiya Legal | T24: =VLOOKUP(S24,U:U,1,0) -> Bathiya Legal | U24: Chetan shah | V24: =VLOOKUP(U24,X:X,1,0) -> Chetan shah | X24: Bharat Chugh | Y24: =VLOOKUP(X24,AA:AA,1,0) -> Bharat Chugh | AA24: Pratik Patnaik | AB24: =VLOOKUP(AA24,AD:AD,1,0) -> Pratik Patnaik | AD24: Pradeep Sancheti | AE24: =VLOOKUP(AD24,AA:AA,1,0) -> #N/A
D25: Ratan Kumar Singh | E25: =VLOOKUP(D25,G:G,1,0) -> Ratan Kumar Singh | G25: Naushad Engineer | H25: =VLOOKUP(G25,J:J,1,0) -> Naushad Engineer | J25: Ish Jain / Regius Partners LLP | K25: =VLOOKUP(J25,M:M,1,0) -> Ish Jain / Regius Partners LLP | M25: Badar Durrez | N25: =VLOOKUP(M25,P:P,1,0) -> Badar Durrez | P25: Rashmikant and Partners | Q25: =VLOOKUP(P25,S:S,1,0) -> Rashmikant and Partners | S25: Justice (Retd.) Kurian Joseph | T25: =VLOOKUP(S25,U:U,1,0) -> Justice (Retd.) Kurian Joseph | U25: Sneha Phene | V25: =VLOOKUP(U25,X:X,1,0) -> Sneha Phene | X25: Birendra Saraf | Y25: =VLOOKUP(X25,AA:AA,1,0) -> Birendra Saraf | AA25: Saswat Mohanty | AB25: =VLOOKUP(AA25,AD:AD,1,0) -> Saswat Mohanty | AD25: Pratik Patnaik | AE25: =VLOOKUP(AD25,AA:AA,1,0) -> Pratik Patnaik
D26: ANG | E26: =VLOOKUP(D26,G:G,1,0) -> ANG | G26: Office of ASG (N. Venkatraman) | H26: =VLOOKUP(G26,J:J,1,0) -> Office of ASG (N. Venkatraman) | J26: Justice (Retd.) AK Sikri | K26: =VLOOKUP(J26,M:M,1,0) -> Justice (Retd.) AK Sikri | M26: Rashmikant and Partners | N26: =VLOOKUP(M26,P:P,1,0) -> Rashmikant and Partners | P26: TLH, Advocates & Solicitors | Q26: =VLOOKUP(P26,S:S,1,0) -> TLH, Advocates & Solicitors | S26: SINHA & COMPANY | T26: =VLOOKUP(S26,U:U,1,0) -> SINHA & COMPANY | U26: Gunjan Mangla | V26: =VLOOKUP(U26,X:X,1,0) -> Gunjan Mangla | X26: Bishwajit Dubey | Y26: =VLOOKUP(X26,AA:AA,1,0) -> Bishwajit Dubey | AA26: Chambers of Aman Vachher | AB26: =VLOOKUP(AA26,AD:AD,1,0) -> Chambers of Aman Vachher | AD26: Saswat Mohanty | AE26: =VLOOKUP(AD26,AA:AA,1,0) -> Saswat Mohanty
D27: The Guild | Advocates & Associate Counsel | E27: =VLOOKUP(D27,G:G,1,0) -> The Guild | Advocates & Associate Counsel | G27: Prompt Legal (Shared by Jayanth) | H27: =VLOOKUP(G27,J:J,1,0) -> Prompt Legal (Shared by Jayanth) | J27: Justice (Retd.) Kurian Joseph | K27: =VLOOKUP(J27,M:M,1,0) -> Justice (Retd.) Kurian Joseph | M27: TLH, Advocates & Solicitors | N27: =VLOOKUP(M27,P:P,1,0) -> TLH, Advocates & Solicitors | P27: Shreeyash Lalit | Q27: =VLOOKUP(P27,S:S,1,0) -> Shreeyash Lalit | S27: Darshit Jain | T27: =VLOOKUP(S27,U:U,1,0) -> Darshit Jain | U27: Zulfiqar Jariwala | V27: =VLOOKUP(U27,X:X,1,0) -> Zulfiqar Jariwala | X27: Brijesh Oberoi | Y27: =VLOOKUP(X27,AA:AA,1,0) -> Brijesh Oberoi | AA27: SK Singhi and Partners | AB27: =VLOOKUP(AA27,AD:AD,1,0) -> SK Singhi and Partners | AD27: Chambers of Aman Vachher | AE27: =VLOOKUP(AD27,AA:AA,1,0) -> Chambers of Aman Vachher
D28: Dipankar Majumdar | E28: =VLOOKUP(D28,G:G,1,0) -> Dipankar Majumdar | G28: Ratan Kumar Singh | H28: =VLOOKUP(G28,J:J,1,0) -> Ratan Kumar Singh | J28: Keystone Partners | K28: =VLOOKUP(J28,M:M,1,0) -> Keystone Partners | M28: Shreeyash Lalit | N28: =VLOOKUP(M28,P:P,1,0) -> Shreeyash Lalit | P28: Dewani Associates | Q28: =VLOOKUP(P28,S:S,1,0) -> Dewani Associates | S28: Sagar Ghogre | T28: =VLOOKUP(S28,U:U,1,0) -> Sagar Ghogre | U28: Manjari Shah | V28: =VLOOKUP(U28,X:X,1,0) -> Manjari Shah | X28: Chambers of Aman Vachher | Y28: =VLOOKUP(X28,AA:AA,1,0) -> Chambers of Aman Vachher | AA28: SKR & associates | AB28: =VLOOKUP(AA28,AD:AD,1,0) -> SKR & associates | AD28: SK Singhi and Partners | AE28: =VLOOKUP(AD28,AA:AA,1,0) -> SK Singhi and Partners
G29: Sanjay Udeshi & Co. | H29: =VLOOKUP(G29,J:J,1,0) -> Sanjay Udeshi & Co. | J29: Manish kelker | K29: =VLOOKUP(J29,M:M,1,0) -> Manish kelker | M29: Dewani Associates | N29: =VLOOKUP(M29,P:P,1,0) -> Dewani Associates | P29: R. Vishnu Kumar, Advocate | Q29: =VLOOKUP(P29,S:S,1,0) -> R. Vishnu Kumar, Advocate | S29: Chetan shah | T29: =VLOOKUP(S29,U:U,1,0) -> Chetan shah | U29: Sagar Sheth | V29: =VLOOKUP(U29,X:X,1,0) -> Sagar Sheth | X29: Chambers of Justice Mohit S Shah (Retd.), Former Chief Justice of Bombay and Calcutta High Court | Y29: =VLOOKUP(X29,AA:AA,1,0) -> Chambers of Justice Mohit S Shah (Retd.), Former Chief Justice of Bombay and Calcutta High Court | AA29: Srivastava & Company | AB29: =VLOOKUP(AA29,AD:AD,1,0) -> Srivastava & Company | AD29: SKR & associates | AE29: =VLOOKUP(AD29,AA:AA,1,0) -> SKR & associates
G30: Saswat Mohanty | H30: =VLOOKUP(G30,J:J,1,0) -> Saswat Mohanty | J30: Megha Chandra | K30: =VLOOKUP(J30,M:M,1,0) -> Megha Chandra | M30: R. Vishnu Kumar, Advocate | N30: =VLOOKUP(M30,P:P,1,0) -> R. Vishnu Kumar, Advocate | P30: Yash Momaya | Q30: =VLOOKUP(P30,S:S,1,0) -> #N/A | S30: Sneha Phene | T30: =VLOOKUP(S30,U:U,1,0) -> Sneha Phene | U30: Mahek Bookwala | V30: =VLOOKUP(U30,X:X,1,0) -> Mahek Bookwala | X30: Chambers of Moazzam Khan | Y30: =VLOOKUP(X30,AA:AA,1,0) -> Chambers of Moazzam Khan | AA30: Piyush Raheja | AB30: =VLOOKUP(AA30,AD:AD,1,0) -> Piyush Raheja | AD30: Srivastava & Company | AE30: =VLOOKUP(AD30,AA:AA,1,0) -> Srivastava & Company
G31: Shiraz Rustomjee | H31: =VLOOKUP(G31,J:J,1,0) -> Shiraz Rustomjee | J31: Monalisa Kosaria | K31: =VLOOKUP(J31,M:M,1,0) -> Monalisa Kosaria | M31: Yash Momaya | N31: =VLOOKUP(M31,P:P,1,0) -> Yash Momaya | P31: Chetan Dedhia | Q31: =VLOOKUP(P31,S:S,1,0) -> Chetan Dedhia | S31: Gunjan Mangla | T31: =VLOOKUP(S31,U:U,1,0) -> Gunjan Mangla | U31: Pradeep Sancheti | V31: =VLOOKUP(U31,X:X,1,0) -> Pradeep Sancheti | X31: Chambers of Ninad Laud | Y31: =VLOOKUP(X31,AA:AA,1,0) -> Chambers of Ninad Laud | AA31: ⁠Feroze Patel | AB31: =VLOOKUP(AA31,AD:AD,1,0) -> ⁠Feroze Patel | AD31: Piyush Raheja | AE31: =VLOOKUP(AD31,AA:AA,1,0) -> Piyush Raheja
G32: Shyam Kapadia | H32: =VLOOKUP(G32,J:J,1,0) -> Shyam Kapadia | J32: Mr Sudhanshu Kumar | K32: =VLOOKUP(J32,M:M,1,0) -> Mr Sudhanshu Kumar | M32: Chetan Dedhia | N32: =VLOOKUP(M32,P:P,1,0) -> Chetan Dedhia | P32: NC Legal | Q32: =VLOOKUP(P32,S:S,1,0) -> NC Legal | S32: Zulfiqar Jariwala | T32: =VLOOKUP(S32,U:U,1,0) -> Zulfiqar Jariwala | U32: AHUJA VALECHA & ASSOCIATES LLP | V32: =VLOOKUP(U32,X:X,1,0) -> AHUJA VALECHA & ASSOCIATES LLP | X32: Chetan Dedhia | Y32: =VLOOKUP(X32,AA:AA,1,0) -> Chetan Dedhia | AA32: Kazan Shroff | AB32: =VLOOKUP(AA32,AD:AD,1,0) -> Kazan Shroff | AD32: ⁠Feroze Patel | AE32: =VLOOKUP(AD32,AA:AA,1,0) -> ⁠Feroze Patel
G33: SRCO Legal / Salvador Raghav & Co. | H33: =VLOOKUP(G33,J:J,1,0) -> SRCO Legal / Salvador Raghav & Co. | J33: Mr. Jehangir Jejeebhoy | K33: =VLOOKUP(J33,M:M,1,0) -> Mr. Jehangir Jejeebhoy | M33: Aakash Sharma | N33: =VLOOKUP(M33,P:P,1,0) -> Aakash Sharma | P33: Aakash Sharma | Q33: =VLOOKUP(P33,S:S,1,0) -> #N/A | S33: Manjari Shah | T33: =VLOOKUP(S33,U:U,1,0) -> Manjari Shah | U33: ICL CORPORATE ADVISORY PRIVATE LIMITED | V33: =VLOOKUP(U33,X:X,1,0) -> ICL CORPORATE ADVISORY PRIVATE LIMITED | X33: Chetan shah | Y33: =VLOOKUP(X33,AA:AA,1,0) -> Chetan shah | AA33: Kajol Punjabi | AB33: =VLOOKUP(AA33,AD:AD,1,0) -> Kajol Punjabi | AD33: Kazan Shroff | AE33: =VLOOKUP(AD33,AA:AA,1,0) -> Kazan Shroff
G34: Venkatesh Dhond | H34: =VLOOKUP(G34,J:J,1,0) -> Venkatesh Dhond | J34: Mustafa S Doctor | K34: =VLOOKUP(J34,M:M,1,0) -> Mustafa S Doctor | M34: Saga Legal | N34: =VLOOKUP(M34,P:P,1,0) -> Saga Legal | P34: Saga Legal | Q34: =VLOOKUP(P34,S:S,1,0) -> #N/A | S34: Sagar Sheth | T34: =VLOOKUP(S34,U:U,1,0) -> Sagar Sheth | U34: Pratik Patnaik | V34: =VLOOKUP(U34,X:X,1,0) -> Pratik Patnaik | X34: Chirag shah, Advocate | Y34: =VLOOKUP(X34,AA:AA,1,0) -> Chirag shah, Advocate | AA34: Neeta Jain | AB34: =VLOOKUP(AA34,AD:AD,1,0) -> Neeta Jain | AD34: Kajol Punjabi | AE34: =VLOOKUP(AD34,AA:AA,1,0) -> Kajol Punjabi
G35: Vesta Legal | H35: =VLOOKUP(G35,J:J,1,0) -> Vesta Legal | J35: MV Law Partners | K35: =VLOOKUP(J35,M:M,1,0) -> MV Law Partners | M35: RPV LEGAL | N35: =VLOOKUP(M35,P:P,1,0) -> RPV LEGAL | P35: RPV LEGAL | Q35: =VLOOKUP(P35,S:S,1,0) -> RPV LEGAL | S35: Mahek Bookwala | T35: =VLOOKUP(S35,U:U,1,0) -> Mahek Bookwala | U35: Saswat Mohanty | V35: =VLOOKUP(U35,X:X,1,0) -> Saswat Mohanty | X35: Clavius Legal | Y35: =VLOOKUP(X35,AA:AA,1,0) -> Clavius Legal | AA35: Amrut Joshi | AB35: =VLOOKUP(AA35,AD:AD,1,0) -> Amrut Joshi | AD35: Neeta Jain | AE35: =VLOOKUP(AD35,AA:AA,1,0) -> Neeta Jain
G36: Victoram Legal / Mr. Sajal Awasthi | H36: =VLOOKUP(G36,J:J,1,0) -> Victoram Legal / Mr. Sajal Awasthi | J36: MZM Legal LLP | K36: =VLOOKUP(J36,M:M,1,0) -> MZM Legal LLP | M36: AP & Partners, Advocates | N36: =VLOOKUP(M36,P:P,1,0) -> AP & Partners, Advocates | P36: AP & Partners, Advocates | Q36: =VLOOKUP(P36,S:S,1,0) -> AP & Partners, Advocates | S36: Pradeep Sancheti | T36: =VLOOKUP(S36,U:U,1,0) -> Pradeep Sancheti | U36: Chambers of Aman Vachher | V36: =VLOOKUP(U36,X:X,1,0) -> Chambers of Aman Vachher | X36: Darius J. Khambata | Y36: =VLOOKUP(X36,AA:AA,1,0) -> Darius J. Khambata | AA36: Gaurav Joshi | AB36: =VLOOKUP(AA36,AD:AD,1,0) -> Gaurav Joshi | AD36: Amrut Joshi | AE36: =VLOOKUP(AD36,AA:AA,1,0) -> Amrut Joshi
J37: Naushad Engineer | K37: =VLOOKUP(J37,M:M,1,0) -> Naushad Engineer | M37: Pranay Chitale | N37: =VLOOKUP(M37,P:P,1,0) -> Pranay Chitale | P37: Pranay Chitale | Q37: =VLOOKUP(P37,S:S,1,0) -> #N/A | S37: AHUJA VALECHA & ASSOCIATES LLP | T37: =VLOOKUP(S37,U:U,1,0) -> AHUJA VALECHA & ASSOCIATES LLP | U37: SK Singhi and Partners | V37: =VLOOKUP(U37,X:X,1,0) -> SK Singhi and Partners | X37: Darshit Jain | Y37: =VLOOKUP(X37,AA:AA,1,0) -> Darshit Jain | AA37: Kamaljeet Singh | AB37: =VLOOKUP(AA37,AD:AD,1,0) -> Kamaljeet Singh | AD37: Gaurav Joshi | AE37: =VLOOKUP(AD37,AA:AA,1,0) -> Gaurav Joshi
J38: NIKHIL DEELIP P | K38: =VLOOKUP(J38,M:M,1,0) -> NIKHIL DEELIP P | M38: Spark Legal | N38: =VLOOKUP(M38,P:P,1,0) -> Spark Legal | P38: Spark Legal | Q38: =VLOOKUP(P38,S:S,1,0) -> #N/A | S38: ICL CORPORATE ADVISORY PRIVATE LIMITED | T38: =VLOOKUP(S38,U:U,1,0) -> ICL CORPORATE ADVISORY PRIVATE LIMITED | U38: SKR & associates | V38: =VLOOKUP(U38,X:X,1,0) -> SKR & associates | X38: Daswani & Daswani | Y38: =VLOOKUP(X38,AA:AA,1,0) -> Daswani & Daswani | AA38: Manish kelker | AB38: =VLOOKUP(AA38,AD:AD,1,0) -> Manish kelker | AD38: Kamaljeet Singh | AE38: =VLOOKUP(AD38,AA:AA,1,0) -> Kamaljeet Singh
J39: Nora Legal Consultants LLP | K39: =VLOOKUP(J39,M:M,1,0) -> Nora Legal Consultants LLP | M39: Bathiya Legal | N39: =VLOOKUP(M39,P:P,1,0) -> Bathiya Legal | P39: Bathiya Legal | Q39: =VLOOKUP(P39,S:S,1,0) -> Bathiya Legal | S39: Pratik Patnaik | T39: =VLOOKUP(S39,U:U,1,0) -> Pratik Patnaik | U39: Srivastava & Company | V39: =VLOOKUP(U39,X:X,1,0) -> Srivastava & Company | X39: Deep Cover Law- Chirag Narasimiah | Y39: =VLOOKUP(X39,AA:AA,1,0) -> #N/A | AA39: Diwan Law Associates | AB39: =VLOOKUP(AA39,AD:AD,1,0) -> Diwan Law Associates | AD39: Manish kelker | AE39: =VLOOKUP(AD39,AA:AA,1,0) -> Manish kelker
J40: Office of ASG (N. Venkatraman) | K40: =VLOOKUP(J40,M:M,1,0) -> Office of ASG (N. Venkatraman) | M40: Justice (Retd.) Kurian Joseph | N40: =VLOOKUP(M40,P:P,1,0) -> Justice (Retd.) Kurian Joseph | P40: Justice (Retd.) Kurian Joseph | Q40: =VLOOKUP(P40,S:S,1,0) -> Justice (Retd.) Kurian Joseph | S40: Saswat Mohanty | T40: =VLOOKUP(S40,U:U,1,0) -> Saswat Mohanty | U40: Piyush Raheja | V40: =VLOOKUP(U40,X:X,1,0) -> Piyush Raheja | X40: Devina Sehgal | Y40: =VLOOKUP(X40,AA:AA,1,0) -> Devina Sehgal | AA40: SRCO Legal / Salvador Raghav & Co. | AB40: =VLOOKUP(AA40,AD:AD,1,0) -> SRCO Legal / Salvador Raghav & Co. | AD40: Diwan Law Associates | AE40: =VLOOKUP(AD40,AA:AA,1,0) -> Diwan Law Associates
J41: Prantar | K41: =VLOOKUP(J41,M:M,1,0) -> Prantar | M41: SINHA & COMPANY | N41: =VLOOKUP(M41,P:P,1,0) -> SINHA & COMPANY | P41: SINHA & COMPANY | Q41: =VLOOKUP(P41,S:S,1,0) -> SINHA & COMPANY | S41: Chambers of Aman Vachher | T41: =VLOOKUP(S41,U:U,1,0) -> Chambers of Aman Vachher | U41: ⁠Feroze Patel | V41: =VLOOKUP(U41,X:X,1,0) -> ⁠Feroze Patel | X41: Dewani Associates | Y41: =VLOOKUP(X41,AA:AA,1,0) -> Dewani Associates | AA41: Kunal Kunango | AB41: =VLOOKUP(AA41,AD:AD,1,0) -> Kunal Kunango | AD41: SRCO Legal / Salvador Raghav & Co. | AE41: =VLOOKUP(AD41,AA:AA,1,0) -> SRCO Legal / Salvador Raghav & Co.
J42: Prompt Legal (Shared by Jayanth) | K42: =VLOOKUP(J42,M:M,1,0) -> Prompt Legal (Shared by Jayanth) | M42: Darshit Jain | N42: =VLOOKUP(M42,P:P,1,0) -> Darshit Jain | P42: Darshit Jain | Q42: =VLOOKUP(P42,S:S,1,0) -> Darshit Jain | S42: SK Singhi and Partners | T42: =VLOOKUP(S42,U:U,1,0) -> SK Singhi and Partners | U42: Kazan Shroff | V42: =VLOOKUP(U42,X:X,1,0) -> Kazan Shroff | X42: Dharma Law Partners | Y42: =VLOOKUP(X42,AA:AA,1,0) -> Dharma Law Partners | AA42: Divyanshu Rai | AB42: =VLOOKUP(AA42,AD:AD,1,0) -> Divyanshu Rai | AD42: Kunal Kunango | AE42: =VLOOKUP(AD42,AA:AA,1,0) -> Kunal Kunango
J43: Ratan Kumar Singh | K43: =VLOOKUP(J43,M:M,1,0) -> Ratan Kumar Singh | M43: Sagar Ghogre | N43: =VLOOKUP(M43,P:P,1,0) -> Sagar Ghogre | P43: Sagar Ghogre | Q43: =VLOOKUP(P43,S:S,1,0) -> Sagar Ghogre | S43: SKR & associates | T43: =VLOOKUP(S43,U:U,1,0) -> SKR & associates | U43: Kajol Punjabi | V43: =VLOOKUP(U43,X:X,1,0) -> Kajol Punjabi | X43: Dhruve Liladhar & Co | Y43: =VLOOKUP(X43,AA:AA,1,0) -> Dhruve Liladhar & Co | AA43: Hamza mir | AB43: =VLOOKUP(AA43,AD:AD,1,0) -> Hamza mir | AD43: Divyanshu Rai | AE43: =VLOOKUP(AD43,AA:AA,1,0) -> Divyanshu Rai
J44: Rohit Sharma (lex Merita) | K44: =VLOOKUP(J44,M:M,1,0) -> Rohit Sharma (lex Merita) | M44: Chetan shah | N44: =VLOOKUP(M44,P:P,1,0) -> Chetan shah | P44: Chetan shah | Q44: =VLOOKUP(P44,S:S,1,0) -> Chetan shah | S44: Srivastava & Company | T44: =VLOOKUP(S44,U:U,1,0) -> Srivastava & Company | U44: Neeta Jain | V44: =VLOOKUP(U44,X:X,1,0) -> Neeta Jain | X44: Dileep Poolakkot | Y44: =VLOOKUP(X44,AA:AA,1,0) -> Dileep Poolakkot | AA44: Chambers of Ninad Laud | AB44: =VLOOKUP(AA44,AD:AD,1,0) -> Chambers of Ninad Laud | AD44: Chambers of Ninad Laud | AE44: =VLOOKUP(AD44,AA:AA,1,0) -> Chambers of Ninad Laud
J45: Sanjay Udeshi & Co. | K45: =VLOOKUP(J45,M:M,1,0) -> Sanjay Udeshi & Co. | M45: Sneha Phene | N45: =VLOOKUP(M45,P:P,1,0) -> Sneha Phene | P45: Sneha Phene | Q45: =VLOOKUP(P45,S:S,1,0) -> Sneha Phene | S45: Piyush Raheja | T45: =VLOOKUP(S45,U:U,1,0) -> Piyush Raheja | U45: Amrut Joshi | V45: =VLOOKUP(U45,X:X,1,0) -> Amrut Joshi | X45: Dipankar Majumdar | Y45: =VLOOKUP(X45,AA:AA,1,0) -> Dipankar Majumdar | AA45: Kachwaha & Partners | AB45: =VLOOKUP(AA45,AD:AD,1,0) -> Kachwaha & Partners | AD45: Kachwaha & Partners | AE45: =VLOOKUP(AD45,AA:AA,1,0) -> Kachwaha & Partners
J46: Santosh Kumar | K46: =VLOOKUP(J46,M:M,1,0) -> Santosh Kumar | M46: Gunjan Mangla | N46: =VLOOKUP(M46,P:P,1,0) -> Gunjan Mangla | P46: Gunjan Mangla | Q46: =VLOOKUP(P46,S:S,1,0) -> Gunjan Mangla | S46: ⁠Feroze Patel | T46: =VLOOKUP(S46,U:U,1,0) -> ⁠Feroze Patel | U46: Gaurav Joshi | V46: =VLOOKUP(U46,X:X,1,0) -> Gaurav Joshi | X46: Divyanshu Rai | Y46: =VLOOKUP(X46,AA:AA,1,0) -> Divyanshu Rai | AA46: Chambers of Moazzam Khan | AB46: =VLOOKUP(AA46,AD:AD,1,0) -> Chambers of Moazzam Khan | AD46: Chambers of Moazzam Khan | AE46: =VLOOKUP(AD46,AA:AA,1,0) -> Chambers of Moazzam Khan
J47: Saswat Mohanty | K47: =VLOOKUP(J47,M:M,1,0) -> Saswat Mohanty | M47: Zulfiqar Jariwala | N47: =VLOOKUP(M47,P:P,1,0) -> Zulfiqar Jariwala | P47: Zulfiqar Jariwala | Q47: =VLOOKUP(P47,S:S,1,0) -> Zulfiqar Jariwala | S47: Kazan Shroff | T47: =VLOOKUP(S47,U:U,1,0) -> Kazan Shroff | U47: Kamaljeet Singh | V47: =VLOOKUP(U47,X:X,1,0) -> Kamaljeet Singh | X47: Diwan Law Associates | Y47: =VLOOKUP(X47,AA:AA,1,0) -> Diwan Law Associates | AA47: Nikhil Pai | AB47: =VLOOKUP(AA47,AD:AD,1,0) -> Nikhil Pai | AD47: Nikhil Pai | AE47: =VLOOKUP(AD47,AA:AA,1,0) -> Nikhil Pai
J48: Shiraz Rustomjee | K48: =VLOOKUP(J48,M:M,1,0) -> Shiraz Rustomjee | M48: Manjari Shah | N48: =VLOOKUP(M48,P:P,1,0) -> Manjari Shah | P48: Manjari Shah | Q48: =VLOOKUP(P48,S:S,1,0) -> Manjari Shah | S48: Kajol Punjabi | T48: =VLOOKUP(S48,U:U,1,0) -> Kajol Punjabi | U48: Manish kelker | V48: =VLOOKUP(U48,X:X,1,0) -> Manish kelker | X48: Ecclesia Advocates and Solicitors | Y48: =VLOOKUP(X48,AA:AA,1,0) -> Ecclesia Advocates and Solicitors | AA48: Vesta Legal | AB48: =VLOOKUP(AA48,AD:AD,1,0) -> #N/A | AD48: Vyom Shah | AE48: =VLOOKUP(AD48,AA:AA,1,0) -> Vyom Shah
... J58: Yash Momaya | K58: =VLOOKUP(J58,M:M,1,0) -> Yash Momaya | M58: SK Singhi and Partners | N58: =VLOOKUP(M58,P:P,1,0) -> SK Singhi and Partners | P58: SK Singhi and Partners | Q58: =VLOOKUP(P58,S:S,1,0) -> SK Singhi and Partners | S58: Gupta Law Associates | T58: =VLOOKUP(S58,U:U,1,0) -> Gupta Law Associates | U58: Chambers of Moazzam Khan | V58: =VLOOKUP(U58,X:X,1,0) -> Chambers of Moazzam Khan | X58: Gaurav Ray, Advocate on Record | Y58: =VLOOKUP(X58,AA:AA,1,0) -> Gaurav Ray, Advocate on Record | AA58: Nitish Raj | AB58: =VLOOKUP(AA58,AD:AD,1,0) -> Nitish Raj | AD58: Daswani & Daswani | AE58: =VLOOKUP(AD58,AA:AA,1,0) -> Daswani & Daswani
M59: Centre for Law and Policy Research Trust | N59: =VLOOKUP(M59,P:P,1,0) -> Centre for Law and Policy Research Trust | P59: Centre for Law and Policy Research Trust | Q59: =VLOOKUP(P59,S:S,1,0) -> Centre for Law and Policy Research Trust | S59: Kunal Kunango | T59: =VLOOKUP(S59,U:U,1,0) -> Kunal Kunango | U59: Phoenix Legal | V59: =VLOOKUP(U59,X:X,1,0) -> Phoenix Legal | X59: Gauri Puri | Y59: =VLOOKUP(X59,AA:AA,1,0) -> Gauri Puri | AA59: Daswani & Daswani | AB59: =VLOOKUP(AA59,AD:AD,1,0) -> Daswani & Daswani | AD59: Samya Law Chambers | AE59: =VLOOKUP(AD59,AA:AA,1,0) -> Samya Law Chambers
M60: SKR & associates | N60: =VLOOKUP(M60,P:P,1,0) -> SKR & associates | P60: SKR & associates | Q60: =VLOOKUP(P60,S:S,1,0) -> SKR & associates | S60: Divyanshu Rai | T60: =VLOOKUP(S60,U:U,1,0) -> Divyanshu Rai | U60: Nikhil Pai | V60: =VLOOKUP(U60,X:X,1,0) -> Nikhil Pai | X60: GC Legal | Y60: =VLOOKUP(X60,AA:AA,1,0) -> GC Legal | AA60: Samya Law Chambers | AB60: =VLOOKUP(AA60,AD:AD,1,0) -> Samya Law Chambers | AD60: Shri Venkatesh , SKV law offices | AE60: =VLOOKUP(AD60,AA:AA,1,0) -> Shri Venkatesh , SKV law offices
M61: Srivastava & Company | N61: =VLOOKUP(M61,P:P,1,0) -> Srivastava & Company | P61: Srivastava & Company | Q61: =VLOOKUP(P61,S:S,1,0) -> Srivastava & Company | S61: Hamza mir | T61: =VLOOKUP(S61,U:U,1,0) -> Hamza mir | U61: Vesta Legal | V61: =VLOOKUP(U61,X:X,1,0) -> Vesta Legal | X61: Giriraj Subramanium | Y61: =VLOOKUP(X61,AA:AA,1,0) -> Giriraj Subramanium | AA61: Shri Venkatesh , SKV law offices | AB61: =VLOOKUP(AA61,AD:AD,1,0) -> Shri Venkatesh , SKV law offices | AD61: IndusLaw | AE61: =VLOOKUP(AD61,AA:AA,1,0) -> IndusLaw
M62: Piyush Raheja | N62: =VLOOKUP(M62,P:P,1,0) -> Piyush Raheja | P62: Piyush Raheja | Q62: =VLOOKUP(P62,S:S,1,0) -> Piyush Raheja | S62: Chambers of Ninad Laud | T62: =VLOOKUP(S62,U:U,1,0) -> Chambers of Ninad Laud | U62: Vyom Shah | V62: =VLOOKUP(U62,X:X,1,0) -> Vyom Shah | X62: GM Legal | Y62: =VLOOKUP(X62,AA:AA,1,0) -> GM Legal | AA62: IndusLaw | AB62: =VLOOKUP(AA62,AD:AD,1,0) -> IndusLaw | AD62: Keystone Partners | AE62: =VLOOKUP(AD62,AA:AA,1,0) -> Keystone Partners
M63: ⁠Feroze Patel | N63: =VLOOKUP(M63,P:P,1,0) -> ⁠Feroze Patel | P63: ⁠Feroze Patel | Q63: =VLOOKUP(P63,S:S,1,0) -> ⁠Feroze Patel | S63: Gera Developments Pvt. Ltd. | T63: =VLOOKUP(S63,U:U,1,0) -> #N/A | U63: Zubin Behramkamdin | V63: =VLOOKUP(U63,X:X,1,0) -> Zubin Behramkamdin | X63: Gourab Banreji | Y63: =VLOOKUP(X63,AA:AA,1,0) -> Gourab Banreji | AA63: Keystone Partners | AB63: =VLOOKUP(AA63,AD:AD,1,0) -> Keystone Partners | AD63: Prompt Legal (Shared by Jayanth) | AE63: =VLOOKUP(AD63,AA:AA,1,0) -> Prompt Legal (Shared by Jayanth)
M64: Kazan Shroff | N64: =VLOOKUP(M64,P:P,1,0) -> Kazan Shroff | P64: Kazan Shroff | Q64: =VLOOKUP(P64,S:S,1,0) -> Kazan Shroff | S64: Gaurav Mehta | T64: =VLOOKUP(S64,U:U,1,0) -> Gaurav Mehta | U64: Jennifer Michael | V64: =VLOOKUP(U64,X:X,1,0) -> Jennifer Michael | X64: Gunjan Mangla | Y64: =VLOOKUP(X64,AA:AA,1,0) -> Gunjan Mangla | AA64: Prompt Legal (Shared by Jayanth) | AB64: =VLOOKUP(AA64,AD:AD,1,0) -> Prompt Legal (Shared by Jayanth) | AD64: Justice (Retd.) AK Sikri | AE64: =VLOOKUP(AD64,AA:AA,1,0) -> Justice (Retd.) AK Sikri
M65: Kajol Punjabi | N65: =VLOOKUP(M65,P:P,1,0) -> Kajol Punjabi | P65: Kajol Punjabi | Q65: =VLOOKUP(P65,S:S,1,0) -> Kajol Punjabi | S65: MD&T Partners | T65: =VLOOKUP(S65,U:U,1,0) -> #N/A | U65: SomÂ Sinha & Associates | V65: =VLOOKUP(U65,X:X,1,0) -> SomÂ Sinha & Associates | X65: Gupta Law Associates | Y65: =VLOOKUP(X65,AA:AA,1,0) -> Gupta Law Associates | AA65: Justice (Retd.) AK Sikri | AB65: =VLOOKUP(AA65,AD:AD,1,0) -> Justice (Retd.) AK Sikri | AD65: Amrita Panda / ADP Chambers- 62 | AE65: =VLOOKUP(AD65,AA:AA,1,0) -> Amrita Panda / ADP Chambers- 62
M66: Neeta Jain | N66: =VLOOKUP(M66,P:P,1,0) -> Neeta Jain | P66: Neeta Jain | Q66: =VLOOKUP(P66,S:S,1,0) -> Neeta Jain | S66: Kachwaha & Partners | T66: =VLOOKUP(S66,U:U,1,0) -> Kachwaha & Partners | U66: MZM Legal LLP | V66: =VLOOKUP(U66,X:X,1,0) -> MZM Legal LLP | X66: Hamsaanandini Nanduri | Y66: =VLOOKUP(X66,AA:AA,1,0) -> Hamsaanandini Nanduri | AA66: Amrita Panda / ADP Chambers- 62 | AB66: =VLOOKUP(AA66,AD:AD,1,0) -> Amrita Panda / ADP Chambers- 62 | AD66: Akshat Vachher | AE66: =VLOOKUP(AD66,AA:AA,1,0) -> #N/A
M67: Amrut Joshi | N67: =VLOOKUP(M67,P:P,1,0) -> Amrut Joshi | P67: Amrut Joshi | Q67: =VLOOKUP(P67,S:S,1,0) -> Amrut Joshi | S67: Vishal Kanade | T67: =VLOOKUP(S67,U:U,1,0) -> Vishal Kanade | U67: Stride Legal | V67: =VLOOKUP(U67,X:X,1,0) -> Stride Legal | X67: Hamza mir | Y67: =VLOOKUP(X67,AA:AA,1,0) -> Hamza mir | AA67: Chambers of Justice Mohit S Shah (Retd.), Former Chief Justice of Bombay and Calcutta High Court | AB67: =VLOOKUP(AA67,AD:AD,1,0) -> Chambers of Justice Mohit S Shah (Retd.), Former Chief Justice of Bombay and Calcutta High Court | AD67: Chambers of Justice Mohit S Shah (Retd.), Former Chief Justice of Bombay and Calcutta High Court | AE67: =VLOOKUP(AD67,AA:AA,1,0) -> Chambers of Justice Mohit S Shah (Retd.), Former Chief Justice of Bombay and Calcutta High Court
M68: Gaurav Joshi | N68: =VLOOKUP(M68,P:P,1,0) -> Gaurav Joshi | P68: Gaurav Joshi | Q68: =VLOOKUP(P68,S:S,1,0) -> Gaurav Joshi | S68: Vritti Law Partners | T68: =VLOOKUP(S68,U:U,1,0) -> #N/A | U68: Chetan Dedhia | V68: =VLOOKUP(U68,X:X,1,0) -> Chetan Dedhia | X68: Harshit Malik | Y68: =VLOOKUP(X68,AA:AA,1,0) -> Harshit Malik | AA68: Wadia Ghandy & Co. | AB68: =VLOOKUP(AA68,AD:AD,1,0) -> Wadia Ghandy & Co. | AD68: Wadia Ghandy & Co. | AE68: =VLOOKUP(AD68,AA:AA,1,0) -> Wadia Ghandy & Co.
M69: Kamaljeet Singh | N69: =VLOOKUP(M69,P:P,1,0) -> Kamaljeet Singh | P69: Kamaljeet Singh | Q69: =VLOOKUP(P69,S:S,1,0) -> Kamaljeet Singh | S69: C&S Partners | T69: =VLOOKUP(S69,U:U,1,0) -> C&S Partners | U69: Zoheb Hossain | V69: =VLOOKUP(U69,X:X,1,0) -> Zoheb Hossain | X69: ICL CORPORATE ADVISORY PRIVATE LIMITED | Y69: =VLOOKUP(X69,AA:AA,1,0) -> ICL CORPORATE ADVISORY PRIVATE LIMITED | AA69: Eternity Legal | AB69: =VLOOKUP(AA69,AD:AD,1,0) -> Eternity Legal | AD69: Eternity Legal | AE69: =VLOOKUP(AD69,AA:AA,1,0) -> Eternity Legal
M70: Pioneer Legal | N70: =VLOOKUP(M70,P:P,1,0) -> Pioneer Legal | P70: Saraf and Partners | Q70: =VLOOKUP(P70,S:S,1,0) -> #N/A | S70: Asahi Legal LLP | T70: =VLOOKUP(S70,U:U,1,0) -> Asahi Legal LLP | U70: Meghav Gupta | V70: =VLOOKUP(U70,X:X,1,0) -> Meghav Gupta | X70: IndusLaw | Y70: =VLOOKUP(X70,AA:AA,1,0) -> IndusLaw | AA70: Nora Legal Consultants LLP | AB70: =VLOOKUP(AA70,AD:AD,1,0) -> Nora Legal Consultants LLP | AD70: Nora Legal Consultants LLP | AE70: =VLOOKUP(AD70,AA:AA,1,0) -> Nora Legal Consultants LLP
... M118: Monalisa Kosaria | N118: =VLOOKUP(M118,P:P,1,0) -> Monalisa Kosaria | P118: Wadia Ghandy & Co. | Q118: =VLOOKUP(P118,S:S,1,0) -> Wadia Ghandy & Co. | S118: Naushad Engineer | T118: =VLOOKUP(S118,U:U,1,0) -> Naushad Engineer | U118: Agraa Legal | V118: =VLOOKUP(U118,X:X,1,0) -> Agraa Legal | X118: MZM Legal LLP | Y118: =VLOOKUP(X118,AA:AA,1,0) -> MZM Legal LLP | AA118: Swapnil Wagh | AB118: =VLOOKUP(AA118,AD:AD,1,0) -> Swapnil Wagh | AD118: Swapnil Wagh | AE118: =VLOOKUP(AD118,AA:AA,1,0) -> Swapnil Wagh
P119: Burgeon Law LLP | Q119: =VLOOKUP(P119,S:S,1,0) -> Burgeon Law LLP | S119: Shyam Kapadia | T119: =VLOOKUP(S119,U:U,1,0) -> Shyam Kapadia | U119: KINJAL CIVILCON LLP | V119: =VLOOKUP(U119,X:X,1,0) -> #N/A | X119: Narottam Sharma | Y119: =VLOOKUP(X119,AA:AA,1,0) -> Narottam Sharma | AA119: Arpit Gupta | AB119: =VLOOKUP(AA119,AD:AD,1,0) -> Arpit Gupta | AD119: Arpit Gupta | AE119: =VLOOKUP(AD119,AA:AA,1,0) -> Arpit Gupta
P120: Eternity Legal | Q120: =VLOOKUP(P120,S:S,1,0) -> Eternity Legal | S120: Tvashta Law | T120: =VLOOKUP(S120,U:U,1,0) -> Tvashta Law | U120: Shobit Phutela | V120: =VLOOKUP(U120,X:X,1,0) -> Shobit Phutela | X120: Naushad Engineer | Y120: =VLOOKUP(X120,AA:AA,1,0) -> Naushad Engineer | AA120: Poovayya & CO | AB120: =VLOOKUP(AA120,AD:AD,1,0) -> Poovayya & CO | AD120: Poovayya & CO | AE120: =VLOOKUP(AD120,AA:AA,1,0) -> Poovayya & CO
P121: Nora Legal Consultants LLP | Q121: =VLOOKUP(P121,S:S,1,0) -> Nora Legal Consultants LLP | S121: Ish Jain / Regius Partners LLP | T121: =VLOOKUP(S121,U:U,1,0) -> Ish Jain / Regius Partners LLP | U121: Narottam Sharma | V121: =VLOOKUP(U121,X:X,1,0) -> Narottam Sharma | X121: Nayana Tara BG | Y121: =VLOOKUP(X121,AA:AA,1,0) -> Nayana Tara BG | AA121: J INFRATECH LIMITED | AB121: =VLOOKUP(AA121,AD:AD,1,0) -> J INFRATECH LIMITED | AD121: J INFRATECH LIMITED | AE121: =VLOOKUP(AD121,AA:AA,1,0) -> J INFRATECH LIMITED
P122: Innovatus Law | Q122: =VLOOKUP(P122,S:S,1,0) -> Innovatus Law | S122: The Guild | Advocates & Associate Counsel | T122: =VLOOKUP(S122,U:U,1,0) -> The Guild | Advocates & Associate Counsel | U122: Rahul Saboo, Advocate | V122: =VLOOKUP(U122,X:X,1,0) -> Rahul Saboo, Advocate | X122: NC Legal | Y122: =VLOOKUP(X122,AA:AA,1,0) -> NC Legal | AA122: Rohan Shah | AB122: =VLOOKUP(AA122,AD:AD,1,0) -> Rohan Shah | AD122: Rohan Shah | AE122: =VLOOKUP(AD122,AA:AA,1,0) -> Rohan Shah
P123: Gourab Banreji | Q123: =VLOOKUP(P123,S:S,1,0) -> Gourab Banreji | S123: Abhimanyu Garg / Methodica Legal | T123: =VLOOKUP(S123,U:U,1,0) -> Abhimanyu Garg / Methodica Legal | U123: DSK Legal | V123: =VLOOKUP(U123,X:X,1,0) -> #N/A | X123: Neeta Jain | Y123: =VLOOKUP(X123,AA:AA,1,0) -> Neeta Jain | AA123: GM Legal | AB123: =VLOOKUP(AA123,AD:AD,1,0) -> GM Legal | AD123: GM Legal | AE123: =VLOOKUP(AD123,AA:AA,1,0) -> GM Legal
P124: Solaris Legal | Q124: =VLOOKUP(P124,S:S,1,0) -> #N/A | S124: Megha Chandra | T124: =VLOOKUP(S124,U:U,1,0) -> Megha Chandra | U124: RAJANI ASSOCIATES | V124: =VLOOKUP(U124,X:X,1,0) -> RAJANI ASSOCIATES | X124: Nikhil Pai | Y124: =VLOOKUP(X124,AA:AA,1,0) -> Nikhil Pai | AA124: S Priya | AB124: =VLOOKUP(AA124,AD:AD,1,0) -> S Priya | AD124: S Priya | AE124: =VLOOKUP(AD124,AA:AA,1,0) -> S Priya
P125: MV Law Partners | Q125: =VLOOKUP(P125,S:S,1,0) -> MV Law Partners | S125: Shiraz Rustomjee | T125: =VLOOKUP(S125,U:U,1,0) -> Shiraz Rustomjee | U125: Meghna Talwar | V125: =VLOOKUP(U125,X:X,1,0) -> Meghna Talwar | X125: Nitish Raj | Y125: =VLOOKUP(X125,AA:AA,1,0) -> Nitish Raj | AA125: Ujjwal Sharma | AB125: =VLOOKUP(AA125,AD:AD,1,0) -> Ujjwal Sharma | AD125: Ujjwal Sharma | AE125: =VLOOKUP(AD125,AA:AA,1,0) -> Ujjwal Sharma
P126: Ratan Kumar Singh | Q126: =VLOOKUP(P126,S:S,1,0) -> Ratan Kumar Singh | S126: Dipankar Majumdar | T126: =VLOOKUP(S126,U:U,1,0) -> Dipankar Majumdar | U126: S Priya | V126: =VLOOKUP(U126,X:X,1,0) -> S Priya | X126: NKR Law Offices | Y126: =VLOOKUP(X126,AA:AA,1,0) -> NKR Law Offices | AA126: Trust Law | AB126: =VLOOKUP(AA126,AD:AD,1,0) -> Trust Law | AD126: Trust Law | AE126: =VLOOKUP(AD126,AA:AA,1,0) -> Trust Law
P127: Mr Rohit Gupta | Q127: =VLOOKUP(P127,S:S,1,0) -> Mr Rohit Gupta | S127: Office of ASG (N. Venkatraman) | T127: =VLOOKUP(S127,U:U,1,0) -> Office of ASG (N. Venkatraman) | U127: Joy Baxi & Associates | V127: =VLOOKUP(U127,X:X,1,0) -> Joy Baxi & Associates | X127: Nora Legal Consultants LLP | Y127: =VLOOKUP(X127,AA:AA,1,0) -> Nora Legal Consultants LLP | AA127: Priyanshi Kholia | AB127: =VLOOKUP(AA127,AD:AD,1,0) -> Priyanshi Kholia | AD127: Priyanshi Kholia | AE127: =VLOOKUP(AD127,AA:AA,1,0) -> Priyanshi Kholia
P128: Sanjay Udeshi & Co. | Q128: =VLOOKUP(P128,S:S,1,0) -> Sanjay Udeshi & Co. | S128: LEGALOGIC CONSULTING LLP | T128: =VLOOKUP(S128,U:U,1,0) -> LEGALOGIC CONSULTING LLP | U128: Dewani Associates | V128: =VLOOKUP(U128,X:X,1,0) -> Dewani Associates | X128: Office of ASG (N. Venkatraman) | Y128: =VLOOKUP(X128,AA:AA,1,0) -> Office of ASG (N. Venkatraman) | AA128: Bishwajit Dubey | AB128: =VLOOKUP(AA128,AD:AD,1,0) -> Bishwajit Dubey | AD128: Bishwajit Dubey | AE128: =VLOOKUP(AD128,AA:AA,1,0) -> Bishwajit Dubey
P129: Abel Tom Benny // Thomas and Thomas Advocates | Q129: =VLOOKUP(P129,S:S,1,0) -> Abel Tom Benny // Thomas and Thomas Advocates | S129: Poovayya & CO | T129: =VLOOKUP(S129,U:U,1,0) -> Poovayya & CO | U129: Ganesh & Co. | V129: =VLOOKUP(U129,X:X,1,0) -> Ganesh & Co. | X129: Parakram Legal | Y129: =VLOOKUP(X129,AA:AA,1,0) -> #N/A | AA129: Krati Gupta | AB129: =VLOOKUP(AA129,AD:AD,1,0) -> Krati Gupta | AD129: Krati Gupta | AE129: =VLOOKUP(AD129,AA:AA,1,0) -> Krati Gupta
P130: Farhan Dubash | Q130: =VLOOKUP(P130,S:S,1,0) -> Farhan Dubash | S130: Sajan Poovayya | T130: =VLOOKUP(S130,U:U,1,0) -> Sajan Poovayya | U130: AMS Legal | V130: =VLOOKUP(U130,X:X,1,0) -> #N/A | X130: Parinam Law Associates | Y130: =VLOOKUP(X130,AA:AA,1,0) -> #N/A | AA130: Hamsaanandini Nanduri | AB130: =VLOOKUP(AA130,AD:AD,1,0) -> Hamsaanandini Nanduri | AD130: Hamsaanandini Nanduri | AE130: =VLOOKUP(AD130,AA:AA,1,0) -> Hamsaanandini Nanduri
... P144: Shrey Lodha | Q144: =VLOOKUP(P144,S:S,1,0) -> Shrey Lodha | S144: DSK Legal | T144: =VLOOKUP(S144,U:U,1,0) -> DSK Legal | U144: Harshit Malik | V144: =VLOOKUP(U144,X:X,1,0) -> Harshit Malik | X144: R. Vishnu Kumar, Advocate | Y144: =VLOOKUP(X144,AA:AA,1,0) -> R. Vishnu Kumar, Advocate | AA144: Sarthak Advocates & Solicitors | AB144: =VLOOKUP(AA144,AD:AD,1,0) -> Sarthak Advocates & Solicitors | AD144: Sarthak Advocates & Solicitors | AE144: =VLOOKUP(AD144,AA:AA,1,0) -> Sarthak Advocates & Solicitors
S145: RAJANI ASSOCIATES | T145: =VLOOKUP(S145,U:U,1,0) -> RAJANI ASSOCIATES | U145: Shrey Lodha | V145: =VLOOKUP(U145,X:X,1,0) -> #N/A | X145: Rahul Saboo, Advocate | Y145: =VLOOKUP(X145,AA:AA,1,0) -> Rahul Saboo, Advocate | AA145: LEGALOGIC CONSULTING LLP | AB145: =VLOOKUP(AA145,AD:AD,1,0) -> LEGALOGIC CONSULTING LLP | AD145: LEGALOGIC CONSULTING LLP | AE145: =VLOOKUP(AD145,AA:AA,1,0) -> LEGALOGIC CONSULTING LLP
S146: Meghna Talwar | T146: =VLOOKUP(S146,U:U,1,0) -> Meghna Talwar | U146: Solaris Legal | V146: =VLOOKUP(U146,X:X,1,0) -> Solaris Legal | X146: RAJANI ASSOCIATES | Y146: =VLOOKUP(X146,AA:AA,1,0) -> RAJANI ASSOCIATES | AA146: ASV Legal LLP | AB146: =VLOOKUP(AA146,AD:AD,1,0) -> ASV Legal LLP | AD146: ASV Legal LLP | AE146: =VLOOKUP(AD146,AA:AA,1,0) -> ASV Legal LLP
S147: S Priya | T147: =VLOOKUP(S147,U:U,1,0) -> S Priya | U147: Surel Shah | V147: =VLOOKUP(U147,X:X,1,0) -> Surel Shah | X147: Rajeev K. Virmani | Y147: =VLOOKUP(X147,AA:AA,1,0) -> #N/A | AA147: Tarun G Reddy | AB147: =VLOOKUP(AA147,AD:AD,1,0) -> Tarun G Reddy | AD147: Tarun G Reddy | AE147: =VLOOKUP(AD147,AA:AA,1,0) -> Tarun G Reddy
S148: Joy Baxi & Associates | T148: =VLOOKUP(S148,U:U,1,0) -> Joy Baxi & Associates | U148: MG Ramachandran | V148: =VLOOKUP(U148,X:X,1,0) -> MG Ramachandran | X148: Rashmikant and Partners | Y148: =VLOOKUP(X148,AA:AA,1,0) -> Rashmikant and Partners | AA148: Karanjawala & Company Advocates | AB148: =VLOOKUP(AA148,AD:AD,1,0) -> #N/A | AD148: Swapna Sheshadri | AE148: =VLOOKUP(AD148,AA:AA,1,0) -> Swapna Sheshadri
S149: Ganesh & Co. | T149: =VLOOKUP(S149,U:U,1,0) -> Ganesh & Co. | U149: Jade Lex Partners | V149: =VLOOKUP(U149,X:X,1,0) -> Jade Lex Partners | X149: Ratan Kumar Singh | Y149: =VLOOKUP(X149,AA:AA,1,0) -> Ratan Kumar Singh | AA149: Swapna Sheshadri | AB149: =VLOOKUP(AA149,AD:AD,1,0) -> Swapna Sheshadri | AD149: Krishna Dev Jagarlamudi | AE149: =VLOOKUP(AD149,AA:AA,1,0) -> Krishna Dev Jagarlamudi
S150: AMS Legal | T150: =VLOOKUP(S150,U:U,1,0) -> AMS Legal | U150: Aanchal Basur | V150: =VLOOKUP(U150,X:X,1,0) -> Aanchal Basur | X150: Reliance Corporate Advisors (R) | Y150: =VLOOKUP(X150,AA:AA,1,0) -> Reliance Corporate Advisors (R) | AA150: Krishna Dev Jagarlamudi | AB150: =VLOOKUP(AA150,AD:AD,1,0) -> Krishna Dev Jagarlamudi | AD150: Gaurav Ray, Advocate on Record | AE150: =VLOOKUP(AD150,AA:AA,1,0) -> Gaurav Ray, Advocate on Record
S151: Gauri Puri | T151: =VLOOKUP(S151,U:U,1,0) -> Gauri Puri | U151: RUNWAL ENTERPRISES LIMITED | V151: =VLOOKUP(U151,X:X,1,0) -> RUNWAL ENTERPRISES LIMITED | X151: RHP Partners | Y151: =VLOOKUP(X151,AA:AA,1,0) -> RHP Partners | AA151: Gaurav Ray, Advocate on Record | AB151: =VLOOKUP(AA151,AD:AD,1,0) -> Gaurav Ray, Advocate on Record | AD151: Dhruve Liladhar & Co | AE151: =VLOOKUP(AD151,AA:AA,1,0) -> Dhruve Liladhar & Co
S152: Amit Bhagat | T152: =VLOOKUP(S152,U:U,1,0) -> Amit Bhagat | U152: ANM Global Inc | V152: =VLOOKUP(U152,X:X,1,0) -> ANM Global Inc | X152: Rithin Rai | Y152: =VLOOKUP(X152,AA:AA,1,0) -> #N/A | AA152: Dhruve Liladhar & Co | AB152: =VLOOKUP(AA152,AD:AD,1,0) -> Dhruve Liladhar & Co | AD152: R. Ginodia & Co. LLP | AE152: =VLOOKUP(AD152,AA:AA,1,0) -> R. Ginodia & Co. LLP
S153: Sundeep Karnik | T153: =VLOOKUP(S153,U:U,1,0) -> Sundeep Karnik | U153: NKR Law Offices | V153: =VLOOKUP(U153,X:X,1,0) -> NKR Law Offices | X153: Rohan Shah | Y153: =VLOOKUP(X153,AA:AA,1,0) -> Rohan Shah | AA153: R. Ginodia & Co. LLP | AB153: =VLOOKUP(AA153,AD:AD,1,0) -> R. Ginodia & Co. LLP | AD153: Saurabh Prakash | AE153: =VLOOKUP(AD153,AA:AA,1,0) -> Saurabh Prakash
S154: Rohan Talwar | T154: =VLOOKUP(S154,U:U,1,0) -> Rohan Talwar | U154: C&S Partners | V154: =VLOOKUP(U154,X:X,1,0) -> #N/A | X154: Rohan Talwar | Y154: =VLOOKUP(X154,AA:AA,1,0) -> Rohan Talwar | AA154: Saurabh Prakash | AB154: =VLOOKUP(AA154,AD:AD,1,0) -> Saurabh Prakash | AD154: Ecclesia Advocates and Solicitors | AE154: =VLOOKUP(AD154,AA:AA,1,0) -> Ecclesia Advocates and Solicitors
S155: Aurtus Consulting LLP | T155: =VLOOKUP(S155,U:U,1,0) -> Aurtus Consulting LLP | U155: Vikas Mehta | V155: =VLOOKUP(U155,X:X,1,0) -> Vikas Mehta | X155: Roshan Santhalia | Y155: =VLOOKUP(X155,AA:AA,1,0) -> Roshan Santhalia | AA155: Ecclesia Advocates and Solicitors | AB155: =VLOOKUP(AA155,AD:AD,1,0) -> Ecclesia Advocates and Solicitors | AD155: Touchstone Partners | AE155: =VLOOKUP(AD155,AA:AA,1,0) -> Touchstone Partners
S156: Tejeshwar Singh | T156: =VLOOKUP(S156,U:U,1,0) -> Tejeshwar Singh | U156: Swapnil Wagh | V156: =VLOOKUP(U156,X:X,1,0) -> Swapnil Wagh | X156: RPV LEGAL | Y156: =VLOOKUP(X156,AA:AA,1,0) -> RPV LEGAL | AA156: Touchstone Partners | AB156: =VLOOKUP(AA156,AD:AD,1,0) -> Touchstone Partners | AD156: Jaiveer Shergil | AE156: =VLOOKUP(AD156,AA:AA,1,0) -> Jaiveer Shergil
... S159: Shrey Lodha | T159: =VLOOKUP(S159,U:U,1,0) -> Shrey Lodha | U159: J INFRATECH LIMITED | V159: =VLOOKUP(U159,X:X,1,0) -> J INFRATECH LIMITED | X159: S Priya | Y159: =VLOOKUP(X159,AA:AA,1,0) -> S Priya | AA159: Mukul Sharma and Company | AB159: =VLOOKUP(AA159,AD:AD,1,0) -> Mukul Sharma and Company | AD159: Brijesh Oberoi | AE159: =VLOOKUP(AD159,AA:AA,1,0) -> Brijesh Oberoi
U160: Rohan Shah | V160: =VLOOKUP(U160,X:X,1,0) -> Rohan Shah | X160: SAGA LEGAL | Y160: =VLOOKUP(X160,AA:AA,1,0) -> SAGA LEGAL | AA160: AHUJA VALECHA & ASSOCIATES LLP | AB160: =VLOOKUP(AA160,AD:AD,1,0) -> AHUJA VALECHA & ASSOCIATES LLP | AD160: Tipping Mr Pink Private Limited | AE160: =VLOOKUP(AD160,AA:AA,1,0) -> Tipping Mr Pink Private Limited
U161: GM Legal | V161: =VLOOKUP(U161,X:X,1,0) -> GM Legal | X161: Sagar Ghogre | Y161: =VLOOKUP(X161,AA:AA,1,0) -> Sagar Ghogre | AA161: Brijesh Oberoi | AB161: =VLOOKUP(AA161,AD:AD,1,0) -> Brijesh Oberoi | AD161: Pranav Badheka | AE161: =VLOOKUP(AD161,AA:AA,1,0) -> Pranav Badheka
U162: Rajeev K. Virmani | V162: =VLOOKUP(U162,X:X,1,0) -> Rajeev K. Virmani | X162: Sagar Sheth | Y162: =VLOOKUP(X162,AA:AA,1,0) -> Sagar Sheth | AA162: Tipping Mr Pink Private Limited | AB162: =VLOOKUP(AA162,AD:AD,1,0) -> Tipping Mr Pink Private Limited | AD162: TRILOK POWER AND CABLES PRIVATE LIMITED | AE162: =VLOOKUP(AD162,AA:AA,1,0) -> TRILOK POWER AND CABLES PRIVATE LIMITED
U163: Vaish Associates | V163: =VLOOKUP(U163,X:X,1,0) -> Vaish Associates | X163: Samya Law Chambers | Y163: =VLOOKUP(X163,AA:AA,1,0) -> Samya Law Chambers | AA163: Pranav Badheka | AB163: =VLOOKUP(AA163,AD:AD,1,0) -> Pranav Badheka | AD163: Saraf and Partners | AE163: =VLOOKUP(AD163,AA:AA,1,0) -> Saraf and Partners
U164: Acuity Law LLP | V164: =VLOOKUP(U164,X:X,1,0) -> Acuity Law LLP | X164: Sanjay Udeshi & Co. | Y164: =VLOOKUP(X164,AA:AA,1,0) -> Sanjay Udeshi & Co. | AA164: TRILOK POWER AND CABLES PRIVATE LIMITED | AB164: =VLOOKUP(AA164,AD:AD,1,0) -> TRILOK POWER AND CABLES PRIVATE LIMITED | AD164: Chirag shah, Advocate | AE164: =VLOOKUP(AD164,AA:AA,1,0) -> Chirag shah, Advocate
U165: Trust Law | V165: =VLOOKUP(U165,X:X,1,0) -> Trust Law | X165: Saraf and Partners | Y165: =VLOOKUP(X165,AA:AA,1,0) -> Saraf and Partners | AA165: Saraf and Partners | AB165: =VLOOKUP(AA165,AD:AD,1,0) -> Saraf and Partners | AD165: Dharma Law Partners | AE165: =VLOOKUP(AD165,AA:AA,1,0) -> Dharma Law Partners
U166: Priyanshi Kholia | V166: =VLOOKUP(U166,X:X,1,0) -> Priyanshi Kholia | X166: Sarthak Advocates & Solicitors | Y166: =VLOOKUP(X166,AA:AA,1,0) -> Sarthak Advocates & Solicitors | AA166: Chirag shah, Advocate | AB166: =VLOOKUP(AA166,AD:AD,1,0) -> Chirag shah, Advocate | AD166: Kevic Setalvad | AE166: =VLOOKUP(AD166,AA:AA,1,0) -> Kevic Setalvad
U167: Khaitan Legal Associates | V167: =VLOOKUP(U167,X:X,1,0) -> Khaitan Legal Associates | X167: Saswat Mohanty | Y167: =VLOOKUP(X167,AA:AA,1,0) -> Saswat Mohanty | AA167: Vidhii Partners | AB167: =VLOOKUP(AA167,AD:AD,1,0) -> Vidhii Partners | AD167: Giriraj Subramanium | AE167: =VLOOKUP(AD167,AA:AA,1,0) -> Giriraj Subramanium
U168: Rithin Rai | V168: =VLOOKUP(U168,X:X,1,0) -> Rithin Rai | X168: Saurabh Prakash | Y168: =VLOOKUP(X168,AA:AA,1,0) -> Saurabh Prakash | AA168: Dharma Law Partners | AB168: =VLOOKUP(AA168,AD:AD,1,0) -> Dharma Law Partners | AD168: Phoenix Legal | AE168: =VLOOKUP(AD168,AA:AA,1,0) -> Phoenix Legal
U169: Bishwajit Dubey | V169: =VLOOKUP(U169,X:X,1,0) -> Bishwajit Dubey | X169: Shashwat Bajpai | Y169: =VLOOKUP(X169,AA:AA,1,0) -> Shashwat Bajpai | AA169: Kevic Setalvad | AB169: =VLOOKUP(AA169,AD:AD,1,0) -> Kevic Setalvad | AD169: Malak Bhatt | AE169: =VLOOKUP(AD169,AA:AA,1,0) -> Malak Bhatt
U170: Krati Gupta | V170: =VLOOKUP(U170,X:X,1,0) -> Krati Gupta | X170: Shiraz Rustomjee | Y170: =VLOOKUP(X170,AA:AA,1,0) -> Shiraz Rustomjee | AA170: Giriraj Subramanium | AB170: =VLOOKUP(AA170,AD:AD,1,0) -> Giriraj Subramanium | AD170: Vikas Mehta | AE170: =VLOOKUP(AD170,AA:AA,1,0) -> Vikas Mehta
U171: S C Sharada & Associates| Company Secretaries | V171: =VLOOKUP(U171,X:X,1,0) -> S C Sharada & Associates| Company Secretaries | X171: Shobit Phutela | Y171: =VLOOKUP(X171,AA:AA,1,0) -> Shobit Phutela | AA171: Phoenix Legal | AB171: =VLOOKUP(AA171,AD:AD,1,0) -> Phoenix Legal | AD171: IRIS LEGAL | AE171: =VLOOKUP(AD171,AA:AA,1,0) -> IRIS LEGAL
...

Sheet Deletions
B1: Coresphere100 Technologies Pvt. Ltd.
B2: List of customer not continiued-Deletions
B4: S.No. | C4: 45658 | D4: 45689 | E4: 45717 | F4: 45748 | G4: 45778 | H4: 45809 | I4: 45839 | J4: 45870 | K4: 45901 | L4: 45931
B5: 1 | C5: Solaris Legal | D5: Tejas Bhide | E5: Chetan Dedhia | F5: Akshat Vachher | G5: Balbir Singh | H5: Bimal Rajasekhar | I5: Touchstone Partners | J5: Vutts & Associates LLP | K5: Ankit Talsania | L5: Vesta Legal
B6: =B5+1 -> 2 | C6: Incanus Technologies Private Limited | D6: Amrita Panda / ADP Chambers- 5 | E6: ANG | G6: Federal & Company | H6: Advocate Rohit Jaiswal | I6: Utkarsh Joshi | J6: AP & Partners, Advocates | K6: ANM Global Inc | L6: Karanjawala & Company Advocates
B7: =B6+1 -> 3 | C7: Chambers of Pujari | D7: Parakram Legal | G7: Akriti Chaubey | H7: Venkatesh Mohanraj | I7: Karan Butalia | J7: Bathiya Legal | K7: Deep Cover Law- Chirag Narasimiah | L7: J.R. LADDHA FINANCIAL SERVICES PRIVATE LIMITED
B8: =B7+1 -> 4 | C8: Talha Abdul Rahman | D8: Kanungo & Co. | G8: GM Legal | H8: Jade Lex Partners | I8: Dua Associates | J8: Manini Brar | K8: Gaurav Mehta | L8: Shreya Desai
B9: =B8+1 -> 5 | D9: Prantar | G9: Prantar | H9: Alankrit Bajpai | I9: Gera Developments Pvt. Ltd. | J9: Centre for Law and Policy Research Trust | K9: Jayakar and Partners | L9: MEESHO LIMITED
B10: =B9+1 -> 6 | G10: Rohit Sharma (lex Merita) | H10: Badar Durrez | I10: MD&T Partners | J10: Sajan Poovayya | K10: Parakram Legal | L10: Consera Legal LLP
B11: =B10+1 -> 7 | G11: Mr Sudhanshu Kumar | H11: Aakash Sharma | I11: Vritti Law Partners | J11: AJNM LAW INDIA LLP | K11: Parinam Law Associates
B12: =B11+1 -> 8 | G12: Santosh Kumar | H12: Saga Legal | I12: Aquilaw | J12: KINJAL CIVILCON LLP | K12: Pradeep Sancheti
B13: =B12+1 -> 9 | G13: NIKHIL DEELIP P | H13: Pranay Chitale | I13: Svarniti Law Offices | J13: DSK Legal | K13: Rajeev K. Virmani
B14: =B13+1 -> 10 | G14: Hiresh Chaudhary | H14: Spark Legal | I14: Khaitan Legal Asscoiates | J14: AMS Legal | K14: Rithin Rai
B15: =B14+1 -> 11 | G15: Victoram Legal / Mr. Sajal Awasthi | H15: Argus Partners | I15: Burgeon Law LLP | J15: ZEUS Law Associates | K15: Stride Legal
B16: =B15+1 -> 12 | H16: Saraf and Partners | J16: Tejeshwar Singh | K16: Vaish Associates
B17: =B16+1 -> 13 | H17: Pioneer Legal | J17: Shrey Lodha | K17: Venkatesh Dhond
B18: =B17+1 -> 14 | H18: Solaris Legal | J18: C&S Partners
B19: =B18+1 -> 15 | H19: Mr. Jehangir Jejeebhoy
B20: =B19+1 -> 16 | H20: Monalisa Kosaria
B21: =B20+1 -> 17 | H21: Yash Momaya
B22: =B21+1 -> 18

Sheet Addition
B1: Coresphere100 Technologies Pvt. Ltd.
B2: List of customer added- Addition
B4: S.No. | C4: 45658 | D4: 45689 | E4: 45717 | F4: 45748 | G4: 45778 | H4: 45809 | I4: 45839 | J4: 45870 | K4: 45901 | L4: 45931
B5: 1 | C5: Agama Law Associates | D5: Abel Tom Benny // Thomas and Thomas Advocates | E5: Akriti Chaubey | F5: Touchstone Partners | G5: NC Legal | H5: Daswani & Daswani | I5: Manini Brar | J5: Akkash Bhadana | K5: ZEUS Law Associates | L5: Pradeep Sancheti
B6: =B5+1 -> 2 | C6: Dipankar Majumdar | D6: Argus Partners | E6: Akshat Vachher | F6: Bimal Rajasekhar | G6: Saraf and Partners | H6: Shri Venkatesh , SKV law offices | I6: ZEUS Law Associates | J6: Amrit Grewal | K6: Saqeb Mahbub | L6: Akshat Vachher
B7: =B6+1 -> 3 | C7: Farhan Dubash | D7: Asahi Legal LLP | E7: Amrita Panda / ADP Chambers- 62 | F7: Veritas Legal Advocates and Solicitors | G7: Dua Associates | H7: Deep Cover Law- Chirag Narasimiah | I7: Apoorv Kurup | J7: Argus Partners | K7: Justice Ravindra Bhat | L7: Shrey Lodha
B8: =B7+1 -> 4 | C8: Gourab Banerji | D8: Chetan Dedhia | E8: Balbir Singh | F8: LEGALOGIC CONSULTING LLP | G8: Sarthak Advocates & Solicitors | H8: NKR Law Offices | I8: Solaris Legal | J8: Bharat Chugh | K8: Gera Developments Pvt. Ltd. | L8: AKS Advocates
B9: =B8+1 -> 5 | C9: Keystone Partners | D9: Darius J. Khambata | E9: Burgeon Law LLP | F9: VACUITAS COUNSELLOR LLP | G9: Gupta Law Associates | H9: Poovayya & CO | I9: Surel Shah | J9: Brijesh Oberoi | K9: MEESHO LIMITED | L9: S Arjun Suresh
B10: =B9+1 -> 6 | C10: Mustafa S Doctor | D10: Eternity Legal | E10: Chambers of Aman Vachher | F10: U. S. GANDHI & CO. | G10: Kunal Kunango | H10: Sajan Poovayya | I10: MG Ramachandran | J10: Chirag shah, Advocate | K10: Consera Legal LLP | L10: Sourish Roy
B11: =B10+1 -> 7 | C11: Naushad Engineer | D11: Monalisa Kosaria | E11: Chambers of Justice Mohit S Shah (Retd.), Former Chief Justice of Bombay and Calcutta High Court | F11: Advocate Rohit Jaiswal | G11: Divyanshu Rai | H11: Vardharma Chambers | I11: Jade Lex Partners | J11: Devina Sehgal | K11: Udai V. S. Rathore | L11: Sarvottam Law Offices
B12: =B11+1 -> 8 | C12: Parakram Legal | D12: Mr. Jehangir Jejeebhoy | E12: Federal & Company | F12: Dileep Poolakkot | G12: Hamza mir | H12: Birendra Saraf | I12: Aanchal Basur | J12: Dharma Law Partners | K12: Yash Momaya | L12: SACH & THARAAS ADVOCATES
B13: =B12+1 -> 9 | C13: Prantar | D13: MV Law Partners | E13: GM Legal | F13: Utkarsh Joshi | G13: Chambers of Ninad Laud | H13: IRIS LEGAL | I13: RUNWAL ENTERPRISES LIMITED | J13: Dhruve Liladhar & Co | K13: MDP Legal | L13: Udyam Law Practice
B14: =B13+1 -> 10 | C14: Saswat Mohanty | D14: MZM Legal LLP | E14: Harshit Malik | F14: Karan Butalia | G14: Gera Developments Pvt. Ltd. | H14: JYOT-A Public Trust | I14: ANM Global Inc | J14: Foresight Law Offices | K14: RRG & Associates | L14: Pioneer Legal
B15: =B14+1 -> 11 | C15: Shiraz Rustomjee | D15: Prompt Legal (Shared by Jayanth) | E15: Innovatus Law | F15: RAJANI ASSOCIATES | G15: Gaurav Mehta | H15: Yakshay Chheda | I15: Vikas Mehta | J15: Gaurav Gupta | K15: Dhru & Co | L15: Lzafeer Ahmad B F
B16: =B15+1 -> 12 | C16: Shyam Kapadia | D16: Sanjay Udeshi & Co. | E16: Justice (Retd.) AK Sikri | F16: PSN Legal Advocates and Legal Consultants | G16: MD&T Partners | H16: Tipping Mr Pink Private Limited | I16: Swapnil Wagh | J16: Giriraj Subramanium | K16: Hiren Kamod | L16: Puneet Rathsharma
B17: =B16+1 -> 13 | C17: Tejas Bhide | D17: Vesta Legal | E17: Justice (Retd.) Kurian Joseph | F17: Swapna Sheshadri | G17: Kachwaha & Partners | H17: KUAJ LEGAL | I17: Arpit Gupta | J17: J.R. LADDHA FINANCIAL SERVICES PRIVATE LIMITED | K17: Pravah Law | L17: Aarna Law LLP
B18: =B17+1 -> 14 | C18: Venkatesh Dhond | E18: Megha Chandra | F18: Vutts & Associates LLP | G18: Vishal Kanade | H18: AJNM LAW INDIA LLP | I18: Jayakar and Partners | J18: Jain and Talukdar | K18: AP & Partners, Advocates | L18: Singularity Legal LLP
B19: =B18+1 -> 15 | C19: Victoram Legal / Mr. Sajal Awasthi | E19: Mr Sudhanshu Kumar | F19: Miglani Varma & Co. | G19: Vritti Law Partners | H19: Agraa Legal | I19: Rohan Shah | J19: JSM Law Partners | K19: Ajinkya Kurdukar | L19: Sir Sobha Singh & Sons Pvt Ltd
B20: =B19+1 -> 16 | E20: NIKHIL DEELIP P | F20: Venkatesh Mohanraj | G20: C&S Partners | H20: KINJAL CIVILCON LLP | I20: GM Legal | J20: Karthik Sundar | K20: Vijay Manjreka | L20: Laksha Kalappa B
B21: =B20+1 -> 17 | E21: Nora Legal Consultants LLP | F21: Jade Lex Partners | G21: Chambers of Moazzam Khan | H21: Shobit Phutela | I21: Rajeev K. Virmani | J21: KATARIYA CONSULTANCY INDIA LLP | K21: Ankur Mahindro | L21: Vaish Associates
B22: =B21+1 -> 18 | E22: Prantar | F22: Alankrit Bajpai | G22: Vis Legis Law Practice | H22: Narottam Sharma | I22: Vaish Associates | J22: Kevic Setalvad | K22: Pragati Law Chambers | L22: NINE PILLARS INFRATECH LLP
B23: =B22+1 -> 19 | E23: Rohit Sharma (lex Merita) | F23: Badar Durrez | G23: Phoenix Legal | H23: Rahul Saboo, Advocate | I23: Acuity Law LLP | J23: KRISH HOMES | K23: KK & Co | L23: Dr Sanjay Jain
B24: =B23+1 -> 20 | E24: Santosh Kumar | F24: Rashmikant and Partners | G24: Nikhil Pai | H24: DSK Legal | I24: Trust Law | J24: Kushagra Shah | K24: Aditya Narayan Mahajan | L24: Arun Kumar P
B25: =B24+1 -> 21 | E25: SK Singhi and Partners | F25: TLH, Advocates & Solicitors | G25: J INFRATECH LIMITED | H25: Meghna Talwar | I25: Priyanshi Kholia | J25: Malak Bhatt | K25: Prateek Rath | L25: Ahan Gadkari
B26: =B25+1 -> 22 | E26: Solaris Legal | F26: Shreeyash Lalit | G26: Vyom Shah | H26: S Priya | I26: Khaitan Legal Associates | J26: Mukul Sharma and Company | K26: OASIS REALTY | L26: ASREC India Ltd
B27: =B26+1 -> 23 | E27: Wadia Ghandy & Co. | F27: Dewani Associates | G27: Zubin Behramkamdin | H27: Joy Baxi & Associates | I27: Bishwajit Dubey | J27: Parul Sharma | K27: Jehangir Jeejeebhoy | L27: Chavi V Jain
B28: =B27+1 -> 24 | E28: Yash Momaya | F28: R. Vishnu Kumar, Advocate | G28: Jennifer Michael | H28: Ganesh & Co. | I28: Krati Gupta | J28: Pranav Badheka | K28: Samar Bansal | L28: Mahadeshwara. D
B29: =B28+1 -> 25 | F29: Chetan Dedhia | G29: SomÂ Sinha & Associates | H29: AMS Legal | I29: S C Sharada & Associates| Company Secretaries | J29: Reliance Corporate Advisors (R) | K29: Law office of Amrita Sarkar | L29: Pramit Mohanty
B30: =B29+1 -> 26 | F30: Aakash Sharma | G30: Stride Legal | H30: Gauri Puri | I30: Hamsaanandini Nanduri | J30: SAGA LEGAL | K30: Ankita Sharma | L30: Manaswi Agrawal
B31: =B30+1 -> 27 | F31: Saga Legal | G31: Rithin Rai | H31: Amit Bhagat | I31: Monalisa Kosaria | J31: Saraf and Partners | K31: Mihir Desai | L31: Parekh Legal Proprieter Ami Parekh
B32: =B31+1 -> 28 | F32: RPV LEGAL | G32: Meghav Gupta | H32: Sundeep Karnik | I32: Krishnan Venugopal | J32: Shreya Desai | K32: Kunal Vaishnav | L32: AKS LAW ASSOCIATES
B33: =B32+1 -> 29 | F33: AP & Partners, Advocates | G33: Shashwat Bajpai | H33: Rohan Talwar | I33: GC Legal | J33: Svarniti Law Offices | K33: Rajdeep Panda | L33: Aravindakshan Nair
B34: =B33+1 -> 30 | F34: Pranay Chitale | G34: Nitish Raj | H34: Aurtus Consulting LLP | I34: Anush Raajan | J34: Talha Abdul Rahman | K34: Hammurabi & Solomon Partner | L34: Nyayosh Bharucha
B35: =B34+1 -> 31 | F35: Spark Legal | G35: Aquilaw | H35: Tejeshwar Singh | I35: Philips India Limited | J35: Touchstone Partners | K35: Prerit Goyal | L35: Sahil Singh
B36: =B35+1 -> 32 | F36: Bathiya Legal | G36: Svarniti Law Offices | H36: Elixir Legal Services | I36: Nayana Tara BG | J36: TREELIFE VENTURES SERVICES PRIVATE LIMITED | K36: Shamik Sanjanwala | L36: Mohammed Moin
B37: =B36+1 -> 33 | F37: SINHA & COMPANY | G37: Khaitan Legal Asscoiates | I37: PSP Legal | J37: TRILOK POWER AND CABLES PRIVATE LIMITED | K37: Adarsh Ramakrishnan | L37: Amicus Lex & Associates
B38: =B37+1 -> 34 | F38: Darshit Jain | G38: Samya Law Chambers | I38: Vivek Anand Anthony Britto | J38: Tuli & Co. | K38: Aditya S Puar | L38: Arvind Menon
B39: =B38+1 -> 35 | F39: Sagar Ghogre | G39: Parakram Legal | I39: Parinam Law Associates | J39: Tushar Jarwal | K39: Debopriyo Moulik | L39: Kaizen Law
B40: =B39+1 -> 36 | F40: Chetan shah | G40: IndusLaw | I40: Roshan Santhalia | J40: Ujjwal Sharma | K40: REMFRY & SAGAR CONSULTANT PVT LTD | L40: Vrinda Taneja
B41: =B40+1 -> 37 | F41: Sneha Phene | G41: Shrey Lodha | I41: RHP Partners | J41: Vidhii Partners | K41: Anirban Bhattacharya | L41: Precinct Legal
B42: =B41+1 -> 38 | F42: Gunjan Mangla | I42: Ankit Talsania | J42: Virmani & Virmani | K42: Jayant Mehta | L42: Major Nirvikar Singh (Retd.)
B43: =B42+1 -> 39 | F43: Zulfiqar Jariwala | I43: ASV Legal LLP | K43: Rohit Sharma | L43: Sandip Agarwal and Co.
B44: =B43+1 -> 40 | F44: Manjari Shah | I44: Tarun G Reddy | L44: Vinayak Sharma
B45: =B44+1 -> 41 | F45: Sagar Sheth | I45: Karanjawala & Company Advocates | L45: Lighthouse Legal
B46: =B45+1 -> 42 | F46: Mahek Bookwala | I46: Clavius Legal | L46: AL- Fanar Closed Joint Stock Company
B47: =B46+1 -> 43 | F47: Pradeep Sancheti | I47: Krishna Dev Jagarlamudi | L47: Diya Kapur
B48: =B47+1 -> 44 | F48: AHUJA VALECHA & ASSOCIATES LLP | I48: Gaurav Ray, Advocate on Record | L48: Optimus Legal
B49: =B48+1 -> 45 | F49: ICL CORPORATE ADVISORY PRIVATE LIMITED | I49: R. Ginodia & Co. LLP | L49: Vidhittas Legal
B50: =B49+1 -> 46 | F50: Pratik Patnaik | I50: Saurabh Prakash | L50: Solicitors India Law Offices
B51: =B50+1 -> 47 | F51: Centre for Law and Policy Research Trust | I51: Ecclesia Advocates and Solicitors | L51: Jani & Parikh, Advocates and Solicitors
B52: =B51+1 -> 48 | F52: SKR & associates | I52: Jaiveer Shergil | L52: Siddhant Makkar
B53: =B52+1 -> 49 | F53: Srivastava & Company | L53: Astik Vaid
B54: =B53+1 -> 50 | F54: Piyush Raheja
B55: =B54+1 -> 51 | F55: ⁠Feroze Patel
B56: =B55+1 -> 52 | F56: Kazan Shroff
B57: =B56+1 -> 53 | F57: Kajol Punjabi
B58: =B57+1 -> 54 | F58: Neeta Jain
B59: =B58+1 -> 55 | F59: Amrut Joshi
B60: =B59+1 -> 56 | F60: Gaurav Joshi
B61: =B60+1 -> 57 | F61: Kamaljeet Singh
B62: =B61+1 -> 58 | F62: Pioneer Legal
B63: =B62+1 -> 59 | F63: Zoheb Hossain
B64: =B63+1 -> 60 | F64: Mr Rohit Gupta
B65: =B64+1 -> 61 | F65: Hiresh Chaudhary

Sheet Invoice
A1: Invoice Date | B1: Invoice ID | C1: Invoice Number | D1: Invoice Status | E1: Customer ID | F1: Customer Name | G1: Place of Supply | H1: Place of Supply(With State Code) | I1: GST Treatment | J1: Is Inclusive Tax | K1: Due Date | L1: PurchaseOrder | M1: Currency Code | N1: Exchange Rate | O1: Discount Type | P1: Is Discount Before Tax | Q1: Template Name | R1: Entity Discount Percent | S1: TCS Tax Name | T1: TCS Percentage | U1: TDS Calculation Type | V1: TDS Name | W1: TDS Percentage | X1: TDS Section Code | Y1: TDS Section | Z1: TDS Amount | AA1: SubTotal | AB1: Total | AC1: Balance | AD1: Adjustment | AE1: Adjustment Description | AF1: Expected Payment Date | AG1: Last Payment Date | AH1: Payment Terms | AI1: Payment Terms Label | AJ1: Notes | AK1: Terms & Conditions | AL1: E-WayBill Number | AM1: E-WayBill Generated Time | AN1: E-WayBill Status | AO1: E-WayBill Cancelled Time | AP1: E-WayBill Expired Time | AQ1: Transporter Name | AR1: Transporter ID | AS1: TCS Amount | AT1: Invoice Type | AU1: Entity Discount Amount | AV1: Shipping Charge | AW1: Shipping Charge Tax ID | AX1: Shipping Charge Tax Amount | AY1: Shipping Charge Tax Name | AZ1: Shipping Charge Tax % | BA1: Shipping Charge Tax Type | BB1: Shipping Charge Tax Exemption Code | BC1: Shipping Charge SAC Code | BD1: Item Name | BE1: Item Desc | BF1: Quantity | BG1: Discount | BH1: Discount Amount | BI1: Item Total | BJ1: Usage unit | BK1: Item Price | BL1: Product ID | BM1: Brand | BN1: Sales Order Number | BO1: Expense Reference ID | BP1: Recurrence Name | BQ1: Billing Attention | BR1: Billing Address | BS1: Billing Street2 | BT1: Billing City | BU1: Billing State | BV1: Billing Country | BW1: Billing Code | BX1: Billing Phone | BY1: Billing Fax | BZ1: Shipping Attention | CA1: Shipping Address | CB1: Shipping Street2 | CC1: Shipping City | CD1: Shipping State | CE1: Shipping Country | CF1: Shipping Code | CG1: Shipping Fax | CH1: Shipping Phone Number | CI1: Supplier Org Name | CJ1: Supplier GST Registration Number | CK1: Supplier Street Address | CL1: Supplier City | CM1: Supplier State | CN1: Supplier Country | CO1: Supplier ZipCode | CP1: Supplier Phone | CQ1: Supplier E-Mail | CR1: CGST Rate % | CS1: SGST Rate % | CT1: IGST Rate % | CU1: CESS Rate % | CV1: CGST(FCY) | CW1: SGST(FCY) | CX1: IGST(FCY) | CY1: CESS(FCY) | CZ1: CGST | DA1: SGST | DB1: IGST | DC1: CESS | DD1: Reverse Charge Tax Name | DE1: Reverse Charge Tax Rate | DF1: Reverse Charge Tax Type | DG1: Item TDS Name | DH1: Item TDS Percentage | DI1: Item TDS Amount | DJ1: Item TDS Section Code | DK1: Item TDS Section | DL1: GST Identification Number (GSTIN) | DM1: Nature Of Collection | DN1: Project ID | DO1: Project Name | DP1: HSN/SAC | DQ1: Round Off | DR1: Sales person | DS1: Subject | DT1: Primary Contact EmailID | DU1: Primary Contact Mobile | DV1: Primary Contact Phone | DW1: Estimate Number | DX1: Item Type | DY1: Custom Charges | DZ1: Shipping Bill# | EA1: Shipping Bill Date | EB1: Shipping Bill Total | EC1: PortCode | ED1: Reference Invoice# | EE1: Reference Invoice Date | EF1: Reference Invoice Type | EG1: GST Registration Number(Reference Invoice) | EH1: Reason for issuing Debit Note | EI1: E-Commerce Operator Name | EJ1: E-Commerce Operator GSTIN | EK1: Account | EL1: Account Code | EM1: Supply Type | EN1: Tax ID | EO1: Item Tax | EP1: Item Tax % | EQ1: Item Tax Amount | ER1: Item Tax Type | ES1: Item Tax Exemption Reason | ET1: Kit Combo Item Name
A2: 45748 | B2: 2297152000000050064 | C2: INV-25-26-000001 | D2: Closed | E2: 2297152000000050001 | F2: Touchstone Partners | G2: DL | H2: 07-Delhi | I2: business_none | J2: false | K2: 45748 | M2: INR | N2: 1 | O2: item_level | P2: true | Q2: Tax Invoice | R2: 0.00 | U2: entity_level | V2: Technical Fees (2%) | W2: 2.00 | X2: 194J | Y2: Section 194 J | Z2: 1200.000 | AA2: 60000 | AB2: =69600 -> 69600 | AC2: 0 | AD2: 0 | AE2: Adjustment | AG2: 45749 | AH2: 0 | AI2: Due On Receipt | AJ2: Thanks for your business. | AT2: Invoice | AU2: 0.0 | AV2: 0 | BD2: Jurisphere Enterprise Subscription | BE2: License Period- 1st Apr to 30th June25 Description- 10 licenses for 3 months, at Rs. 2000 each month per license | BF2: 3 | BG2: 0.00 | BH2: 0.00 | BI2: 60000 | BJ2: pcs | BK2: 20000 | BL2: 2297152000000039748 | BR2: 2nd Floor, Block E, The MIRA Plot 1 & 2, | BS2: Ishwar Nagar, Mathura Road, | BT2: New Delhi | BU2: Delhi | BV2: India | BW2: 110065 | CA2: 2nd Floor, Block E, The MIRA Plot 1 & 2, | CB2: Ishwar Nagar, Mathura Road, | CC2: New Delhi | CD2: Delhi | CE2: India | CF2: 110065 | CI2: Coresphere100 Technologies Pvt. Ltd. | CJ2: 09AALCC7037K1Z7 | CK2: 16026, 16th Floor, Tower Oakwood, | CL2: Greater Noida, | CM2: Uttar Pradesh | CN2: India | CO2: 201306 | CP2: 8928163657 | CQ2: manas@jurisphere.ai | CR2: 0.00 | CS2: 0.00 | CT2: 18.00 | CU2: 0.00 | CV2: 0.00 | CW2: 0.00 | CX2: 10800.00 | CY2: 0.00 | CZ2: 0.00 | DA2: 0.00 | DB2: 10800.00 | DC2: 0.00 | DP2: 998313 | DQ2: 0 | DX2: service | EH2: Others | EK2: Sales | EM2: Taxable | EN2: 2297152000000031111 | EO2: IGST18 | EP2: 18.00 | EQ2: 10800 | ER2: ItemAmount
A3: 45748 | B3: 2297152000000050138 | C3: INV-25-26-000002 | D3: Closed | E3: 2297152000000050113 | F3: Bimal Rajasekhar | G3: MH | H3: 27-Maharashtra | I3: business_none | J3: false | K3: 45748 | M3: INR | N3: 1 | O3: item_level | P3: true | Q3: Tax Invoice | R3: 0.00 | U3: item_level | W3: 0.00 | Z3: 0.000 | AA3: 30000 | AB3: 35400 | AC3: 0 | AD3: 0 | AE3: Adjustment | AG3: 45749 | AH3: 0 | AI3: Due On Receipt | AJ3: Thanks for your business. | AK3: 1. FLEXIBLE CANCELLATION, WITH PRO-RATED REFUND 2. ALL UPCOMING FEATURES WILL BE INCLUDED IN THE SUBSCRIPTION | AT3: Invoice | AU3: 0.0 | AV3: 0 | BD3: Jurisphere Enterprise Subscription | BE3: Period - 1st Apr 25 to 31st May 25 Description- Pilot Access of 5 licenses for 2 months of Rs.15000 per month | BF3: 2 | BG3: 0.00 | BH3: 0.00 | BI3: 30000 | BJ3: pcs | BK3: 15000 | BL3: 2297152000000039748 | CI3: Coresphere100 Technologies Pvt. Ltd. | CJ3: 09AALCC7037K1Z7 | CK3: 16026, 16th Floor, Tower Oakwood, | CL3: Greater Noida, | CM3: Uttar Pradesh | CN3: India | CO3: 201306 | CP3: 8928163657 | CQ3: manas@jurisphere.ai | CR3: 0.00 | CS3: 0.00 | CT3: 18.00 | CU3: 0.00 | CV3: 0.00 | CW3: 0.00 | CX3: 5400.00 | CY3: 0.00 | CZ3: 0.00 | DA3: 0.00 | DB3: 5400.00 | DC3: 0.00 | DI3: 0.000 | DP3: 998313 | DQ3: 0 | DX3: service | EH3: Others | EK3: Sales | EM3: Taxable | EN3: 2297152000000031111 | EO3: IGST18 | EP3: 18.00 | EQ3: 5400 | ER3: ItemAmount
A4: 45749 | B4: 2297152000000050202 | C4: INV-25-26-000003 | D4: Closed | E4: 2297152000000050184 | F4: Veritas Legal Advocates and Solicitors | G4: MH | H4: 27-Maharashtra | I4: business_registered_composition | J4: false | K4: 45749 | M4: INR | N4: 1 | O4: item_level | P4: true | Q4: Tax Invoice | R4: 0.00 | U4: entity_level | V4: Technical Fees (2%) | W4: 2.00 | X4: 194J | Y4: Section 194 J | Z4: 19872.000 | AA4: 993600 | AB4: 1152576 | AC4: 0 | AD4: 0 | AE4: Adjustment | AG4: 45762 | AH4: 0 | AI4: Due On Receipt | AJ4: Thanks for your business. | AT4: Invoice | AU4: 0.0 | AV4: 0 | BD4: Jurisphere Enterprise Subscription | BE4: Duration - 6 months Subscriptions Description- 46 licenses of Rs. 4000 per month per license | BF4: 46 | BG4: 10.00 | BH4: 110400.000 | BI4: 993600 | BJ4: pcs | BK4: 24000 | BL4: 2297152000000039748 | BQ4: Tushar Raut | BR4: 1st Floor, Veritas Legal, Forbes Building, | BS4: Charanjit Rai Marg, Azad Maidan, Fort, | BT4: Mumbai | BU4: Maharashtra | BV4: India | BW4: 400001 | BX4: +91-22-43686700 | BZ4: Tushar Raut | CA4: 1st Floor, Veritas Legal, Forbes Building, | CB4: Charanjit Rai Marg, Azad Maidan, Fort, | CC4: Mumbai | CD4: Maharashtra | CE4: India | CF4: 400001 | CH4: +91-22-43686700 | CI4: Coresphere100 Technologies Pvt. Ltd. | CJ4: 09AALCC7037K1Z7 | CK4: 16026, 16th Floor, Tower Oakwood, | CL4: Greater Noida, | CM4: Uttar Pradesh | CN4: India | CO4: 201306 | CP4: 8928163657 | CQ4: manas@jurisphere.ai | CR4: 0.00 | CS4: 0.00 | CT4: 18.00 | CU4: 0.00 | CV4: 0.00 | CW4: 0.00 | CX4: 178848.00 | CY4: 0.00 | CZ4: 0.00 | DA4: 0.00 | DB4: 178848.00 | DC4: 0.00 | DL4: 27AANFV0524F1Z7 | DP4: 998313 | DQ4: 0 | DT4: tushar.raut@veritaslegal.in | DV4: +91-22-43686700 | DX4: service | EH4: Others | EK4: Sales | EM4: Taxable | EN4: 2297152000000031111 | EO4: IGST18 | EP4: 18.00 | EQ4: 178848 | ER4: ItemAmount
A5: 45749 | B5: 2297152000000051047 | C5: INV-25-26-000004 | D5: Closed | E5: 2297152000000051029 | F5: LEGALOGIC CONSULTING LLP | G5: MH | H5: 27-Maharashtra | I5: business_gst | J5: false | K5: 45749 | M5: INR | N5: 1 | O5: item_level | P5: true | Q5: Tax Invoice | R5: 0.00 | U5: entity_level | V5: Professional Fees | W5: 10.00 | X5: 194J | Y5: Section 194 J | Z5: 3000.000 | AA5: 30000 | AB5: 32400 | AC5: 0 | AD5: 0 | AE5: Adjustment | AG5: 45752 | AH5: 0 | AI5: Due On Receipt | AJ5: Thanks for your business. | AT5: Invoice | AU5: 0.0 | AV5: 0 | BD5: Jurisphere Enterprise Subscription | BE5: Subscription Period : monthly invoice 01 April 2025 to 30 June, 2025 Unlimited Access- Enterprise Tool (for 15 users) | BF5: 1 | BG5: 0.00 | BH5: 0.00 | BI5: 30000 | BJ5: pcs | BK5: 30000 | BL5: 2297152000000039748 | BR5: Unit No.3A, PV House, FP No. 85, | BS5: T.P. Scheme No. 1 55, Damle Road, Erandwane | BT5: Pune | BU5: Maharashtra | BV5: India | BW5: 411004 | CA5: Unit No.3A, PV House, FP No. 85, | CB5: T.P. Scheme No. 1 55, Damle Road, Erandwane | CC5: Pune | CD5: Maharashtra | CE5: India | CF5: 411004 | CI5: Coresphere100 Technologies Pvt. Ltd. | CJ5: 09AALCC7037K1Z7 | CK5: 16026, 16th Floor, Tower Oakwood, | CL5: Greater Noida, | CM5: Uttar Pradesh | CN5: India | CO5: 201306 | CP5: 8928163657 | CQ5: manas@jurisphere.ai | CR5: 0.00 | CS5: 0.00 | CT5: 18.00 | CU5: 0.00 | CV5: 0.00 | CW5: 0.00 | CX5: 5400.00 | CY5: 0.00 | CZ5: 0.00 | DA5: 0.00 | DB5: 5400.00 | DC5: 0.00 | DL5: 27AAFFL6917J1ZZ | DP5: 998313 | DQ5: 0 | DX5: service | EH5: Others | EK5: Sales | EM5: Taxable | EN5: 2297152000000031111 | EO5: IGST18 | EP5: 18.00 | EQ5: 5400 | ER5: ItemAmount
A6: 45750 | B6: 2297152000000051071 | C6: INV-25-26-000005 | D6: Overdue | E6: 2297152000000051011 | F6: VACUITAS COUNSELLOR LLP | G6: WB | H6: 19-West Bengal | I6: business_gst | J6: false | K6: 45750 | M6: INR | N6: 1 | O6: item_level | P6: true | Q6: Tax Invoice | R6: 0.00 | U6: item_level | W6: 0.00 | Z6: 0.000 | AA6: 99000 | AB6: 116820 | AC6: 116820 | AD6: 0 | AE6: Adjustment | AH6: 0 | AI6: Due On Receipt | AJ6: Thanks for your business. | AT6: Invoice | AU6: 0.0 | AV6: 0 | BD6: Jurisphere Enterprise Subscription | BE6: Subscription Period- 1 year Description- Unlimited Tool for 2 logins | BF6: 2 | BG6: 0.00 | BH6: 0.00 | BI6: 99000 | BJ6: pcs | BK6: 49500 | BL6: 2297152000000039748 | BR6: 6, Brabourne Road, | BT6: Kolkata | BU6: West Bengal | BV6: India | BW6: 700001 | CA6: 6, Brabourne Road, | CC6: Kolkata | CD6: West Bengal | CE6: India | CF6: 700001 | CI6: Coresphere100 Technologies Pvt. Ltd. | CJ6: 09AALCC7037K1Z7 | CK6: 16026, 16th Floor, Tower Oakwood, | CL6: Greater Noida, | CM6: Uttar Pradesh | CN6: India | CO6: 201306 | CP6: 8928163657 | CQ6: manas@jurisphere.ai | CR6: 0.00 | CS6: 0.00 | CT6: 18.00 | CU6: 0.00 | CV6: 0.00 | CW6: 0.00 | CX6: 17820.00 | CY6: 0.00 | CZ6: 0.00 | DA6: 0.00 | DB6: 17820.00 | DC6: 0.00 | DI6: 0.000 | DL6: 19AAVFV8769L1ZO | DP6: 998313 | DQ6: 0 | DX6: service | EH6: Others | EK6: Sales | EM6: Taxable | EN6: 2297152000000031111 | EO6: IGST18 | EP6: 18.00 | EQ6: 17820 | ER6: ItemAmount
A7: 45752 | B7: 2297152000000053035 | C7: INV-25-26-000006 | D7: Closed | E7: 2297152000000053017 | F7: Tvashta Law | G7: DL | H7: 07-Delhi | I7: business_none | J7: false | K7: 45752 | M7: INR | N7: 1 | O7: item_level | P7: true | Q7: Tax Invoice | R7: 0.00 | U7: item_level | W7: 0.00 | Z7: 0.000 | AA7: 2000 | AB7: 2360 | AC7: 0 | AD7: 0 | AE7: Adjustment | AG7: 45752 | AH7: 0 | AI7: Due On Receipt | AJ7: Thanks for your business. | AT7: Invoice | AU7: 0.0 | AV7: 0 | BD7: Jurisphere Enterprise Subscription | BE7: Description - 10 credits for MCA of INR 200/credit | BF7: 10 | BG7: 0.00 | BH7: 0.00 | BI7: 2000 | BJ7: pcs | BK7: 200 | BL7: 2297152000000039748 | BR7: C 36 Lower Ground Floor, | BS7: Mayfair Gardens, | BT7: New Delhi | BU7: Delhi | BV7: India | BW7: 110019 | CA7: C 36 Lower Ground Floor, | CB7: Mayfair Gardens, | CC7: New Delhi | CD7: Delhi | CE7: India | CF7: 110019 | CI7: Coresphere100 Technologies Pvt. Ltd. | CJ7: 09AALCC7037K1Z7 | CK7: 16026, 16th Floor, Tower Oakwood, | CL7: Greater Noida, | CM7: Uttar Pradesh | CN7: India | CO7: 201306 | CP7: 8928163657 | CQ7: manas@jurisphere.ai | CR7: 0.00 | CS7: 0.00 | CT7: 18.00 | CU7: 0.00 | CV7: 0.00 | CW7: 0.00 | CX7: 360.00 | CY7: 0.00 | CZ7: 0.00 | DA7: 0.00 | DB7: 360.00 | DC7: 0.00 | DI7: 0.000 | DP7: 998313 | DQ7: 0 | DX7: service | EH7: Others | EK7: Sales | EM7: Taxable | EN7: 2297152000000031111 | EO7: IGST18 | EP7: 18.00 | EQ7: 360 | ER7: ItemAmount
A8: 45754 | B8: 2297152000000054231 | C8: INV-25-26-000007 | D8: Closed | E8: 2297152000000054193 | F8: U. S. GANDHI & CO. | G8: MH | H8: 27-Maharashtra | I8: business_gst | J8: false | K8: 45754 | M8: INR | N8: 1 | O8: item_level | P8: true | Q8: Tax Invoice | R8: 0.00 | U8: item_level | W8: 0.00 | Z8: 0.000 | AA8: 8000 | AB8: 9440 | AC8: 0 | AD8: 0 | AE8: Adjustment | AG8: 45754 | AH8: 0 | AI8: Due On Receipt | AJ8: Thanks for your business. | AT8: Invoice | AU8: 0.0 | AV8: 0 | BD8: Jurisphere Enterprise Subscription | BE8: Description - Unlimited usage of 1 license for 2 months for Rs.4000/month | BF8: 1 | BG8: 0.00 | BH8: 0.00 | BI8: 8000 | BJ8: pcs | BK8: 8000 | BL8: 2297152000000039748 | BR8: 2ND FLOOR, 114, SUNDERVILLA, SV ROAD, | BS8: NEXT TO VIJAY SALES, SANTACRUZ WEST, Mumbai Suburban, | BT8: Mumbai | BU8: Maharashtra | BV8: India | BW8: 400054 | CA8: 2ND FLOOR, 114, SUNDERVILLA, SV ROAD, | CB8: NEXT TO VIJAY SALES, SANTACRUZ WEST, Mumbai Suburban, | CC8: Mumbai | CD8: Maharashtra | CE8: India | CF8: 400054 | CI8: Coresphere100 Technologies Pvt. Ltd. | CJ8: 09AALCC7037K1Z7 | CK8: 16026, 16th Floor, Tower Oakwood, | CL8: Greater Noida, | CM8: Uttar Pradesh | CN8: India | CO8: 201306 | CP8: 8928163657 | CQ8: manas@jurisphere.ai | CR8: 0.00 | CS8: 0.00 | CT8: 18.00 | CU8: 0.00 | CV8: 0.00 | CW8: 0.00 | CX8: 1440.00 | CY8: 0.00 | CZ8: 0.00 | DA8: 0.00 | DB8: 1440.00 | DC8: 0.00 | DI8: 0.000 | DL8: 27AACFU5143J1Z1 | DP8: 998313 | DQ8: 0 | DX8: service | EH8: Others | EK8: Sales | EM8: Taxable | EN8: 2297152000000031111 | EO8: IGST18 | EP8: 18.00 | EQ8: 1440 | ER8: ItemAmount
A9: 45754 | B9: 2297152000000054324 | C9: INV-25-26-000008 | D9: Closed | E9: 2297152000000061001 | F9: B2C | G9: UP | H9: 09-Uttar Pradesh | I9: business_none | J9: false | K9: 45754 | M9: INR | N9: 1 | O9: item_level | P9: true | Q9: Tax Invoice | R9: 0.00 | U9: item_level | W9: 0.00 | Z9: 0.000 | AA9: 12277.12 | AB9: 14487 | AC9: 0 | AD9: 0 | AE9: Adjustment | AG9: 45754 | AH9: 0 | AI9: Due On Receipt | AJ9: Thanks for your business. | AT9: Invoice | AU9: 0.0 | AV9: 0 | BD9: Jurisphere Enterprise Subscription | BE9: Razorpay B2C sales from 1st Apr to 7th Apr 25 | BF9: 1 | BG9: 0.00 | BH9: 0.00 | BI9: 12277.12 | BJ9: pcs | BK9: 12277.12 | BL9: 2297152000000039748 | CI9: Coresphere100 Technologies Pvt. Ltd. | CJ9: 09AALCC7037K1Z7 | CK9: 16026, 16th Floor, Tower Oakwood, | CL9: Greater Noida, | CM9: Uttar Pradesh | CN9: India | CO9: 201306 | CP9: 8928163657 | CQ9: manas@jurisphere.ai | CR9: 9.00 | CS9: 9.00 | CT9: 0.00 | CU9: 0.00 | CV9: 1104.94 | CW9: 1104.94 | CX9: 0.00 | CY9: 0.00 | CZ9: 1104.94 | DA9: 1104.94 | DB9: 0.00 | DC9: 0.00 | DI9: 0.000 | DP9: 998313 | DQ9: 0 | DX9: service | EH9: Others | EK9: Sales | EM9: Taxable | EN9: 2297152000000031213 | EO9: GST18 | EP9: 18.00 | EQ9: 2209.88 | ER9: Tax Group
